Workbook
Name covariates: covariates!$A$1:$H$124
Name full_text_screening: 'screening 1.0'!$E$2:$E$101
Name study: 'screening 1.0'!$D$2:$D$101
Name subgroups: 'screening 1.0'!$C$2:$C$101
Name outcomes: 'screening 1.0'!$F$2:$F$101
Name ID: LAMBDA(id, range, IFERROR(ARRAYFORMULA(IF(range<>"",ROW(ID)-1,"")),""))
Name P_SD: LAMBDA(n, k, (((k+0.5)/(n+0.5))/((1-(k+0.5)/(n+0.5)))*SQRT(n)))
Name QUOTES: LAMBDA(string, text, string&text&string)
Name COMBINE_SD: LAMBDA(n_1, n_2, sd_1, sd_2, m_1, m_2, SQRT((((n_1-1)*(sd_1^2))+((n_2-1)*(sd_2^2))+((n_1*n_2)/(n_1+n_2))*((m_1^2)+(m_2^2)-(2*m_1*m_2)))/((n_1+n_2-1))))
Name MEDIAN_MEAN: LAMBDA(n, a, m, b, (4/(4+n^0.75))*((a+b)/2)+(n^0.75/(4+n^0.75))*m)
Name REFERENCE_LINK: LAMBDA(id, doi, HYPERLINK("https://doi.org/"&doi,id))
Name FUNCTION4: LAMBDA(range3, range4, range5, BYROW(range5, LAMBDA(sym, TEXTJOIN(", ", TRUE, FILTER(range3, range4 = sym)))))
Name CI_SD: LAMBDA(n, ci_ul, ci_ll, ((ci_ul-ci_ll)/3.92)*(SQRT(n)))
Name PLNUSD: LAMBDA(pln, if(pln<>"",GOOGLEFINANCE("PLNUSD")*pln,""))
Name USDPLN: LAMBDA(usd, if(usd<>"",GOOGLEFINANCE("USDPLN")*usd,""))
Name MANY_TO_MANY: LAMBDA(range5, range1, range2, IFERROR(BYROW(range5, LAMBDA(sym, TEXTJOIN(", ", TRUE, FILTER(FUNCTION1(range1,range2), FUNCTION2(range1,range2) = sym)))),""))
Name NUM_AUTHORS: LAMBDA(authors, nondelimiters, delimiter, IFARRAY(counta(split(regexreplace(authors,"["&nondelimiters&"]",""),delimiter&" ",false))))
Name FUNCTION3: LAMBDA(range4, iferror(unique(range4),""))
Name IFARRAY: LAMBDA(formula, iferror(arrayformula(formula),""))
Name RANGE_SD: LAMBDA(n, a, b, round(((b-a)/(2*NORM.S.INV((n-0.375)/(n+0.25)))),3))
Name BOOLEAN: LAMBDA(quotes, string, field, operator, IFERROR(ARRAYFORMULA(quotes&string&quotes&"["&field&"]"&" "&operator&" "),""))
Name DENORM: LAMBDA(junction_table, id_column, BYROW(id_column, LAMBDA(column, TEXTJOIN(", ", TRUE, FILTER(junction_table = column)))))

Sheet master
A1: id | B1: study | C1: id | D1: subgroup | E1: outcome | F1: data_type | G1: n | H1: mean | I1: sd | J1: age | K1: male | L1: female | M1: follow_up
A2: 6 | B2: =HYPERLINK("https://github.com/d-wkim/phd/blob/main/data/pdf/anz_2023.pdf","Anz et al., 2023") -> Anz et al., 2023 | C2: 6 | D2: BPTB | E2: graft rupture | F2: dichotomous | G2: 8 | H2: 0 | I2: =iferror(P_SD(G2,H2),"") -> 0.1767767 | J2: =VLOOKUP($A2,covariates!$A$3:$Z$1126,6,false) | K2: =VLOOKUP($A2,covariates!$A$3:$H$1126,5,false) -> at surgery | L2: =VLOOKUP($A2,covariates!$A$3:$H$1126,5,false) -> at surgery | M2: =VLOOKUP($A2,covariates!$A$3:$H$1126,5,false) -> at surgery
A3: 6 | B3: =HYPERLINK("https://github.com/d-wkim/phd/blob/main/data/pdf/anz_2023.pdf","Anz et al., 2023") -> Anz et al., 2023 | C3: 6 | D3: HT | E3: graft rupture | F3: dichotomous | G3: 8 | H3: 0 | I3: =iferror(P_SD(G3,H3),"") -> 0.1767767 | J3: =VLOOKUP($A3,covariates!$A$3:$H$1126,5,false) -> at surgery | L3: =VLOOKUP($A3,covariates!$A$3:$H$1126,6,false) | M3: =VLOOKUP($A3,covariates!$A$3:$H$1126,6,false)
A4: 43 | B4: =HYPERLINK("https://github.com/d-wkim/phd/blob/main/data/pdf/kautzner_2015.pdf","Kautzner et al., 2015") -> Kautzner et al., 2015 | C4: 43 | D4: BPTB | E4: graft rupture | F4: dichotomous | G4: 74 | H4: 0 | I4: =iferror(P_SD(G4,H4),"") -> 0.058123819 | J4: =VLOOKUP($A4,covariates!$A$3:$H$1126,5,false) -> at surgery | L4: =VLOOKUP($A4,covariates!$A$3:$H$1126,6,false) | M4: =VLOOKUP($A4,covariates!$A$3:$H$1126,6,false)
A5: 43 | B5: =HYPERLINK("https://github.com/d-wkim/phd/blob/main/data/pdf/kautzner_2015.pdf","Kautzner et al., 2015") -> Kautzner et al., 2015 | C5: 43 | D5: HT | E5: graft rupture | F5: dichotomous | G5: 73 | H5: 2 | I5: =iferror(P_SD(G5,H5),"") -> 0.3008452 | J5: =VLOOKUP($A5,covariates!$A$3:$H$1126,5,false) -> at surgery | L5: =VLOOKUP($A5,covariates!$A$3:$H$1126,6,false) | M5: =VLOOKUP($A5,covariates!$A$3:$H$1126,6,false)
A6: 49 | B6: =HYPERLINK("https://github.com/d-wkim/phd/blob/main/data/pdf/laxdal_2005.pdf","Laxdal et al., 2005") -> Laxdal et al., 2005 | C6: 49 | D6: BPTB | E6: graft rupture | F6: dichotomous | G6: 40 | H6: 1 | I6: =iferror(P_SD(G6,H6),"") -> 0.24325213 | J6: =VLOOKUP($A6,covariates!$A$3:$H$1126,5,false) -> at surgery | L6: =VLOOKUP($A6,covariates!$A$3:$H$1126,6,false) | M6: =VLOOKUP($A6,covariates!$A$3:$H$1126,6,false)
A7: 49 | B7: =HYPERLINK("https://github.com/d-wkim/phd/blob/main/data/pdf/laxdal_2005.pdf","Laxdal et al., 2005") -> Laxdal et al., 2005 | C7: 49 | D7: HT | E7: graft rupture | F7: dichotomous | G7: 78 | H7: 2 | I7: 0.42059596 | J7: =VLOOKUP($A7,covariates!$A$3:$H$1126,5,false) -> at surgery | L7: =VLOOKUP($A7,covariates!$A$3:$H$1126,6,false) | M7: =VLOOKUP($A7,covariates!$A$3:$H$1126,6,false)
A8: 54 | B8: =HYPERLINK("https://github.com/d-wkim/phd/blob/main/data/pdf/lucidi_2025.pdf","Lucidi et al., 2025") -> Lucidi et al., 2025 | C8: 54 | D8: BPTB | E8: graft rupture | F8: dichotomous | G8: 19 | H8: 7 | I8: =iferror(P_SD(G8,H8),"") -> 2.7243118 | J8: =VLOOKUP($A8,covariates!$A$3:$H$1126,5,false) -> at surgery | L8: =VLOOKUP($A8,covariates!$A$3:$H$1126,6,false) | M8: =VLOOKUP($A8,covariates!$A$3:$H$1126,6,false)
A9: 54 | B9: =HYPERLINK("https://github.com/d-wkim/phd/blob/main/data/pdf/lucidi_2025.pdf","Lucidi et al., 2025") -> Lucidi et al., 2025 | C9: 54 | D9: HT | E9: graft rupture | F9: dichotomous | G9: 20 | H9: 3 | I9: =iferror(P_SD(G9,H9),"") -> 0.92073387 | J9: =VLOOKUP($A9,covariates!$A$3:$H$1126,5,false) -> at surgery | L9: =VLOOKUP($A9,covariates!$A$3:$H$1126,6,false) | M9: =VLOOKUP($A9,covariates!$A$3:$H$1126,6,false)
A10: 66 | B10: =HYPERLINK("https://github.com/d-wkim/phd/blob/main/data/pdf/mohtadi_2016a.pdf","Mohtadi et al., 2016") -> Mohtadi et al., 2016 | C10: 66 | D10: BPTB | E10: graft rupture | F10: dichotomous | G10: 110 | H10: 19 | I10: =iferror(P_SD(G10,H10),"") -> 2.2474475 | J10: =VLOOKUP($A10,covariates!$A$3:$H$1126,5,false) -> at surgery | L10: =VLOOKUP($A10,covariates!$A$3:$H$1126,6,false) | M10: =VLOOKUP($A10,covariates!$A$3:$H$1126,6,false)
A11: 66 | B11: =HYPERLINK("https://github.com/d-wkim/phd/blob/main/data/pdf/mohtadi_2016a.pdf","Mohtadi et al., 2016") -> Mohtadi et al., 2016 | C11: 66 | D11: HT | E11: graft rupture | F11: dichotomous | G11: 110 | H11: 24 | I11: =iferror(P_SD(G11,H11),"") -> 2.9878857 | J11: =VLOOKUP($A11,covariates!$A$3:$H$1126,5,false) -> at surgery | L11: =VLOOKUP($A11,covariates!$A$3:$H$1126,6,false) | M11: =VLOOKUP($A11,covariates!$A$3:$H$1126,6,false)
A12: 76 | B12: =HYPERLINK("https://github.com/d-wkim/phd/blob/main/data/pdf/pinczewski_2007.pdf","Pinczewski et al., 2007") -> Pinczewski et al., 2007 | C12: 76 | D12: BPTB | E12: graft rupture | F12: dichotomous | G12: 90 | H12: 7 | I12: =iferror(P_SD(G12,H12),"") -> 0.85724394 | J12: =VLOOKUP($A12,covariates!$A$3:$H$1126,5,false) -> at surgery | L12: =VLOOKUP($A12,covariates!$A$3:$H$1126,6,false) | M12: =VLOOKUP($A12,covariates!$A$3:$H$1126,6,false)
A13: 76 | B13: =HYPERLINK("https://github.com/d-wkim/phd/blob/main/data/pdf/pinczewski_2007.pdf","Pinczewski et al., 2007") -> Pinczewski et al., 2007 | C13: 76 | D13: HT | E13: graft rupture | F13: dichotomous | G13: 90 | H13: 12 | I13: =iferror(P_SD(G13,H13),"") -> 1.5203258 | J13: =VLOOKUP($A13,covariates!$A$3:$H$1126,5,false) -> at surgery | L13: =VLOOKUP($A13,covariates!$A$3:$H$1126,6,false) | M13: =VLOOKUP($A13,covariates!$A$3:$H$1126,6,false)
A14: 77 | B14: =HYPERLINK("https://github.com/d-wkim/phd/blob/main/data/pdf/popovic_2024.pdf","Popovic et al., 2024") -> Popovic et al., 2024 | C14: 77 | D14: BPTB | E14: graft rupture | F14: dichotomous | G14: 38 | H14: 3 | I14: =iferror(P_SD(G14,H14),"") -> 0.6164414 | J14: =VLOOKUP($A14,covariates!$A$3:$H$1126,5,false) -> at surgery | L14: =VLOOKUP($A14,covariates!$A$3:$H$1126,6,false) | M14: =VLOOKUP($A14,covariates!$A$3:$H$1126,6,false)
A15: 77 | B15: =HYPERLINK("https://github.com/d-wkim/phd/blob/main/data/pdf/popovic_2024.pdf","Popovic et al., 2024") -> Popovic et al., 2024 | C15: 77 | D15: HT | E15: graft rupture | F15: dichotomous | G15: 33 | H15: 4 | I15: =iferror(P_SD(G15,H15),"") -> 0.89139765 | J15: =VLOOKUP($A15,covariates!$A$3:$H$1126,5,false) -> at surgery | L15: =VLOOKUP($A15,covariates!$A$3:$H$1126,6,false) | M15: =VLOOKUP($A15,covariates!$A$3:$H$1126,6,false)
A16: 85 | B16: =HYPERLINK("https://github.com/d-wkim/phd/blob/main/data/pdf/smith_2020.pdf","Smith et al., 2020") -> Smith et al., 2020 | C16: 85 | D16: BPTB | E16: graft rupture | F16: dichotomous | G16: 32 | H16: 0 | I16: =iferror(P_SD(G16,H16),"") -> 0.088388348 | J16: =VLOOKUP($A16,covariates!$A$3:$H$1126,5,false) -> at surgery | L16: =VLOOKUP($A16,covariates!$A$3:$H$1126,6,false) | M16: =VLOOKUP($A16,covariates!$A$3:$H$1126,6,false)
A17: 85 | B17: =HYPERLINK("https://github.com/d-wkim/phd/blob/main/data/pdf/smith_2020.pdf","Smith et al., 2020") -> Smith et al., 2020 | C17: 85 | D17: HT | E17: graft rupture | F17: dichotomous | G17: 32 | H17: 2 | I17: =iferror(P_SD(G17,H17),"") -> 0.47140452 | J17: =VLOOKUP($A17,covariates!$A$3:$H$1126,5,false) -> at surgery | L17: =VLOOKUP($A17,covariates!$A$3:$H$1126,6,false) | M17: =VLOOKUP($A17,covariates!$A$3:$H$1126,6,false)
A18: 87 | B18: =HYPERLINK("https://github.com/d-wkim/phd/blob/main/data/pdf/sonnery-cottet_2026.pdf","Sonnery-cottet et al., 2026") -> Sonnery-cottet et al., 2026 | C18: 87 | D18: BPTB | E18: graft rupture | F18: dichotomous | G18: 273 | H18: 12 | I18: =iferror(P_SD(G18,H18),"") -> 0.79131761 | J18: =VLOOKUP($A18,covariates!$A$3:$H$1126,5,false) -> at surgery | L18: =VLOOKUP($A18,covariates!$A$3:$H$1126,6,false) | M18: =VLOOKUP($A18,covariates!$A$3:$H$1126,6,false)
A19: 87 | B19: =HYPERLINK("https://github.com/d-wkim/phd/blob/main/data/pdf/sonnery-cottet_2026.pdf","Sonnery-cottet et al., 2026") -> Sonnery-cottet et al., 2026 | C19: 87 | D19: HT | E19: graft rupture | F19: dichotomous | G19: 283 | H19: 12 | I19: =iferror(P_SD(G19,H19),"") -> 0.77595036 | J19: =VLOOKUP($A19,covariates!$A$3:$H$1126,5,false) -> at surgery | L19: =VLOOKUP($A19,covariates!$A$3:$H$1126,6,false) | M19: =VLOOKUP($A19,covariates!$A$3:$H$1126,6,false)
A20: 90 | B20: =HYPERLINK("https://github.com/d-wkim/phd/blob/main/data/pdf/taylor_2009.pdf","Taylor et al., 2009") -> Taylor et al., 2009 | C20: 90 | D20: BPTB | E20: graft rupture | F20: dichotomous | G20: 32 | H20: 3 | I20: =iferror(P_SD(G20,H20),"") -> 0.68272379 | J20: =VLOOKUP($A20,covariates!$A$3:$H$1126,5,false) -> at surgery | L20: =VLOOKUP($A20,covariates!$A$3:$H$1126,6,false) | M20: =VLOOKUP($A20,covariates!$A$3:$H$1126,6,false)
A21: 90 | B21: =HYPERLINK("https://github.com/d-wkim/phd/blob/main/data/pdf/taylor_2009.pdf","Taylor et al., 2009") -> Taylor et al., 2009 | C21: 90 | D21: HT | E21: graft rupture | F21: dichotomous | G21: 32 | H21: 4 | I21: =iferror(P_SD(G21,H21),"") -> 0.90913729 | J21: =VLOOKUP($A21,covariates!$A$3:$H$1126,5,false) -> at surgery | L21: =VLOOKUP($A21,covariates!$A$3:$H$1126,6,false) | M21: =VLOOKUP($A21,covariates!$A$3:$H$1126,6,false)
A22: 96 | B22: =HYPERLINK("https://github.com/d-wkim/phd/blob/main/data/pdf/wipfler_2011.pdf","Wipfler et al., 2011") -> Wipfler et al., 2011 | C22: 96 | D22: BPTB | E22: graft rupture | F22: dichotomous | G22: 29 | H22: 3 | I22: =iferror(P_SD(G22,H22),"") -> 0.72492603 | J22: =VLOOKUP($A22,covariates!$A$3:$H$1126,5,false) -> at surgery | L22: =VLOOKUP($A22,covariates!$A$3:$H$1126,6,false) | M22: =VLOOKUP($A22,covariates!$A$3:$H$1126,6,false)
A23: 96 | B23: =HYPERLINK("https://github.com/d-wkim/phd/blob/main/data/pdf/wipfler_2011.pdf","Wipfler et al., 2011") -> Wipfler et al., 2011 | C23: 96 | D23: HT | E23: graft rupture | F23: dichotomous | G23: 25 | H23: 3 | I23: =iferror(P_SD(G23,H23),"") -> 0.79545455 | J23: =VLOOKUP($A23,covariates!$A$3:$H$1126,5,false) -> at surgery | L23: =VLOOKUP($A23,covariates!$A$3:$H$1126,6,false) | M23: =VLOOKUP($A23,covariates!$A$3:$H$1126,6,false)
A24: 97 | B24: =HYPERLINK("https://github.com/d-wkim/phd/blob/main/data/pdf/yadav_2025.pdf","Yadav et al., 2025") -> Yadav et al., 2025 | C24: 97 | D24: HT | E24: graft rupture | F24: dichotomous | G24: 36 | H24: 1 | I24: =iferror(P_SD(G24,H24),"") -> 0.25714286 | J24: =VLOOKUP($A24,covariates!$A$3:$H$1126,5,false) -> at surgery | L24: =VLOOKUP($A24,covariates!$A$3:$H$1126,6,false) | M24: =VLOOKUP($A24,covariates!$A$3:$H$1126,6,false)
A25: 97 | B25: =HYPERLINK("https://github.com/d-wkim/phd/blob/main/data/pdf/yadav_2025.pdf","Yadav et al., 2025") -> Yadav et al., 2025 | C25: 97 | D25: QT | E25: graft rupture | F25: dichotomous | G25: 33 | H25: 0 | I25: =iferror(P_SD(G25,H25),"") -> 0.087038828 | J25: =VLOOKUP($A25,covariates!$A$3:$H$1126,5,false) -> at surgery | L25: =VLOOKUP($A25,covariates!$A$3:$H$1126,6,false) | M25: =VLOOKUP($A25,covariates!$A$3:$H$1126,6,false)
A26: 10 | B26: =HYPERLINK("https://github.com/d-wkim/phd/blob/main/data/pdf/barié_2020.pdf","Barié et al., 2020") -> Barié et al., 2020 | C26: 10 | D26: BPTB | E26: ikdc_subjective | F26: continuous | G26: 43 | H26: 91 | I26: 7.3 | J26: =VLOOKUP($A26,covariates!$A$3:$H$1126,5,false) -> at surgery | K26: =VLOOKUP($A26,covariates!$A$3:$H$1126,6,false) | L26: =VLOOKUP($A26,covariates!$A$3:$H$1126,7,false) -> 30.6 | M26: =VLOOKUP($A26,covariates!$A$3:$H$1126,8,false) -> 7.5
A27: 10 | B27: =HYPERLINK("https://github.com/d-wkim/phd/blob/main/data/pdf/barié_2020.pdf","Barié et al., 2020") -> Barié et al., 2020 | C27: 10 | D27: QT | E27: ikdc_subjective | F27: continuous | G27: 43 | H27: 92 | I27: 11.5 | J27: =VLOOKUP($A27,covariates!$A$3:$H$1126,5,false) -> at surgery | K27: =VLOOKUP($A27,covariates!$A$3:$H$1126,6,false) | L27: =VLOOKUP($A27,covariates!$A$3:$H$1126,7,false) -> 30.6 | M27: =VLOOKUP($A27,covariates!$A$3:$H$1126,8,false) -> 7.5
A28: 12 | B28: =HYPERLINK("https://github.com/d-wkim/phd/blob/main/data/pdf/bi_2018.pdf","Bi et al., 2018") -> Bi et al., 2018 | C28: 12 | D28: HT | E28: ikdc_subjective | F28: continuous | G28: 62 | H28: 90.4 | I28: 7.1 | J28: =VLOOKUP($A28,covariates!$A$3:$H$1126,5,false) -> at surgery | K28: =VLOOKUP($A28,covariates!$A$3:$H$1126,6,false) | L28: =VLOOKUP($A28,covariates!$A$3:$H$1126,7,false) -> 27.9 | M28: =VLOOKUP($A28,covariates!$A$3:$H$1126,8,false) -> 6.7
A29: 12 | B29: =HYPERLINK("https://github.com/d-wkim/phd/blob/main/data/pdf/bi_2018.pdf","Bi et al., 2018") -> Bi et al., 2018 | C29: 12 | D29: PLT | E29: ikdc_subjective | F29: continuous | G29: 62 | H29: 89.3 | I29: 8.4 | J29: =VLOOKUP($A29,covariates!$A$3:$H$1126,5,false) -> at surgery | K29: =VLOOKUP($A29,covariates!$A$3:$H$1126,6,false) | L29: =VLOOKUP($A29,covariates!$A$3:$H$1126,7,false) -> 27.9 | M29: =VLOOKUP($A29,covariates!$A$3:$H$1126,8,false) -> 6.7
A30: 13 | B30: =HYPERLINK("https://github.com/d-wkim/phd/blob/main/data/pdf/björnsson_2016.pdf","Björnsson et al., 2016") -> Björnsson et al., 2016 | C30: 13 | D30: BPTB | E30: ikdc_subjective | F30: continuous | G30: 61 | H30: 67.3 | I30: 20.8 | J30: =VLOOKUP($A30,covariates!$A$3:$H$1126,5,false) -> at surgery | K30: =VLOOKUP($A30,covariates!$A$3:$H$1126,6,false) | L30: =VLOOKUP($A30,covariates!$A$3:$H$1126,7,false) -> 28.2 | M30: =VLOOKUP($A30,covariates!$A$3:$H$1126,8,false) -> 9.1
A31: 13 | B31: =HYPERLINK("https://github.com/d-wkim/phd/blob/main/data/pdf/björnsson_2016.pdf","Björnsson et al., 2016") -> Björnsson et al., 2016 | C31: 13 | D31: HT | E31: ikdc_subjective | F31: continuous | G31: 86 | H31: 74 | I31: 18.8 | J31: =VLOOKUP($A31,covariates!$A$3:$H$1126,5,false) -> at surgery | K31: =VLOOKUP($A31,covariates!$A$3:$H$1126,6,false) | L31: =VLOOKUP($A31,covariates!$A$3:$H$1126,7,false) -> 28.2 | M31: =VLOOKUP($A31,covariates!$A$3:$H$1126,8,false) -> 9.1
A32: 14 | B32: =HYPERLINK("https://github.com/d-wkim/phd/blob/main/data/pdf/bottoni_2015.pdf","Bottoni et al., 2015") -> Bottoni et al., 2015 | C32: 14 | D32: HT | E32: ikdc_subjective | F32: continuous | G32: 44 | H32: 79.5 | I32: 24.7 | J32: =VLOOKUP($A32,covariates!$A$3:$H$1126,5,false) -> at surgery | K32: =VLOOKUP($A32,covariates!$A$3:$H$1126,6,false) | L32: =VLOOKUP($A32,covariates!$A$3:$H$1126,7,false) -> 28.9 | M32: =VLOOKUP($A32,covariates!$A$3:$H$1126,8,false) -> 5.8
A33: 14 | B33: =HYPERLINK("https://github.com/d-wkim/phd/blob/main/data/pdf/bottoni_2015.pdf","Bottoni et al., 2015") -> Bottoni et al., 2015 | C33: 14 | D33: TA | E33: ikdc_subjective | F33: continuous | G33: 36 | H33: 81.1 | I33: 23.1 | J33: =VLOOKUP($A33,covariates!$A$3:$H$1126,5,false) -> at surgery | K33: =VLOOKUP($A33,covariates!$A$3:$H$1126,6,false) | L33: =VLOOKUP($A33,covariates!$A$3:$H$1126,7,false) -> 28.9 | M33: =VLOOKUP($A33,covariates!$A$3:$H$1126,8,false) -> 5.8
A34: 18 | B34: =HYPERLINK("https://github.com/d-wkim/phd/blob/main/data/pdf/butt_2024.pdf","Butt et al., 2024") -> Butt et al., 2024 | C34: 18 | D34: HT | E34: ikdc_subjective | F34: continuous | G34: 30 | H34: 89.7 | I34: 5.7 | J34: =VLOOKUP($A34,covariates!$A$3:$H$1126,5,false) -> at surgery | K34: =VLOOKUP($A34,covariates!$A$3:$H$1126,6,false) | L34: =VLOOKUP($A34,covariates!$A$3:$H$1126,7,false) -> 29.17 | M34: =VLOOKUP($A34,covariates!$A$3:$H$1126,8,false) -> 5.03
A35: 18 | B35: =HYPERLINK("https://github.com/d-wkim/phd/blob/main/data/pdf/butt_2024.pdf","Butt et al., 2024") -> Butt et al., 2024 | C35: 18 | D35: PLT | E35: ikdc_subjective | F35: continuous | G35: 30 | H35: 89.9 | I35: 9.8 | J35: =VLOOKUP($A35,covariates!$A$3:$H$1126,5,false) -> at surgery | K35: =VLOOKUP($A35,covariates!$A$3:$H$1126,6,false) | L35: =VLOOKUP($A35,covariates!$A$3:$H$1126,7,false) -> 29.17 | M35: =VLOOKUP($A35,covariates!$A$3:$H$1126,8,false) -> 5.03
A36: 19 | B36: =HYPERLINK("https://github.com/d-wkim/phd/blob/main/data/pdf/calvert_2025.pdf","Calvert et al., 2025") -> Calvert et al., 2025 | C36: 19 | D36: HT | E36: ikdc_subjective | F36: continuous | G36: 92 | H36: 92 | I36: 8 | J36: =VLOOKUP($A36,covariates!$A$3:$H$1126,5,false) -> at surgery | K36: =VLOOKUP($A36,covariates!$A$3:$H$1126,6,false) | L36: =VLOOKUP($A36,covariates!$A$3:$H$1126,7,false) -> 29.4 | M36: =VLOOKUP($A36,covariates!$A$3:$H$1126,8,false) -> 7.7
A37: 19 | B37: =HYPERLINK("https://github.com/d-wkim/phd/blob/main/data/pdf/calvert_2025.pdf","Calvert et al., 2025") -> Calvert et al., 2025 | C37: 19 | D37: QT | E37: ikdc_subjective | F37: continuous | G37: 89 | H37: 89 | I37: 10 | J37: =VLOOKUP($A37,covariates!$A$3:$H$1126,5,false) -> at surgery | K37: =VLOOKUP($A37,covariates!$A$3:$H$1126,6,false) | L37: =VLOOKUP($A37,covariates!$A$3:$H$1126,7,false) -> 29.4 | M37: =VLOOKUP($A37,covariates!$A$3:$H$1126,8,false) -> 7.7
A38: 32 | B38: =HYPERLINK("https://github.com/d-wkim/phd/blob/main/data/pdf/guglielmetti_2021.pdf","Guglielmetti et al., 2021") -> Guglielmetti et al., 2021 | C38: 32 | D38: BPTB | E38: ikdc_subjective | F38: continuous | G38: 31 | H38: 88.75 | I38: 9.27 | J38: =VLOOKUP($A38,covariates!$A$3:$H$1126,5,false) -> at surgery | K38: =VLOOKUP($A38,covariates!$A$3:$H$1126,6,false) | L38: =VLOOKUP($A38,covariates!$A$3:$H$1126,7,false) -> 25.2 | M38: =VLOOKUP($A38,covariates!$A$3:$H$1126,8,false) -> 5.48
A39: 32 | B39: =HYPERLINK("https://github.com/d-wkim/phd/blob/main/data/pdf/guglielmetti_2021.pdf","Guglielmetti et al., 2021") -> Guglielmetti et al., 2021 | C39: 32 | D39: HT | E39: ikdc_subjective | F39: continuous | G39: 31 | H39: 91 | I39: 9.07 | J39: =VLOOKUP($A39,covariates!$A$3:$H$1126,5,false) -> at surgery | K39: =VLOOKUP($A39,covariates!$A$3:$H$1126,6,false) | L39: =VLOOKUP($A39,covariates!$A$3:$H$1126,7,false) -> 25.2 | M39: =VLOOKUP($A39,covariates!$A$3:$H$1126,8,false) -> 5.48
A40: 36 | B40: =HYPERLINK("https://github.com/d-wkim/phd/blob/main/data/pdf/horstmann_2022.pdf","Horstmann et al., 2022") -> Horstmann et al., 2022 | C40: 36 | D40: HT | E40: ikdc_subjective | F40: continuous | G40: 26 | H40: 83.7 | I40: 12.7 | J40: =VLOOKUP($A40,covariates!$A$3:$H$1126,5,false) -> at surgery | K40: =VLOOKUP($A40,covariates!$A$3:$H$1126,6,false) | L40: =VLOOKUP($A40,covariates!$A$3:$H$1126,7,false) -> 32.7 | M40: =VLOOKUP($A40,covariates!$A$3:$H$1126,8,false) -> 11.4
A41: 36 | B41: =HYPERLINK("https://github.com/d-wkim/phd/blob/main/data/pdf/horstmann_2022.pdf","Horstmann et al., 2022") -> Horstmann et al., 2022 | C41: 36 | D41: QT | E41: ikdc_subjective | F41: continuous | G41: 23 | H41: 89.3 | I41: 12.2 | J41: =VLOOKUP($A41,covariates!$A$3:$H$1126,5,false) -> at surgery | K41: =VLOOKUP($A41,covariates!$A$3:$H$1126,6,false) | L41: =VLOOKUP($A41,covariates!$A$3:$H$1126,7,false) -> 32.7 | M41: =VLOOKUP($A41,covariates!$A$3:$H$1126,8,false) -> 11.4
A42: 38 | B42: =HYPERLINK("https://github.com/d-wkim/phd/blob/main/data/pdf/iliopoulos_2017.pdf","Iliopoulos et al., 2017") -> Iliopoulos et al., 2017 | C42: 38 | D42: BPTB | E42: ikdc_subjective | F42: continuous | G42: 45 | H42: 83.2 | I42: 2.8 | J42: =VLOOKUP($A42,covariates!$A$3:$H$1126,5,false) -> at surgery | K42: =VLOOKUP($A42,covariates!$A$3:$H$1126,6,false) | L42: =VLOOKUP($A42,covariates!$A$3:$H$1126,7,false) -> 24.8 | M42: =VLOOKUP($A42,covariates!$A$3:$H$1126,8,false) -> 5
A43: 38 | B43: =HYPERLINK("https://github.com/d-wkim/phd/blob/main/data/pdf/iliopoulos_2017.pdf","Iliopoulos et al., 2017") -> Iliopoulos et al., 2017 | C43: 38 | D43: HT | E43: ikdc_subjective | F43: continuous | G43: 45 | H43: 82.78 | I43: 2.8 | J43: =VLOOKUP($A43,covariates!$A$3:$H$1126,5,false) -> at surgery | K43: =VLOOKUP($A43,covariates!$A$3:$H$1126,6,false) | L43: =VLOOKUP($A43,covariates!$A$3:$H$1126,7,false) -> 24.8 | M43: =VLOOKUP($A43,covariates!$A$3:$H$1126,8,false) -> 5
A44: 44 | B44: =HYPERLINK("https://github.com/d-wkim/phd/blob/main/data/pdf/komzak_2022.pdf","Komzak et al., 2022") -> Komzak et al., 2022 | C44: 44 | D44: BPTB | E44: ikdc_subjective | F44: continuous | G44: 36 | H44: 74.2 | I44: 10.2 | J44: =VLOOKUP($A44,covariates!$A$3:$H$1126,5,false) -> at surgery | K44: =VLOOKUP($A44,covariates!$A$3:$H$1126,6,false) | L44: =VLOOKUP($A44,covariates!$A$3:$H$1126,7,false) -> 31 | M44: =VLOOKUP($A44,covariates!$A$3:$H$1126,8,false) -> 9.459
A45: 44 | B45: =HYPERLINK("https://github.com/d-wkim/phd/blob/main/data/pdf/komzak_2022.pdf","Komzak et al., 2022") -> Komzak et al., 2022 | C45: 44 | D45: QT | E45: ikdc_subjective | F45: continuous | G45: 36 | H45: 78.3 | I45: 10.5 | J45: =VLOOKUP($A45,covariates!$A$3:$H$1126,5,false) -> at surgery | K45: =VLOOKUP($A45,covariates!$A$3:$H$1126,6,false) | L45: =VLOOKUP($A45,covariates!$A$3:$H$1126,7,false) -> 31 | M45: =VLOOKUP($A45,covariates!$A$3:$H$1126,8,false) -> 9.459
A46: 51 | B46: =HYPERLINK("https://github.com/d-wkim/phd/blob/main/data/pdf/li_2015.pdf","Li et al., 2015") -> Li et al., 2015 | C46: 51 | D46: HT | E46: ikdc_subjective | F46: continuous | G46: 32 | H46: 87.5 | I46: 3.2 | J46: =VLOOKUP($A46,covariates!$A$3:$H$1126,5,false) -> at surgery | K46: =VLOOKUP($A46,covariates!$A$3:$H$1126,6,false) | L46: =VLOOKUP($A46,covariates!$A$3:$H$1126,7,false) -> 29.8 | M46: =VLOOKUP($A46,covariates!$A$3:$H$1126,8,false) -> 7.9
A47: 51 | B47: =HYPERLINK("https://github.com/d-wkim/phd/blob/main/data/pdf/li_2015.pdf","Li et al., 2015") -> Li et al., 2015 | C47: 51 | D47: TA | E47: ikdc_subjective | F47: continuous | G47: 32 | H47: 83.8 | I47: 6.9 | J47: =VLOOKUP($A47,covariates!$A$3:$H$1126,5,false) -> at surgery | K47: =VLOOKUP($A47,covariates!$A$3:$H$1126,6,false) | L47: =VLOOKUP($A47,covariates!$A$3:$H$1126,7,false) -> 29.8 | M47: =VLOOKUP($A47,covariates!$A$3:$H$1126,8,false) -> 7.9
A48: 53 | B48: =HYPERLINK("https://github.com/d-wkim/phd/blob/main/data/pdf/lind_2020.pdf","Lind et al., 2020") -> Lind et al., 2020 | C48: 53 | D48: HT | E48: ikdc_subjective | F48: continuous | G48: 49 | H48: 78 | I48: 18 | J48: =VLOOKUP($A48,covariates!$A$3:$H$1126,5,false) -> at surgery | K48: =VLOOKUP($A48,covariates!$A$3:$H$1126,6,false) | L48: =VLOOKUP($A48,covariates!$A$3:$H$1126,7,false) -> 27.1 | M48: =VLOOKUP($A48,covariates!$A$3:$H$1126,8,false) -> 6.1
A49: 53 | B49: =HYPERLINK("https://github.com/d-wkim/phd/blob/main/data/pdf/lind_2020.pdf","Lind et al., 2020") -> Lind et al., 2020 | C49: 53 | D49: QT | E49: ikdc_subjective | F49: continuous | G49: 47 | H49: 82 | I49: 14 | J49: =VLOOKUP($A49,covariates!$A$3:$H$1126,5,false) -> at surgery | K49: =VLOOKUP($A49,covariates!$A$3:$H$1126,6,false) | L49: =VLOOKUP($A49,covariates!$A$3:$H$1126,7,false) -> 27.1 | M49: =VLOOKUP($A49,covariates!$A$3:$H$1126,8,false) -> 6.1
A50: 54 | B50: =HYPERLINK("https://github.com/d-wkim/phd/blob/main/data/pdf/lucidi_2025.pdf","Lucidi et al., 2025") -> Lucidi et al., 2025 | C50: 54 | D50: BPTB | E50: ikdc_subjective | F50: continuous | G50: 19 | H50: 78.4 | I50: 13.7 | J50: =VLOOKUP($A50,covariates!$A$3:$H$1126,5,false) -> at surgery | K50: =VLOOKUP($A50,covariates!$A$3:$H$1126,6,false) | L50: =VLOOKUP($A50,covariates!$A$3:$H$1126,7,false) -> 52.8 | M50: =VLOOKUP($A50,covariates!$A$3:$H$1126,8,false) -> 7.3
A51: 54 | B51: =HYPERLINK("https://github.com/d-wkim/phd/blob/main/data/pdf/lucidi_2025.pdf","Lucidi et al., 2025") -> Lucidi et al., 2025 | C51: 54 | D51: HT | E51: ikdc_subjective | F51: continuous | G51: 20 | H51: 81.6 | I51: 11.9 | J51: =VLOOKUP($A51,covariates!$A$3:$H$1126,5,false) -> at surgery | K51: =VLOOKUP($A51,covariates!$A$3:$H$1126,6,false) | L51: =VLOOKUP($A51,covariates!$A$3:$H$1126,7,false) -> 52.8 | M51: =VLOOKUP($A51,covariates!$A$3:$H$1126,8,false) -> 7.3
A52: 55 | B52: =HYPERLINK("https://github.com/d-wkim/phd/blob/main/data/pdf/lui_2012.pdf","Lui et al., 2012") -> Lui et al., 2012 | C52: 55 | D52: BPTB | E52: ikdc_subjective | F52: continuous | G52: 14 | H52: 71.9 | I52: 15.2 | J52: =VLOOKUP($A52,covariates!$A$3:$H$1126,5,false) -> at surgery | K52: =VLOOKUP($A52,covariates!$A$3:$H$1126,6,false) | L52: =VLOOKUP($A52,covariates!$A$3:$H$1126,7,false) -> 26.5 | M52: =VLOOKUP($A52,covariates!$A$3:$H$1126,8,false) -> 5
A53: 55 | B53: =HYPERLINK("https://github.com/d-wkim/phd/blob/main/data/pdf/lui_2012.pdf","Lui et al., 2012") -> Lui et al., 2012 | C53: 55 | D53: HT | E53: ikdc_subjective | F53: continuous | G53: 17 | H53: 73.1 | I53: 12.3 | J53: =VLOOKUP($A53,covariates!$A$3:$H$1126,5,false) -> at surgery | K53: =VLOOKUP($A53,covariates!$A$3:$H$1126,6,false) | L53: =VLOOKUP($A53,covariates!$A$3:$H$1126,7,false) -> 26.5 | M53: =VLOOKUP($A53,covariates!$A$3:$H$1126,8,false) -> 5
A54: 56 | B54: =HYPERLINK("https://github.com/d-wkim/phd/blob/main/data/pdf/lund_2014.pdf","Lund et al., 2014") -> Lund et al., 2014 | C54: 56 | D54: BPTB | E54: ikdc_subjective | F54: continuous | G54: 18 | H54: 75 | I54: 13 | J54: =VLOOKUP($A54,covariates!$A$3:$H$1126,5,false) -> at surgery | K54: =VLOOKUP($A54,covariates!$A$3:$H$1126,6,false) | L54: =VLOOKUP($A54,covariates!$A$3:$H$1126,7,false) -> 31 | M54: =VLOOKUP($A54,covariates!$A$3:$H$1126,8,false) -> 8
A55: 56 | B55: =HYPERLINK("https://github.com/d-wkim/phd/blob/main/data/pdf/lund_2014.pdf","Lund et al., 2014") -> Lund et al., 2014 | C55: 56 | D55: QT | E55: ikdc_subjective | F55: continuous | G55: 21 | H55: 76 | I55: 16 | J55: =VLOOKUP($A55,covariates!$A$3:$H$1126,5,false) -> at surgery | K55: =VLOOKUP($A55,covariates!$A$3:$H$1126,6,false) | L55: =VLOOKUP($A55,covariates!$A$3:$H$1126,7,false) -> 31 | M55: =VLOOKUP($A55,covariates!$A$3:$H$1126,8,false) -> 8
A56: 58 | B56: =HYPERLINK("https://github.com/d-wkim/phd/blob/main/data/pdf/malik_2026.pdf","Malik et al., 2026") -> Malik et al., 2026 | C56: 58 | D56: HT | E56: ikdc_subjective | F56: continuous | G56: 25 | H56: 78.9 | I56: 7.4 | J56: =VLOOKUP($A56,covariates!$A$3:$H$1126,5,false) -> at surgery | K56: =VLOOKUP($A56,covariates!$A$3:$H$1126,6,false) | L56: =VLOOKUP($A56,covariates!$A$3:$H$1126,7,false) -> 28.12 | M56: =VLOOKUP($A56,covariates!$A$3:$H$1126,8,false) -> 5.21
A57: 58 | B57: =HYPERLINK("https://github.com/d-wkim/phd/blob/main/data/pdf/malik_2026.pdf","Malik et al., 2026") -> Malik et al., 2026 | C57: 58 | D57: PLT | E57: ikdc_subjective | F57: continuous | G57: 25 | H57: 82.6 | I57: 6.3 | J57: =VLOOKUP($A57,covariates!$A$3:$H$1126,5,false) -> at surgery | K57: =VLOOKUP($A57,covariates!$A$3:$H$1126,6,false) | L57: =VLOOKUP($A57,covariates!$A$3:$H$1126,7,false) -> 28.12 | M57: =VLOOKUP($A57,covariates!$A$3:$H$1126,8,false) -> 5.21
A58: 62 | B58: =HYPERLINK("https://github.com/d-wkim/phd/blob/main/data/pdf/matsumoto_2006.pdf","Matsumoto et al., 2006") -> Matsumoto et al., 2006 | C58: 62 | D58: BPTB | E58: ikdc_subjective | F58: continuous | G58: 37 | H58: 84.3 | I58: 11 | J58: =VLOOKUP($A58,covariates!$A$3:$H$1126,5,false) -> at surgery | K58: =VLOOKUP($A58,covariates!$A$3:$H$1126,6,false) | L58: =VLOOKUP($A58,covariates!$A$3:$H$1126,7,false) -> 23.7 | M58: =VLOOKUP($A58,covariates!$A$3:$H$1126,8,false) -> 7.7
A59: 62 | B59: =HYPERLINK("https://github.com/d-wkim/phd/blob/main/data/pdf/matsumoto_2006.pdf","Matsumoto et al., 2006") -> Matsumoto et al., 2006 | C59: 62 | D59: HT | E59: ikdc_subjective | F59: continuous | G59: 35 | H59: 86.8 | I59: 8.3 | J59: =VLOOKUP($A59,covariates!$A$3:$H$1126,5,false) -> at surgery | K59: =VLOOKUP($A59,covariates!$A$3:$H$1126,6,false) | L59: =VLOOKUP($A59,covariates!$A$3:$H$1126,7,false) -> 23.7 | M59: =VLOOKUP($A59,covariates!$A$3:$H$1126,8,false) -> 7.7
A60: 68 | B60: =HYPERLINK("https://github.com/d-wkim/phd/blob/main/data/pdf/moraiti_2010.pdf","Moraiti et al., 2010") -> Moraiti et al., 2010 | C60: 68 | D60: BPTB | E60: ikdc_subjective | F60: continuous | G60: 6 | H60: 92 | I60: 7 | J60: =VLOOKUP($A60,covariates!$A$3:$H$1126,5,false) -> at surgery | K60: =VLOOKUP($A60,covariates!$A$3:$H$1126,6,false) | L60: =VLOOKUP($A60,covariates!$A$3:$H$1126,7,false) -> 23 | M60: =VLOOKUP($A60,covariates!$A$3:$H$1126,8,false) -> 2
A61: 68 | B61: =HYPERLINK("https://github.com/d-wkim/phd/blob/main/data/pdf/moraiti_2010.pdf","Moraiti et al., 2010") -> Moraiti et al., 2010 | C61: 68 | D61: HT | E61: ikdc_subjective | F61: continuous | G61: 6 | H61: 90 | I61: 10 | J61: =VLOOKUP($A61,covariates!$A$3:$H$1126,5,false) -> at surgery | K61: =VLOOKUP($A61,covariates!$A$3:$H$1126,6,false) | L61: =VLOOKUP($A61,covariates!$A$3:$H$1126,7,false) -> 23 | M61: =VLOOKUP($A61,covariates!$A$3:$H$1126,8,false) -> 2
A62: 73 | B62: =HYPERLINK("https://github.com/d-wkim/phd/blob/main/data/pdf/papalia_2015.pdf","Papalia et al., 2015") -> Papalia et al., 2015 | C62: 73 | D62: BPTB | E62: ikdc_subjective | F62: continuous | G62: 20 | H62: 86.9 | I62: 11.7 | J62: =VLOOKUP($A62,covariates!$A$3:$H$1126,5,false) -> at surgery | K62: =VLOOKUP($A62,covariates!$A$3:$H$1126,6,false) | L62: =VLOOKUP($A62,covariates!$A$3:$H$1126,7,false) -> 24.7 | M62: =VLOOKUP($A62,covariates!$A$3:$H$1126,8,false)
A63: 73 | B63: =HYPERLINK("https://github.com/d-wkim/phd/blob/main/data/pdf/papalia_2015.pdf","Papalia et al., 2015") -> Papalia et al., 2015 | C63: 73 | D63: HT | E63: ikdc_subjective | F63: continuous | G63: 20 | H63: 90.97 | I63: 5.1 | J63: =VLOOKUP($A63,covariates!$A$3:$H$1126,5,false) -> at surgery | K63: =VLOOKUP($A63,covariates!$A$3:$H$1126,6,false) | L63: =VLOOKUP($A63,covariates!$A$3:$H$1126,7,false) -> 24.7 | M63: =VLOOKUP($A63,covariates!$A$3:$H$1126,8,false)
A64: 84 | B64: =HYPERLINK("https://github.com/d-wkim/phd/blob/main/data/pdf/sinding_2020.pdf","Sinding et al., 2020") -> Sinding et al., 2020 | C64: 84 | D64: HT | E64: ikdc_subjective | F64: continuous | G64: 43 | H64: 76 | I64: 15 | J64: =VLOOKUP($A64,covariates!$A$3:$H$1126,5,false) -> at surgery | K64: =VLOOKUP($A64,covariates!$A$3:$H$1126,6,false) | L64: =VLOOKUP($A64,covariates!$A$3:$H$1126,7,false) -> 28.3 | M64: =VLOOKUP($A64,covariates!$A$3:$H$1126,8,false) -> 6.2
A65: 84 | B65: =HYPERLINK("https://github.com/d-wkim/phd/blob/main/data/pdf/sinding_2020.pdf","Sinding et al., 2020") -> Sinding et al., 2020 | C65: 84 | D65: QT | E65: ikdc_subjective | F65: continuous | G65: 42 | H65: 76 | I65: 17 | J65: =VLOOKUP($A65,covariates!$A$3:$H$1126,5,false) -> at surgery | K65: =VLOOKUP($A65,covariates!$A$3:$H$1126,6,false) | L65: =VLOOKUP($A65,covariates!$A$3:$H$1126,7,false) -> 28.3 | M65: =VLOOKUP($A65,covariates!$A$3:$H$1126,8,false) -> 6.2
A66: 85 | B66: =HYPERLINK("https://github.com/d-wkim/phd/blob/main/data/pdf/smith_2020.pdf","Smith et al., 2020") -> Smith et al., 2020 | C66: 85 | D66: BPTB | E66: ikdc_subjective | F66: continuous | G66: 32 | H66: 89.4 | I66: 9.2 | J66: =VLOOKUP($A66,covariates!$A$3:$H$1126,5,false) -> at surgery | K66: =VLOOKUP($A66,covariates!$A$3:$H$1126,6,false) | L66: =VLOOKUP($A66,covariates!$A$3:$H$1126,7,false) -> 17.7 | M66: =VLOOKUP($A66,covariates!$A$3:$H$1126,8,false) -> 2.4
A67: 85 | B67: =HYPERLINK("https://github.com/d-wkim/phd/blob/main/data/pdf/smith_2020.pdf","Smith et al., 2020") -> Smith et al., 2020 | C67: 85 | D67: HT | E67: ikdc_subjective | F67: continuous | G67: 32 | H67: 94.8 | I67: 6.4 | J67: =VLOOKUP($A67,covariates!$A$3:$H$1126,5,false) -> at surgery | K67: =VLOOKUP($A67,covariates!$A$3:$H$1126,6,false) | L67: =VLOOKUP($A67,covariates!$A$3:$H$1126,7,false) -> 17.7 | M67: =VLOOKUP($A67,covariates!$A$3:$H$1126,8,false) -> 2.4
A68: 87 | B68: =HYPERLINK("https://github.com/d-wkim/phd/blob/main/data/pdf/sonnery-cottet_2026.pdf","Sonnery-cottet et al., 2026") -> Sonnery-cottet et al., 2026 | C68: 87 | D68: BPTB | E68: ikdc_subjective | F68: continuous | G68: 296 | H68: 89.4 | I68: 10.9 | J68: =VLOOKUP($A68,covariates!$A$3:$H$1126,5,false) -> at surgery | K68: =VLOOKUP($A68,covariates!$A$3:$H$1126,6,false) | L68: =VLOOKUP($A68,covariates!$A$3:$H$1126,7,false) -> 24.8 | M68: =VLOOKUP($A68,covariates!$A$3:$H$1126,8,false) -> 4.4
A69: 87 | B69: =HYPERLINK("https://github.com/d-wkim/phd/blob/main/data/pdf/sonnery-cottet_2026.pdf","Sonnery-cottet et al., 2026") -> Sonnery-cottet et al., 2026 | C69: 87 | D69: HT | E69: ikdc_subjective | F69: continuous | G69: 297 | H69: 91 | I69: 10.3 | J69: =VLOOKUP($A69,covariates!$A$3:$H$1126,5,false) -> at surgery | K69: =VLOOKUP($A69,covariates!$A$3:$H$1126,6,false) | L69: =VLOOKUP($A69,covariates!$A$3:$H$1126,7,false) -> 24.8 | M69: =VLOOKUP($A69,covariates!$A$3:$H$1126,8,false) -> 4.4
A70: 89 | B70: =HYPERLINK("https://github.com/d-wkim/phd/blob/main/data/pdf/tang_2023.pdf","Tang et al., 2023") -> Tang et al., 2023 | C70: 89 | D70: HT | E70: ikdc_subjective | F70: continuous | G70: 16 | H70: 90.13 | I70: 6.99 | J70: =VLOOKUP($A70,covariates!$A$3:$H$1126,5,false) -> at surgery | K70: =VLOOKUP($A70,covariates!$A$3:$H$1126,6,false) | L70: =VLOOKUP($A70,covariates!$A$3:$H$1126,7,false) -> 28.31 | M70: =VLOOKUP($A70,covariates!$A$3:$H$1126,8,false) -> 8.55
A71: 89 | B71: =HYPERLINK("https://github.com/d-wkim/phd/blob/main/data/pdf/tang_2023.pdf","Tang et al., 2023") -> Tang et al., 2023 | C71: 89 | D71: QT | E71: ikdc_subjective | F71: continuous | G71: 17 | H71: 87.12 | I71: 6.61 | J71: =VLOOKUP($A71,covariates!$A$3:$H$1126,5,false) -> at surgery | K71: =VLOOKUP($A71,covariates!$A$3:$H$1126,6,false) | L71: =VLOOKUP($A71,covariates!$A$3:$H$1126,7,false) -> 28.31 | M71: =VLOOKUP($A71,covariates!$A$3:$H$1126,8,false) -> 8.55
A72: 93 | B72: =HYPERLINK("https://github.com/d-wkim/phd/blob/main/data/pdf/vilchez-cavazos_2020.pdf","Vilchez-cavazos et al., 2020") -> Vilchez-cavazos et al., 2020 | C72: 93 | D72: BPTB | E72: ikdc_subjective | F72: continuous | G72: 14 | H72: 90 | I72: =iferror(RANGE_SD(G72,#REF!,#REF!),"") | J72: =VLOOKUP($A72,covariates!$A$3:$H$1126,5,false) -> at surgery | K72: =VLOOKUP($A72,covariates!$A$3:$H$1126,6,false) | L72: =VLOOKUP($A72,covariates!$A$3:$H$1126,7,false) -> 24.4557 | M72: =VLOOKUP($A72,covariates!$A$3:$H$1126,8,false) -> 8.2374
A73: 93 | B73: =HYPERLINK("https://github.com/d-wkim/phd/blob/main/data/pdf/vilchez-cavazos_2020.pdf","Vilchez-cavazos et al., 2020") -> Vilchez-cavazos et al., 2020 | C73: 93 | D73: QT | E73: ikdc_subjective | F73: continuous | G73: 14 | H73: 88.17 | I73: =iferror(RANGE_SD(G73,#REF!,#REF!),"") | J73: =VLOOKUP($A73,covariates!$A$3:$H$1126,5,false) -> at surgery | K73: =VLOOKUP($A73,covariates!$A$3:$H$1126,6,false) | L73: =VLOOKUP($A73,covariates!$A$3:$H$1126,7,false) -> 24.4557 | M73: =VLOOKUP($A73,covariates!$A$3:$H$1126,8,false) -> 8.2374
A74: 96 | B74: =HYPERLINK("https://github.com/d-wkim/phd/blob/main/data/pdf/wipfler_2011.pdf","Wipfler et al., 2011") -> Wipfler et al., 2011 | C74: 96 | D74: BPTB | E74: ikdc_subjective | F74: continuous | G74: 29 | H74: 86.72 | I74: 2.271 | J74: =VLOOKUP($A74,covariates!$A$3:$H$1126,5,false) -> at surgery | K74: =VLOOKUP($A74,covariates!$A$3:$H$1126,6,false) | L74: =VLOOKUP($A74,covariates!$A$3:$H$1126,7,false) -> 29.87 | M74: =VLOOKUP($A74,covariates!$A$3:$H$1126,8,false) -> 7.304
A75: 96 | B75: =HYPERLINK("https://github.com/d-wkim/phd/blob/main/data/pdf/wipfler_2011.pdf","Wipfler et al., 2011") -> Wipfler et al., 2011 | C75: 96 | D75: HT | E75: ikdc_subjective | F75: continuous | G75: 25 | H75: 92.95 | I75: 1.992 | J75: =VLOOKUP($A75,covariates!$A$3:$H$1126,5,false) -> at surgery | K75: =VLOOKUP($A75,covariates!$A$3:$H$1126,6,false) | L75: =VLOOKUP($A75,covariates!$A$3:$H$1126,7,false) -> 29.87 | M75: =VLOOKUP($A75,covariates!$A$3:$H$1126,8,false) -> 7.304
A76: 100 | B76: =HYPERLINK("https://github.com/d-wkim/phd/blob/main/data/pdf/zaffagnini_2011.pdf","Zaffagnini et al., 2011") -> Zaffagnini et al., 2011 | C76: 100 | D76: BPTB | E76: ikdc_subjective | F76: continuous | G76: 40 | H76: 82 | I76: 20 | J76: =VLOOKUP($A76,covariates!$A$3:$H$1126,5,false) -> at surgery | K76: =VLOOKUP($A76,covariates!$A$3:$H$1126,6,false) | L76: =VLOOKUP($A76,covariates!$A$3:$H$1126,7,false) -> 26 | M76: =VLOOKUP($A76,covariates!$A$3:$H$1126,8,false) -> 9.5
A77: 100 | B77: =HYPERLINK("https://github.com/d-wkim/phd/blob/main/data/pdf/zaffagnini_2011.pdf","Zaffagnini et al., 2011") -> Zaffagnini et al., 2011 | C77: 100 | D77: HT | E77: ikdc_subjective | F77: continuous | G77: 39 | H77: 88 | I77: 9 | J77: =VLOOKUP($A77,covariates!$A$3:$H$1126,5,false) -> at surgery | K77: =VLOOKUP($A77,covariates!$A$3:$H$1126,6,false) | L77: =VLOOKUP($A77,covariates!$A$3:$H$1126,7,false) -> 26 | M77: =VLOOKUP($A77,covariates!$A$3:$H$1126,8,false) -> 9.5
A78: 2 | B78: =HYPERLINK("https://github.com/d-wkim/phd/blob/main/data/pdf/aglietti_2004.pdf","Aglietti et al., 2004") -> Aglietti et al., 2004 | C78: 2 | D78: BPTB | E78: instrumented_laxity | F78: continuous | G78: 60 | H78: 2.2 | I78: =iferror(RANGE_SD(G78,#REF!,#REF!),"") | J78: =VLOOKUP($A78,covariates!$A$3:$H$1126,5,false) -> at surgery | K78: =VLOOKUP($A78,covariates!$A$3:$H$1126,6,false) | L78: =VLOOKUP($A78,covariates!$A$3:$H$1126,7,false) -> 25 | M78: =VLOOKUP($A78,covariates!$A$3:$H$1126,8,false) -> 4.973
A79: 2 | B79: =HYPERLINK("https://github.com/d-wkim/phd/blob/main/data/pdf/aglietti_2004.pdf","Aglietti et al., 2004") -> Aglietti et al., 2004 | C79: 2 | D79: HT | E79: instrumented_laxity | F79: continuous | G79: 60 | H79: 1.95 | I79: =iferror(RANGE_SD(G79,#REF!,#REF!),"") | J79: =VLOOKUP($A79,covariates!$A$3:$H$1126,5,false) -> at surgery | K79: =VLOOKUP($A79,covariates!$A$3:$H$1126,6,false) | L79: =VLOOKUP($A79,covariates!$A$3:$H$1126,7,false) -> 25 | M79: =VLOOKUP($A79,covariates!$A$3:$H$1126,8,false) -> 4.973
A80: 3 | B80: =HYPERLINK("https://github.com/d-wkim/phd/blob/main/data/pdf/ahldén_2009.pdf","Ahldén et al., 2009") -> Ahldén et al., 2009 | C80: 3 | D80: BPTB | E80: instrumented_laxity | F80: continuous | G80: 25 | H80: 2.6 | I80: 3.3 | J80: =VLOOKUP($A80,covariates!$A$3:$H$1126,5,false) -> at surgery | K80: =VLOOKUP($A80,covariates!$A$3:$H$1126,6,false) | L80: =VLOOKUP($A80,covariates!$A$3:$H$1126,7,false) -> 27.412608 | M80: =VLOOKUP($A80,covariates!$A$3:$H$1126,8,false) -> 8.902
A81: 3 | B81: =HYPERLINK("https://github.com/d-wkim/phd/blob/main/data/pdf/ahldén_2009.pdf","Ahldén et al., 2009") -> Ahldén et al., 2009 | C81: 3 | D81: HT | E81: instrumented_laxity | F81: continuous | G81: 22 | H81: 1.4 | I81: 2.6 | J81: =VLOOKUP($A81,covariates!$A$3:$H$1126,5,false) -> at surgery | K81: =VLOOKUP($A81,covariates!$A$3:$H$1126,6,false) | L81: =VLOOKUP($A81,covariates!$A$3:$H$1126,7,false) -> 27.412608 | M81: =VLOOKUP($A81,covariates!$A$3:$H$1126,8,false) -> 8.902
A82: 5 | B82: =HYPERLINK("https://github.com/d-wkim/phd/blob/main/data/pdf/anderson_2001.pdf","Anderson et al., 2001") -> Anderson et al., 2001 | C82: 5 | D82: BPTB | E82: instrumented_laxity | F82: continuous | G82: 35 | H82: 2.1 | I82: 2 | J82: =VLOOKUP($A82,covariates!$A$3:$H$1126,5,false) -> at surgery | K82: =VLOOKUP($A82,covariates!$A$3:$H$1126,6,false) | L82: =VLOOKUP($A82,covariates!$A$3:$H$1126,7,false) -> 23.6 | M82: =VLOOKUP($A82,covariates!$A$3:$H$1126,8,false) -> 7.132
A83: 5 | B83: =HYPERLINK("https://github.com/d-wkim/phd/blob/main/data/pdf/anderson_2001.pdf","Anderson et al., 2001") -> Anderson et al., 2001 | C83: 5 | D83: HT | E83: instrumented_laxity | F83: continuous | G83: 33 | H83: 3.1 | I83: 2.3 | J83: =VLOOKUP($A83,covariates!$A$3:$H$1126,5,false) -> at surgery | K83: =VLOOKUP($A83,covariates!$A$3:$H$1126,6,false) | L83: =VLOOKUP($A83,covariates!$A$3:$H$1126,7,false) -> 23.6 | M83: =VLOOKUP($A83,covariates!$A$3:$H$1126,8,false) -> 7.132
A84: 7 | B84: =HYPERLINK("https://github.com/d-wkim/phd/blob/main/data/pdf/aune_2001.pdf","Aune et al., 2001") -> Aune et al., 2001 | C84: 7 | D84: BPTB | E84: instrumented_laxity | F84: continuous | G84: 32 | H84: 3.3 | I84: 2.6 | J84: =VLOOKUP($A84,covariates!$A$3:$H$1126,5,false) -> at surgery | K84: =VLOOKUP($A84,covariates!$A$3:$H$1126,6,false) | L84: =VLOOKUP($A84,covariates!$A$3:$H$1126,7,false) -> 25 | M84: =VLOOKUP($A84,covariates!$A$3:$H$1126,8,false) -> 7
A85: 7 | B85: =HYPERLINK("https://github.com/d-wkim/phd/blob/main/data/pdf/aune_2001.pdf","Aune et al., 2001") -> Aune et al., 2001 | C85: 7 | D85: HT | E85: instrumented_laxity | F85: continuous | G85: 29 | H85: 2.9 | I85: 2.4 | J85: =VLOOKUP($A85,covariates!$A$3:$H$1126,5,false) -> at surgery | K85: =VLOOKUP($A85,covariates!$A$3:$H$1126,6,false) | L85: =VLOOKUP($A85,covariates!$A$3:$H$1126,7,false) -> 25 | M85: =VLOOKUP($A85,covariates!$A$3:$H$1126,8,false) -> 7
A86: 10 | B86: =HYPERLINK("https://github.com/d-wkim/phd/blob/main/data/pdf/barié_2020.pdf","Barié et al., 2020") -> Barié et al., 2020 | C86: 10 | D86: BPTB | E86: instrumented_laxity | F86: continuous | G86: 43 | H86: 1.05 | I86: 1.36 | J86: =VLOOKUP($A86,covariates!$A$3:$H$1126,5,false) -> at surgery | K86: =VLOOKUP($A86,covariates!$A$3:$H$1126,6,false) | L86: =VLOOKUP($A86,covariates!$A$3:$H$1126,7,false) -> 30.6 | M86: =VLOOKUP($A86,covariates!$A$3:$H$1126,8,false) -> 7.5
A87: 10 | B87: =HYPERLINK("https://github.com/d-wkim/phd/blob/main/data/pdf/barié_2020.pdf","Barié et al., 2020") -> Barié et al., 2020 | C87: 10 | D87: QT | E87: instrumented_laxity | F87: continuous | G87: 43 | H87: 1 | I87: 1.095 | J87: =VLOOKUP($A87,covariates!$A$3:$H$1126,5,false) -> at surgery | K87: =VLOOKUP($A87,covariates!$A$3:$H$1126,6,false) | L87: =VLOOKUP($A87,covariates!$A$3:$H$1126,7,false) -> 30.6 | M87: =VLOOKUP($A87,covariates!$A$3:$H$1126,8,false) -> 7.5
A88: 12 | B88: =HYPERLINK("https://github.com/d-wkim/phd/blob/main/data/pdf/bi_2018.pdf","Bi et al., 2018") -> Bi et al., 2018 | C88: 12 | D88: HT | E88: instrumented_laxity | F88: continuous | G88: 62 | H88: 1.71 | I88: 0.57 | J88: =VLOOKUP($A88,covariates!$A$3:$H$1126,5,false) -> at surgery | K88: =VLOOKUP($A88,covariates!$A$3:$H$1126,6,false) | L88: =VLOOKUP($A88,covariates!$A$3:$H$1126,7,false) -> 27.9 | M88: =VLOOKUP($A88,covariates!$A$3:$H$1126,8,false) -> 6.7
A89: 12 | B89: =HYPERLINK("https://github.com/d-wkim/phd/blob/main/data/pdf/bi_2018.pdf","Bi et al., 2018") -> Bi et al., 2018 | C89: 12 | D89: PLT | E89: instrumented_laxity | F89: continuous | G89: 62 | H89: 1.85 | I89: 0.77 | J89: =VLOOKUP($A89,covariates!$A$3:$H$1126,5,false) -> at surgery | K89: =VLOOKUP($A89,covariates!$A$3:$H$1126,6,false) | L89: =VLOOKUP($A89,covariates!$A$3:$H$1126,7,false) -> 27.9 | M89: =VLOOKUP($A89,covariates!$A$3:$H$1126,8,false) -> 6.7
A90: 23 | B90: =HYPERLINK("https://github.com/d-wkim/phd/blob/main/data/pdf/ejerhed_2003.pdf","Ejerhed et al., 2003") -> Ejerhed et al., 2003 | C90: 23 | D90: BPTB | E90: instrumented_laxity | F90: continuous | G90: 32 | H90: =iferror(MEDIAN_MEAN(G90,#REF!,#REF!,#REF!),"") | I90: =iferror(RANGE_SD(G90,#REF!,#REF!),"") | J90: =VLOOKUP($A90,covariates!$A$3:$H$1126,5,false) -> at surgery | K90: =VLOOKUP($A90,covariates!$A$3:$H$1126,6,false) | L90: =VLOOKUP($A90,covariates!$A$3:$H$1126,7,false) -> 27.260431 | M90: =VLOOKUP($A90,covariates!$A$3:$H$1126,8,false) -> 8.467
A91: 23 | B91: =HYPERLINK("https://github.com/d-wkim/phd/blob/main/data/pdf/ejerhed_2003.pdf","Ejerhed et al., 2003") -> Ejerhed et al., 2003 | C91: 23 | D91: HT | E91: instrumented_laxity | F91: continuous | G91: 34 | H91: =iferror(MEDIAN_MEAN(G91,#REF!,#REF!,#REF!),"") | I91: =iferror(RANGE_SD(G91,#REF!,#REF!),"") | J91: =VLOOKUP($A91,covariates!$A$3:$H$1126,5,false) -> at surgery | K91: =VLOOKUP($A91,covariates!$A$3:$H$1126,6,false) | L91: =VLOOKUP($A91,covariates!$A$3:$H$1126,7,false) -> 27.260431 | M91: =VLOOKUP($A91,covariates!$A$3:$H$1126,8,false) -> 8.467
A92: 25 | B92: =HYPERLINK("https://github.com/d-wkim/phd/blob/main/data/pdf/eriksson_2006.pdf","Eriksson et al., 2001") -> Eriksson et al., 2001 | C92: 25 | D92: BPTB | E92: instrumented_laxity | F92: continuous | G92: 42 | H92: 0.95 | I92: 0.91 | J92: =VLOOKUP($A92,covariates!$A$3:$H$1126,5,false) -> at surgery | K92: =VLOOKUP($A92,covariates!$A$3:$H$1126,6,false) | L92: =VLOOKUP($A92,covariates!$A$3:$H$1126,7,false) -> 27 | M92: =VLOOKUP($A92,covariates!$A$3:$H$1126,8,false) -> 6
A93: 25 | B93: =HYPERLINK("https://github.com/d-wkim/phd/blob/main/data/pdf/eriksson_2006.pdf","Eriksson et al., 2001") -> Eriksson et al., 2001 | C93: 25 | D93: HT | E93: instrumented_laxity | F93: continuous | G93: 47 | H93: 1.1 | I93: 0.95 | J93: =VLOOKUP($A93,covariates!$A$3:$H$1126,5,false) -> at surgery | K93: =VLOOKUP($A93,covariates!$A$3:$H$1126,6,false) | L93: =VLOOKUP($A93,covariates!$A$3:$H$1126,7,false) -> 27 | M93: =VLOOKUP($A93,covariates!$A$3:$H$1126,8,false) -> 6
A94: 26 | B94: =HYPERLINK("https://github.com/d-wkim/phd/blob/main/data/pdf/feller_webster_2003.pdf","Feller & Webster, 2003") -> Feller & Webster, 2003 | C94: 26 | D94: BPTB | E94: instrumented_laxity | F94: continuous | G94: 27 | H94: 0.5 | I94: 1 | J94: =VLOOKUP($A94,covariates!$A$3:$H$1126,5,false) -> at surgery | K94: =VLOOKUP($A94,covariates!$A$3:$H$1126,6,false) | L94: =VLOOKUP($A94,covariates!$A$3:$H$1126,7,false) -> 25.8 | M94: =VLOOKUP($A94,covariates!$A$3:$H$1126,8,false) -> 6
A95: 26 | B95: =HYPERLINK("https://github.com/d-wkim/phd/blob/main/data/pdf/feller_webster_2003.pdf","Feller & Webster, 2003") -> Feller & Webster, 2003 | C95: 26 | D95: HT | E95: instrumented_laxity | F95: continuous | G95: 21 | H95: 1.1 | I95: 1.2 | J95: =VLOOKUP($A95,covariates!$A$3:$H$1126,5,false) -> at surgery | K95: =VLOOKUP($A95,covariates!$A$3:$H$1126,6,false) | L95: =VLOOKUP($A95,covariates!$A$3:$H$1126,7,false) -> 25.8 | M95: =VLOOKUP($A95,covariates!$A$3:$H$1126,8,false) -> 6
A96: 30 | B96: =HYPERLINK("https://github.com/d-wkim/phd/blob/main/data/pdf/gifstad_2013.pdf","Gifstad et al., 2013") -> Gifstad et al., 2013 | C96: 30 | D96: BPTB | E96: instrumented_laxity | F96: continuous | G96: 41 | H96: 1.4 | I96: 1.8 | J96: =VLOOKUP($A96,covariates!$A$3:$H$1126,5,false) -> at surgery | K96: =VLOOKUP($A96,covariates!$A$3:$H$1126,6,false) | L96: =VLOOKUP($A96,covariates!$A$3:$H$1126,7,false) -> 27 | M96: =VLOOKUP($A96,covariates!$A$3:$H$1126,8,false) -> 6.74
A97: 30 | B97: =HYPERLINK("https://github.com/d-wkim/phd/blob/main/data/pdf/gifstad_2013.pdf","Gifstad et al., 2013") -> Gifstad et al., 2013 | C97: 30 | D97: HT | E97: instrumented_laxity | F97: continuous | G97: 36 | H97: 1.4 | I97: 1.4 | J97: =VLOOKUP($A97,covariates!$A$3:$H$1126,5,false) -> at surgery | K97: =VLOOKUP($A97,covariates!$A$3:$H$1126,6,false) | L97: =VLOOKUP($A97,covariates!$A$3:$H$1126,7,false) -> 27 | M97: =VLOOKUP($A97,covariates!$A$3:$H$1126,8,false) -> 6.74
A98: 33 | B98: =HYPERLINK("https://github.com/d-wkim/phd/blob/main/data/pdf/harilainen_2006.pdf","Harilainen et al., 2006") -> Harilainen et al., 2006 | C98: 33 | D98: BPTB | E98: instrumented_laxity | F98: continuous | G98: 37 | H98: 1.5 | I98: 3 | J98: =VLOOKUP($A98,covariates!$A$3:$H$1126,5,false) -> at surgery | K98: =VLOOKUP($A98,covariates!$A$3:$H$1126,6,false) | L98: =VLOOKUP($A98,covariates!$A$3:$H$1126,7,false) | M98: =VLOOKUP($A98,covariates!$A$3:$H$1126,8,false)
A99: 33 | B99: =HYPERLINK("https://github.com/d-wkim/phd/blob/main/data/pdf/harilainen_2006.pdf","Harilainen et al., 2006") -> Harilainen et al., 2006 | C99: 33 | D99: HT | E99: instrumented_laxity | F99: continuous | G99: 37 | H99: 1.2 | I99: 3.9 | J99: =VLOOKUP($A99,covariates!$A$3:$H$1126,5,false) -> at surgery | K99: =VLOOKUP($A99,covariates!$A$3:$H$1126,6,false) | L99: =VLOOKUP($A99,covariates!$A$3:$H$1126,7,false) | M99: =VLOOKUP($A99,covariates!$A$3:$H$1126,8,false)
A100: 35 | B100: =HYPERLINK("https://github.com/d-wkim/phd/blob/main/data/pdf/holm_2010.pdf","Holm et al., 2010") -> Holm et al., 2010 | C100: 35 | D100: BPTB | E100: instrumented_laxity | F100: continuous | G100: 28 | H100: 3 | I100: 3.2 | J100: =VLOOKUP($A100,covariates!$A$3:$H$1126,5,false) -> at surgery | K100: =VLOOKUP($A100,covariates!$A$3:$H$1126,6,false) | L100: =VLOOKUP($A100,covariates!$A$3:$H$1126,7,false) -> 33.9 | M100: =VLOOKUP($A100,covariates!$A$3:$H$1126,8,false) -> 6.2
...

Sheet Sheet44
A2: 1 | B2: Ageberg et al., 2009 | C2: 10.1007/s00167-008-0645-4 | D2: ="https://doi.org/"&C2 -> https://doi.org/10.1007/s00167-008-0645-4
A3: 1 | B3: Ageberg et al., 2009 | C3: 10.1007/s00167-008-0645-4 | D3: ="https://doi.org/"&C3 -> https://doi.org/10.1007/s00167-008-0645-4
A4: 2 | B4: Aglietti et al., 2004 | D4: ="https://doi.org/"&C4 -> https://doi.org/
A5: 2 | B5: Aglietti et al., 2004 | D5: ="https://doi.org/"&C5 -> https://doi.org/
A6: 3 | B6: Ahldén et al., 2009 | C6: 10.1007/s00167-009-0846-5 | D6: ="https://doi.org/"&C6 -> https://doi.org/10.1007/s00167-009-0846-5
A7: 3 | B7: Ahldén et al., 2009 | C7: 10.1007/s00167-009-0846-5 | D7: ="https://doi.org/"&C7 -> https://doi.org/10.1007/s00167-009-0846-5
A8: 4 | B8: Anderson et al., 2001 | C8: 10.1177/03635465010290030201 | D8: ="https://doi.org/"&C8 -> https://doi.org/10.1177/03635465010290030201
A9: 4 | B9: Anderson et al., 2001 | C9: 10.1177/03635465010290030201 | D9: ="https://doi.org/"&C9 -> https://doi.org/10.1177/03635465010290030201
A10: 5 | B10: Anz et al., 2023 | C10: 10.1177/23259671231210035 | D10: ="https://doi.org/"&C10 -> https://doi.org/10.1177/23259671231210035
A11: 5 | B11: Anz et al., 2023 | C11: 10.1177/23259671231210035 | D11: ="https://doi.org/"&C11 -> https://doi.org/10.1177/23259671231210035
A12: 6 | B12: Aune et al., 2001 | C12: 10.1177/03635465010290060901 | D12: ="https://doi.org/"&C12 -> https://doi.org/10.1177/03635465010290060901
A13: 6 | B13: Aune et al., 2001 | C13: 10.1177/03635465010290060901 | D13: ="https://doi.org/"&C13 -> https://doi.org/10.1177/03635465010290060901
A14: 7 | B14: Barenius et al., 2010 | C14: 10.1177/0363546510369549 | D14: ="https://doi.org/"&C14 -> https://doi.org/10.1177/0363546510369549
A15: 7 | B15: Barenius et al., 2010 | C15: 10.1177/0363546510369549 | D15: ="https://doi.org/"&C15 -> https://doi.org/10.1177/0363546510369549
A16: 8 | B16: Barié et al., 2020 | C16: 10.1007/s00402-020-03508-1 | D16: ="https://doi.org/"&C16 -> https://doi.org/10.1007/s00402-020-03508-1
A17: 8 | B17: Barié et al., 2020 | C17: 10.1007/s00402-020-03508-1 | D17: ="https://doi.org/"&C17 -> https://doi.org/10.1007/s00402-020-03508-1
... A31: 15 | B31: Ejerhed et al., 2003 | C31: 10.1177/03635465030310011401 | D31: ="https://doi.org/"&C31 -> https://doi.org/10.1177/03635465030310011401
A32: 16 | B32: Eriksson et al., 2001 | D32: ="https://doi.org/"&C32 -> https://doi.org/
A33: 16 | B33: Eriksson et al., 2001 | D33: ="https://doi.org/"&C33 -> https://doi.org/
A34: 17 | B34: Feller & Webster, 2003 | C34: 10.1177/03635465030310041501 | D34: ="https://doi.org/"&C34 -> https://doi.org/10.1177/03635465030310041501
A35: 17 | B35: Feller & Webster, 2003 | C35: 10.1177/03635465030310041501 | D35: ="https://doi.org/"&C35 -> https://doi.org/10.1177/03635465030310041501
A36: 18 | B36: Gifstad et al., 2013 | C36: 10.1007/s00167-012-1947-0 | D36: ="https://doi.org/"&C36 -> https://doi.org/10.1007/s00167-012-1947-0
A37: 18 | B37: Gifstad et al., 2013 | C37: 10.1007/s00167-012-1947-0 | D37: ="https://doi.org/"&C37 -> https://doi.org/10.1007/s00167-012-1947-0
A38: 19 | B38: Guglielmetti et al., 2021 | C38: 10.1177/23259671211028168 | D38: ="https://doi.org/"&C38 -> https://doi.org/10.1177/23259671211028168
A39: 19 | B39: Guglielmetti et al., 2021 | C39: 10.1177/23259671211028168 | D39: ="https://doi.org/"&C39 -> https://doi.org/10.1177/23259671211028168
A40: 20 | B40: Harilainen et al., 2006 | C40: 10.1007/s00167-006-0059-0 | D40: ="https://doi.org/"&C40 -> https://doi.org/10.1007/s00167-006-0059-0
A41: 20 | B41: Harilainen et al., 2006 | C41: 10.1007/s00167-006-0059-0 | D41: ="https://doi.org/"&C41 -> https://doi.org/10.1007/s00167-006-0059-0
A42: 21 | B42: Heijne & Werner, 2010 | C42: 10.1007/s00167-009-0961-3 | D42: ="https://doi.org/"&C42 -> https://doi.org/10.1007/s00167-009-0961-3
A43: 21 | B43: Heijne & Werner, 2010 | C43: 10.1007/s00167-009-0961-3 | D43: ="https://doi.org/"&C43 -> https://doi.org/10.1007/s00167-009-0961-3
A44: 22 | B44: Holm et al., 2010 | C44: 10.1177/0363546509350301 | D44: ="https://doi.org/"&C44 -> https://doi.org/10.1177/0363546509350301
A45: 22 | B45: Holm et al., 2010 | C45: 10.1177/0363546509350301 | D45: ="https://doi.org/"&C45 -> https://doi.org/10.1177/0363546509350301
... A59: 29 | B59: Konrads et al., 2016 | C59: 10.1007/s00402-015-2386-4 | D59: ="https://doi.org/"&C59 -> https://doi.org/10.1007/s00402-015-2386-4
A60: 30 | B60: Laoruengthana et al., 2009 | D60: ="https://doi.org/"&C60 -> https://doi.org/
A61: 30 | B61: Laoruengthana et al., 2009 | D61: ="https://doi.org/"&C61 -> https://doi.org/
A62: 31 | B62: Lawhorn et al., 2012 | C62: 10.1016/j.arthro.2012.05.010 | D62: ="https://doi.org/"&C62 -> https://doi.org/10.1016/j.arthro.2012.05.010
A63: 31 | B63: Lawhorn et al., 2012 | C63: 10.1016/j.arthro.2012.05.010 | D63: ="https://doi.org/"&C63 -> https://doi.org/10.1016/j.arthro.2012.05.010
A64: 32 | B64: Laxdal et al., 2005 | C64: 10.1016/j.arthro.2004.09.014 | D64: ="https://doi.org/"&C64 -> https://doi.org/10.1016/j.arthro.2004.09.014
A65: 32 | B65: Laxdal et al., 2005 | C65: 10.1016/j.arthro.2004.09.014 | D65: ="https://doi.org/"&C65 -> https://doi.org/10.1016/j.arthro.2004.09.014
A66: 33 | B66: Li et al., 2015 | C66: 10.1016/j.arthro.2015.02.033 | D66: ="https://doi.org/"&C66 -> https://doi.org/10.1016/j.arthro.2015.02.033
A67: 33 | B67: Li et al., 2015 | C67: 10.1016/j.arthro.2015.02.033 | D67: ="https://doi.org/"&C67 -> https://doi.org/10.1016/j.arthro.2015.02.033
A68: 34 | B68: Lidén et al., 2007 | C68: 10.1177/0363546506298275 | D68: ="https://doi.org/"&C68 -> https://doi.org/10.1177/0363546506298275
A69: 34 | B69: Lidén et al., 2007 | C69: 10.1177/0363546506298275 | D69: ="https://doi.org/"&C69 -> https://doi.org/10.1177/0363546506298275
A70: 35 | B70: Lind et al., 2020 | C70: 10.1136/bjsports-2019-101000 | D70: ="https://doi.org/"&C70 -> https://doi.org/10.1136/bjsports-2019-101000
A71: 35 | B71: Lind et al., 2020 | C71: 10.1136/bjsports-2019-101000 | D71: ="https://doi.org/"&C71 -> https://doi.org/10.1136/bjsports-2019-101000
A72: 36 | B72: Lucidi et al., 2025 | C72: 10.1177/23259671241302348 | D72: ="https://doi.org/"&C72 -> https://doi.org/10.1177/23259671241302348
A73: 36 | B73: Lucidi et al., 2025 | C73: 10.1177/23259671241302348 | D73: ="https://doi.org/"&C73 -> https://doi.org/10.1177/23259671241302348
... A117: 58 | B117: Zaffagnini et al., 2011 | C117: 10.1007/s00167-010-1225-y | D117: ="https://doi.org/"&C117 -> https://doi.org/10.1007/s00167-010-1225-y

Sheet outcomes
A1: id | B1: study | C1: subgroup | D1: outcome | E1: data_type | F1: ni | G1: yi | H1: sdi | I1: min | J1: q1 | K1: median | L1: q3 | M1: max | N1: TE | O1: mean | P1: sd | Q1: min | R1: q1 | S1: median | T1: q3 | U1: max | V1: seTE | W1: male | X1: female | Y1: vi | Z1: mean | AA1: sd | AB1: min | AC1: q1 | AD1: median | AE1: q3 | AF1: max | AG1: screening | AH1: age_mean | AI1: age_sd | AJ1: male | AK1: female | AL1: follow-up_mo | AM1: follow-up_yr
A2: 6 | B2: =HYPERLINK("https://github.com/d-wkim/phd/blob/main/data/pdf/anz_2023.pdf","Anz et al., 2023") -> Anz et al., 2023 | C2: BPTB | D2: graft rupture | E2: dichotomous | F2: 8 | G2: 0 | H2: =iferror(P_SD(F2,G2),"") -> 0.1767767 | AG2: Included | AH2: =iferror(VLOOKUP($B2,covariates!$B$3:$Z$1126,6,FALSE),"") -> 29.4 | AI2: =iferror(VLOOKUP($B2,covariates!$B$3:$Z$1126,7,FALSE),"") -> 7.343 | AJ2: =iferror(VLOOKUP($B2,covariates!$B$3:$Z$1126,14,FALSE),"") -> 4 | AK2: =iferror(VLOOKUP($B2,covariates!$B$3:$Z$1126,16,FALSE),"") -> 6 | AL2: =iferror(VLOOKUP($B2,covariates!$B$3:$Z$1126,18,FALSE),"") -> 12 | AM2: =iferror(VLOOKUP($B2,covariates!$B$3:$Z$1126,19,FALSE),"") -> 1
A3: 6 | B3: =HYPERLINK("https://github.com/d-wkim/phd/blob/main/data/pdf/anz_2023.pdf","Anz et al., 2023") -> Anz et al., 2023 | C3: HT | D3: graft rupture | E3: dichotomous | F3: 8 | G3: 0 | H3: =iferror(P_SD(F3,G3),"") -> 0.1767767 | AG3: Included | AH3: =iferror(VLOOKUP($B3,covariates!$B$3:$Z$1126,6,FALSE),"") -> 29.4 | AI3: =iferror(VLOOKUP($B3,covariates!$B$3:$Z$1126,7,FALSE),"") -> 7.343 | AJ3: =iferror(VLOOKUP($B3,covariates!$B$3:$Z$1126,14,FALSE),"") -> 4 | AK3: =iferror(VLOOKUP($B3,covariates!$B$3:$Z$1126,16,FALSE),"") -> 6 | AL3: =iferror(VLOOKUP($B3,covariates!$B$3:$Z$1126,18,FALSE),"") -> 12 | AM3: =iferror(VLOOKUP($B3,covariates!$B$3:$Z$1126,19,FALSE),"") -> 1
A4: 12 | B4: =HYPERLINK("https://github.com/d-wkim/phd/blob/main/data/pdf/bi_2018.pdf","Bi et al., 2018") -> Bi et al., 2018 | C4: HT | D4: graft rupture | E4: dichotomous | H4: =iferror(P_SD(F4,G4),"") | AG4: Excluded | AH4: =iferror(VLOOKUP($B4,covariates!$B$3:$Z$1126,6,FALSE),"") -> 27.9 | AI4: =iferror(VLOOKUP($B4,covariates!$B$3:$Z$1126,7,FALSE),"") -> 6.7 | AJ4: =iferror(VLOOKUP($B4,covariates!$B$3:$Z$1126,14,FALSE),"") -> 31 | AK4: =iferror(VLOOKUP($B4,covariates!$B$3:$Z$1126,16,FALSE),"") -> 31 | AL4: =iferror(VLOOKUP($B4,covariates!$B$3:$Z$1126,18,FALSE),"") -> 30.3 | AM4: =iferror(VLOOKUP($B4,covariates!$B$3:$Z$1126,19,FALSE),"") -> 2.5
A5: 12 | B5: =HYPERLINK("https://github.com/d-wkim/phd/blob/main/data/pdf/bi_2018.pdf","Bi et al., 2018") -> Bi et al., 2018 | C5: PLT | D5: graft rupture | E5: dichotomous | H5: =iferror(P_SD(F5,G5),"") | AG5: Excluded | AH5: =iferror(VLOOKUP($B5,covariates!$B$3:$Z$1126,6,FALSE),"") -> 27.9 | AI5: =iferror(VLOOKUP($B5,covariates!$B$3:$Z$1126,7,FALSE),"") -> 6.7 | AJ5: =iferror(VLOOKUP($B5,covariates!$B$3:$Z$1126,14,FALSE),"") -> 31 | AK5: =iferror(VLOOKUP($B5,covariates!$B$3:$Z$1126,16,FALSE),"") -> 31 | AL5: =iferror(VLOOKUP($B5,covariates!$B$3:$Z$1126,18,FALSE),"") -> 30.3 | AM5: =iferror(VLOOKUP($B5,covariates!$B$3:$Z$1126,19,FALSE),"") -> 2.5
A6: 22 | B6: =HYPERLINK("https://github.com/d-wkim/phd/blob/main/data/pdf/cruz_2022.pdf","Cruz et al., 2022") -> Cruz et al., 2022 | C6: HT | D6: graft rupture | E6: dichotomous | H6: =iferror(P_SD(F6,G6),"") | AG6: Excluded | AH6: =iferror(VLOOKUP($B6,covariates!$B$3:$Z$1126,6,FALSE),"") | AI6: =iferror(VLOOKUP($B6,covariates!$B$3:$Z$1126,7,FALSE),"") | AJ6: =iferror(VLOOKUP($B6,covariates!$B$3:$Z$1126,14,FALSE),"") | AK6: =iferror(VLOOKUP($B6,covariates!$B$3:$Z$1126,16,FALSE),"") | AL6: =iferror(VLOOKUP($B6,covariates!$B$3:$Z$1126,18,FALSE),"") | AM6: =iferror(VLOOKUP($B6,covariates!$B$3:$Z$1126,19,FALSE),"")
A7: 22 | B7: =HYPERLINK("https://github.com/d-wkim/phd/blob/main/data/pdf/cruz_2022.pdf","Cruz et al., 2022") -> Cruz et al., 2022 | C7: TA | D7: graft rupture | E7: dichotomous | H7: =iferror(P_SD(F7,G7),"") | AG7: Excluded | AH7: =iferror(VLOOKUP($B7,covariates!$B$3:$Z$1126,6,FALSE),"") | AI7: =iferror(VLOOKUP($B7,covariates!$B$3:$Z$1126,7,FALSE),"") | AJ7: =iferror(VLOOKUP($B7,covariates!$B$3:$Z$1126,14,FALSE),"") | AK7: =iferror(VLOOKUP($B7,covariates!$B$3:$Z$1126,16,FALSE),"") | AL7: =iferror(VLOOKUP($B7,covariates!$B$3:$Z$1126,18,FALSE),"") | AM7: =iferror(VLOOKUP($B7,covariates!$B$3:$Z$1126,19,FALSE),"")
A8: 43 | B8: =HYPERLINK("https://github.com/d-wkim/phd/blob/main/data/pdf/kautzner_2015.pdf","Kautzner et al., 2015") -> Kautzner et al., 2015 | C8: BPTB | D8: graft rupture | E8: dichotomous | F8: 74 | G8: 0 | H8: =iferror(P_SD(F8,G8),"") -> 0.058123819 | AG8: Included | AH8: =iferror(VLOOKUP($B8,covariates!$B$3:$Z$1126,6,FALSE),"") -> 26 | AI8: =iferror(VLOOKUP($B8,covariates!$B$3:$Z$1126,7,FALSE),"") -> 6.275 | AJ8: =iferror(VLOOKUP($B8,covariates!$B$3:$Z$1126,14,FALSE),"") -> 0 | AK8: =iferror(VLOOKUP($B8,covariates!$B$3:$Z$1126,16,FALSE),"") -> 74 | AL8: =iferror(VLOOKUP($B8,covariates!$B$3:$Z$1126,18,FALSE),"") -> 24 | AM8: =iferror(VLOOKUP($B8,covariates!$B$3:$Z$1126,19,FALSE),"") -> 2
A9: 43 | B9: =HYPERLINK("https://github.com/d-wkim/phd/blob/main/data/pdf/kautzner_2015.pdf","Kautzner et al., 2015") -> Kautzner et al., 2015 | C9: HT | D9: graft rupture | E9: dichotomous | F9: 73 | G9: 2 | H9: =iferror(P_SD(F9,G9),"") -> 0.3008452 | AG9: Included | AH9: =iferror(VLOOKUP($B9,covariates!$B$3:$Z$1126,6,FALSE),"") -> 26 | AI9: =iferror(VLOOKUP($B9,covariates!$B$3:$Z$1126,7,FALSE),"") -> 6.275 | AJ9: =iferror(VLOOKUP($B9,covariates!$B$3:$Z$1126,14,FALSE),"") -> 0 | AK9: =iferror(VLOOKUP($B9,covariates!$B$3:$Z$1126,16,FALSE),"") -> 74 | AL9: =iferror(VLOOKUP($B9,covariates!$B$3:$Z$1126,18,FALSE),"") -> 24 | AM9: =iferror(VLOOKUP($B9,covariates!$B$3:$Z$1126,19,FALSE),"") -> 2
A10: 49 | B10: =HYPERLINK("https://github.com/d-wkim/phd/blob/main/data/pdf/laxdal_2005.pdf","Laxdal et al., 2005") -> Laxdal et al., 2005 | C10: BPTB | D10: graft rupture | E10: dichotomous | F10: 40 | G10: 1 | H10: =iferror(P_SD(F10,G10),"") -> 0.24325213 | AG10: Included | AH10: =iferror(VLOOKUP($B10,covariates!$B$3:$Z$1126,6,FALSE),"") -> 28 | AI10: =iferror(VLOOKUP($B10,covariates!$B$3:$Z$1126,7,FALSE),"") -> 8.347 | AJ10: =iferror(VLOOKUP($B10,covariates!$B$3:$Z$1126,14,FALSE),"") | AK10: =iferror(VLOOKUP($B10,covariates!$B$3:$Z$1126,16,FALSE),"") | AL10: =iferror(VLOOKUP($B10,covariates!$B$3:$Z$1126,18,FALSE),"") -> 26 | AM10: =iferror(VLOOKUP($B10,covariates!$B$3:$Z$1126,19,FALSE),"") -> 2.2
A11: 49 | B11: =HYPERLINK("https://github.com/d-wkim/phd/blob/main/data/pdf/laxdal_2005.pdf","Laxdal et al., 2005") -> Laxdal et al., 2005 | C11: HT | D11: graft rupture | E11: dichotomous | F11: 78 | G11: 2 | H11: 0.42059596 | AG11: Included | AH11: =iferror(VLOOKUP($B11,covariates!$B$3:$Z$1126,6,FALSE),"") -> 28 | AI11: =iferror(VLOOKUP($B11,covariates!$B$3:$Z$1126,7,FALSE),"") -> 8.347 | AJ11: =iferror(VLOOKUP($B11,covariates!$B$3:$Z$1126,14,FALSE),"") | AK11: =iferror(VLOOKUP($B11,covariates!$B$3:$Z$1126,16,FALSE),"") | AL11: =iferror(VLOOKUP($B11,covariates!$B$3:$Z$1126,18,FALSE),"") -> 26 | AM11: =iferror(VLOOKUP($B11,covariates!$B$3:$Z$1126,19,FALSE),"") -> 2.2
A12: 54 | B12: =HYPERLINK("https://github.com/d-wkim/phd/blob/main/data/pdf/lucidi_2025.pdf","Lucidi et al., 2025") -> Lucidi et al., 2025 | C12: BPTB | D12: graft rupture | E12: dichotomous | F12: 19 | G12: 7 | H12: =iferror(P_SD(F12,G12),"") -> 2.7243118 | AG12: Included | AH12: =iferror(VLOOKUP($B12,covariates!$B$3:$Z$1126,6,FALSE),"") -> 52.8 | AI12: =iferror(VLOOKUP($B12,covariates!$B$3:$Z$1126,7,FALSE),"") -> 7.3 | AJ12: =iferror(VLOOKUP($B12,covariates!$B$3:$Z$1126,14,FALSE),"") | AK12: =iferror(VLOOKUP($B12,covariates!$B$3:$Z$1126,16,FALSE),"") | AL12: =iferror(VLOOKUP($B12,covariates!$B$3:$Z$1126,18,FALSE),"") -> 240 | AM12: =iferror(VLOOKUP($B12,covariates!$B$3:$Z$1126,19,FALSE),"") -> 20
A13: 54 | B13: =HYPERLINK("https://github.com/d-wkim/phd/blob/main/data/pdf/lucidi_2025.pdf","Lucidi et al., 2025") -> Lucidi et al., 2025 | C13: HT | D13: graft rupture | E13: dichotomous | F13: 20 | G13: 3 | H13: =iferror(P_SD(F13,G13),"") -> 0.92073387 | AG13: Included | AH13: =iferror(VLOOKUP($B13,covariates!$B$3:$Z$1126,6,FALSE),"") -> 52.8 | AI13: =iferror(VLOOKUP($B13,covariates!$B$3:$Z$1126,7,FALSE),"") -> 7.3 | AJ13: =iferror(VLOOKUP($B13,covariates!$B$3:$Z$1126,14,FALSE),"") | AK13: =iferror(VLOOKUP($B13,covariates!$B$3:$Z$1126,16,FALSE),"") | AL13: =iferror(VLOOKUP($B13,covariates!$B$3:$Z$1126,18,FALSE),"") -> 240 | AM13: =iferror(VLOOKUP($B13,covariates!$B$3:$Z$1126,19,FALSE),"") -> 20
A14: 66 | B14: =HYPERLINK("https://github.com/d-wkim/phd/blob/main/data/pdf/mohtadi_2016a.pdf","Mohtadi et al., 2016") -> Mohtadi et al., 2016 | C14: BPTB | D14: graft rupture | E14: dichotomous | F14: 110 | G14: 19 | H14: =iferror(P_SD(F14,G14),"") -> 2.2474475 | AG14: Included | AH14: =iferror(VLOOKUP($B14,covariates!$B$3:$Z$1126,6,FALSE),"") -> 28.7 | AI14: =iferror(VLOOKUP($B14,covariates!$B$3:$Z$1126,7,FALSE),"") -> 9.9 | AJ14: =iferror(VLOOKUP($B14,covariates!$B$3:$Z$1126,14,FALSE),"") -> 63 | AK14: =iferror(VLOOKUP($B14,covariates!$B$3:$Z$1126,16,FALSE),"") -> 47 | AL14: =iferror(VLOOKUP($B14,covariates!$B$3:$Z$1126,18,FALSE),"") -> 24 | AM14: =iferror(VLOOKUP($B14,covariates!$B$3:$Z$1126,19,FALSE),"") -> 2
A15: 66 | B15: =HYPERLINK("https://github.com/d-wkim/phd/blob/main/data/pdf/mohtadi_2016a.pdf","Mohtadi et al., 2016") -> Mohtadi et al., 2016 | C15: HT | D15: graft rupture | E15: dichotomous | F15: 110 | G15: 24 | H15: =iferror(P_SD(F15,G15),"") -> 2.9878857 | AG15: Included | AH15: =iferror(VLOOKUP($B15,covariates!$B$3:$Z$1126,6,FALSE),"") -> 28.7 | AI15: =iferror(VLOOKUP($B15,covariates!$B$3:$Z$1126,7,FALSE),"") -> 9.9 | AJ15: =iferror(VLOOKUP($B15,covariates!$B$3:$Z$1126,14,FALSE),"") -> 63 | AK15: =iferror(VLOOKUP($B15,covariates!$B$3:$Z$1126,16,FALSE),"") -> 47 | AL15: =iferror(VLOOKUP($B15,covariates!$B$3:$Z$1126,18,FALSE),"") -> 24 | AM15: =iferror(VLOOKUP($B15,covariates!$B$3:$Z$1126,19,FALSE),"") -> 2
A16: 67 | B16: =HYPERLINK("https://github.com/d-wkim/phd/blob/main/data/pdf/mohtadi_chan_2019.pdf","Mohtadi & Chan, 2019") -> Mohtadi & Chan, 2019 | C16: BPTB | D16: graft rupture | E16: dichotomous | H16: =iferror(P_SD(F16,G16),"") | AG16: Excluded | AH16: =iferror(VLOOKUP($B16,covariates!$B$3:$Z$1126,6,FALSE),"") | AI16: =iferror(VLOOKUP($B16,covariates!$B$3:$Z$1126,7,FALSE),"") | AJ16: =iferror(VLOOKUP($B16,covariates!$B$3:$Z$1126,14,FALSE),"") | AK16: =iferror(VLOOKUP($B16,covariates!$B$3:$Z$1126,16,FALSE),"") | AL16: =iferror(VLOOKUP($B16,covariates!$B$3:$Z$1126,18,FALSE),"") | AM16: =iferror(VLOOKUP($B16,covariates!$B$3:$Z$1126,19,FALSE),"")
A17: 67 | B17: =HYPERLINK("https://github.com/d-wkim/phd/blob/main/data/pdf/mohtadi_chan_2019.pdf","Mohtadi & Chan, 2019") -> Mohtadi & Chan, 2019 | C17: HT | D17: graft rupture | E17: dichotomous | H17: =iferror(P_SD(F17,G17),"") | AG17: Excluded | AH17: =iferror(VLOOKUP($B17,covariates!$B$3:$Z$1126,6,FALSE),"") | AI17: =iferror(VLOOKUP($B17,covariates!$B$3:$Z$1126,7,FALSE),"") | AJ17: =iferror(VLOOKUP($B17,covariates!$B$3:$Z$1126,14,FALSE),"") | AK17: =iferror(VLOOKUP($B17,covariates!$B$3:$Z$1126,16,FALSE),"") | AL17: =iferror(VLOOKUP($B17,covariates!$B$3:$Z$1126,18,FALSE),"") | AM17: =iferror(VLOOKUP($B17,covariates!$B$3:$Z$1126,19,FALSE),"")
A18: 68 | B18: =HYPERLINK("https://github.com/d-wkim/phd/blob/main/data/pdf/moraiti_2010.pdf","Moraiti et al., 2010") -> Moraiti et al., 2010 | C18: BPTB | D18: graft rupture | E18: dichotomous | H18: =iferror(P_SD(F18,G18),"") | AG18: Excluded | AH18: =iferror(VLOOKUP($B18,covariates!$B$3:$Z$1126,6,FALSE),"") -> 23 | AI18: =iferror(VLOOKUP($B18,covariates!$B$3:$Z$1126,7,FALSE),"") -> 2 | AJ18: =iferror(VLOOKUP($B18,covariates!$B$3:$Z$1126,14,FALSE),"") -> 6 | AK18: =iferror(VLOOKUP($B18,covariates!$B$3:$Z$1126,16,FALSE),"") -> 0 | AL18: =iferror(VLOOKUP($B18,covariates!$B$3:$Z$1126,18,FALSE),"") -> 21 | AM18: =iferror(VLOOKUP($B18,covariates!$B$3:$Z$1126,19,FALSE),"") -> 1.8
A19: 68 | B19: =HYPERLINK("https://github.com/d-wkim/phd/blob/main/data/pdf/moraiti_2010.pdf","Moraiti et al., 2010") -> Moraiti et al., 2010 | C19: HT | D19: graft rupture | E19: dichotomous | H19: =iferror(P_SD(F19,G19),"") | AG19: Excluded | AH19: =iferror(VLOOKUP($B19,covariates!$B$3:$Z$1126,6,FALSE),"") -> 23 | AI19: =iferror(VLOOKUP($B19,covariates!$B$3:$Z$1126,7,FALSE),"") -> 2 | AJ19: =iferror(VLOOKUP($B19,covariates!$B$3:$Z$1126,14,FALSE),"") -> 6 | AK19: =iferror(VLOOKUP($B19,covariates!$B$3:$Z$1126,16,FALSE),"") -> 0 | AL19: =iferror(VLOOKUP($B19,covariates!$B$3:$Z$1126,18,FALSE),"") -> 21 | AM19: =iferror(VLOOKUP($B19,covariates!$B$3:$Z$1126,19,FALSE),"") -> 1.8
A20: 70 | B20: =HYPERLINK("https://github.com/d-wkim/phd/blob/main/data/pdf/noh_2011.pdf","Noh et al., 2011") -> Noh et al., 2011 | C20: HT | D20: graft rupture | E20: dichotomous | H20: =iferror(P_SD(F20,G20),"") | AG20: Excluded | AH20: =iferror(VLOOKUP($B20,covariates!$B$3:$Z$1126,6,FALSE),"") -> 25.813974 | AI20: =iferror(VLOOKUP($B20,covariates!$B$3:$Z$1126,7,FALSE),"") -> 7.455 | AJ20: =iferror(VLOOKUP($B20,covariates!$B$3:$Z$1126,14,FALSE),"") -> 30 | AK20: =iferror(VLOOKUP($B20,covariates!$B$3:$Z$1126,16,FALSE),"") -> 3 | AL20: =iferror(VLOOKUP($B20,covariates!$B$3:$Z$1126,18,FALSE),"") -> 28.1 | AM20: =iferror(VLOOKUP($B20,covariates!$B$3:$Z$1126,19,FALSE),"") -> 2.3
A21: 70 | B21: =HYPERLINK("https://github.com/d-wkim/phd/blob/main/data/pdf/noh_2011.pdf","Noh et al., 2011") -> Noh et al., 2011 | C21: AT | D21: graft rupture | E21: dichotomous | H21: =iferror(P_SD(F21,G21),"") | AG21: Excluded | AH21: =iferror(VLOOKUP($B21,covariates!$B$3:$Z$1126,6,FALSE),"") -> 25.813974 | AI21: =iferror(VLOOKUP($B21,covariates!$B$3:$Z$1126,7,FALSE),"") -> 7.455 | AJ21: =iferror(VLOOKUP($B21,covariates!$B$3:$Z$1126,14,FALSE),"") -> 30 | AK21: =iferror(VLOOKUP($B21,covariates!$B$3:$Z$1126,16,FALSE),"") -> 3 | AL21: =iferror(VLOOKUP($B21,covariates!$B$3:$Z$1126,18,FALSE),"") -> 28.1 | AM21: =iferror(VLOOKUP($B21,covariates!$B$3:$Z$1126,19,FALSE),"") -> 2.3
A22: 76 | B22: =HYPERLINK("https://github.com/d-wkim/phd/blob/main/data/pdf/pinczewski_2007.pdf","Pinczewski et al., 2007") -> Pinczewski et al., 2007 | C22: BPTB | D22: graft rupture | E22: dichotomous | F22: 90 | G22: 7 | H22: =iferror(P_SD(F22,G22),"") -> 0.85724394 | AG22: Included | AH22: =iferror(VLOOKUP($B22,covariates!$B$3:$Z$1126,6,FALSE),"") -> 25 | AI22: =iferror(VLOOKUP($B22,covariates!$B$3:$Z$1126,7,FALSE),"") -> 5.485 | AJ22: =iferror(VLOOKUP($B22,covariates!$B$3:$Z$1126,14,FALSE),"") -> 48 | AK22: =iferror(VLOOKUP($B22,covariates!$B$3:$Z$1126,16,FALSE),"") -> 42 | AL22: =iferror(VLOOKUP($B22,covariates!$B$3:$Z$1126,18,FALSE),"") -> 120 | AM22: =iferror(VLOOKUP($B22,covariates!$B$3:$Z$1126,19,FALSE),"") -> 10
A23: 76 | B23: =HYPERLINK("https://github.com/d-wkim/phd/blob/main/data/pdf/pinczewski_2007.pdf","Pinczewski et al., 2007") -> Pinczewski et al., 2007 | C23: HT | D23: graft rupture | E23: dichotomous | F23: 90 | G23: 12 | H23: =iferror(P_SD(F23,G23),"") -> 1.5203258 | AG23: Included | AH23: =iferror(VLOOKUP($B23,covariates!$B$3:$Z$1126,6,FALSE),"") -> 25 | AI23: =iferror(VLOOKUP($B23,covariates!$B$3:$Z$1126,7,FALSE),"") -> 5.485 | AJ23: =iferror(VLOOKUP($B23,covariates!$B$3:$Z$1126,14,FALSE),"") -> 48 | AK23: =iferror(VLOOKUP($B23,covariates!$B$3:$Z$1126,16,FALSE),"") -> 42 | AL23: =iferror(VLOOKUP($B23,covariates!$B$3:$Z$1126,18,FALSE),"") -> 120 | AM23: =iferror(VLOOKUP($B23,covariates!$B$3:$Z$1126,19,FALSE),"") -> 10
A24: 77 | B24: =HYPERLINK("https://github.com/d-wkim/phd/blob/main/data/pdf/popovic_2024.pdf","Popovic et al., 2024") -> Popovic et al., 2024 | C24: BPTB | D24: graft rupture | E24: dichotomous | F24: 38 | G24: 3 | H24: =iferror(P_SD(F24,G24),"") -> 0.6164414 | AG24: Included | AH24: =iferror(VLOOKUP($B24,covariates!$B$3:$Z$1126,6,FALSE),"") -> 27 | AI24: =iferror(VLOOKUP($B24,covariates!$B$3:$Z$1126,7,FALSE),"") -> 6.82 | AJ24: =iferror(VLOOKUP($B24,covariates!$B$3:$Z$1126,14,FALSE),"") | AK24: =iferror(VLOOKUP($B24,covariates!$B$3:$Z$1126,16,FALSE),"") | AL24: =iferror(VLOOKUP($B24,covariates!$B$3:$Z$1126,18,FALSE),"") -> 228 | AM24: =iferror(VLOOKUP($B24,covariates!$B$3:$Z$1126,19,FALSE),"") -> 19
A25: 77 | B25: =HYPERLINK("https://github.com/d-wkim/phd/blob/main/data/pdf/popovic_2024.pdf","Popovic et al., 2024") -> Popovic et al., 2024 | C25: HT | D25: graft rupture | E25: dichotomous | F25: 33 | G25: 4 | H25: =iferror(P_SD(F25,G25),"") -> 0.89139765 | AG25: Included | AH25: =iferror(VLOOKUP($B25,covariates!$B$3:$Z$1126,6,FALSE),"") -> 27 | AI25: =iferror(VLOOKUP($B25,covariates!$B$3:$Z$1126,7,FALSE),"") -> 6.82 | AJ25: =iferror(VLOOKUP($B25,covariates!$B$3:$Z$1126,14,FALSE),"") | AK25: =iferror(VLOOKUP($B25,covariates!$B$3:$Z$1126,16,FALSE),"") | AL25: =iferror(VLOOKUP($B25,covariates!$B$3:$Z$1126,18,FALSE),"") -> 228 | AM25: =iferror(VLOOKUP($B25,covariates!$B$3:$Z$1126,19,FALSE),"") -> 19
A26: 85 | B26: =HYPERLINK("https://github.com/d-wkim/phd/blob/main/data/pdf/smith_2020.pdf","Smith et al., 2020") -> Smith et al., 2020 | C26: BPTB | D26: graft rupture | E26: dichotomous | F26: 32 | G26: 0 | H26: =iferror(P_SD(F26,G26),"") -> 0.088388348 | AG26: Included | AH26: =iferror(VLOOKUP($B26,covariates!$B$3:$Z$1126,6,FALSE),"") -> 17.7 | AI26: =iferror(VLOOKUP($B26,covariates!$B$3:$Z$1126,7,FALSE),"") -> 2.4 | AJ26: =iferror(VLOOKUP($B26,covariates!$B$3:$Z$1126,14,FALSE),"") -> 15 | AK26: =iferror(VLOOKUP($B26,covariates!$B$3:$Z$1126,16,FALSE),"") -> 17 | AL26: =iferror(VLOOKUP($B26,covariates!$B$3:$Z$1126,18,FALSE),"") -> 24 | AM26: =iferror(VLOOKUP($B26,covariates!$B$3:$Z$1126,19,FALSE),"") -> 2
A27: 85 | B27: =HYPERLINK("https://github.com/d-wkim/phd/blob/main/data/pdf/smith_2020.pdf","Smith et al., 2020") -> Smith et al., 2020 | C27: HT | D27: graft rupture | E27: dichotomous | F27: 32 | G27: 2 | H27: =iferror(P_SD(F27,G27),"") -> 0.47140452 | AG27: Included | AH27: =iferror(VLOOKUP($B27,covariates!$B$3:$Z$1126,6,FALSE),"") -> 17.7 | AI27: =iferror(VLOOKUP($B27,covariates!$B$3:$Z$1126,7,FALSE),"") -> 2.4 | AJ27: =iferror(VLOOKUP($B27,covariates!$B$3:$Z$1126,14,FALSE),"") -> 15 | AK27: =iferror(VLOOKUP($B27,covariates!$B$3:$Z$1126,16,FALSE),"") -> 17 | AL27: =iferror(VLOOKUP($B27,covariates!$B$3:$Z$1126,18,FALSE),"") -> 24 | AM27: =iferror(VLOOKUP($B27,covariates!$B$3:$Z$1126,19,FALSE),"") -> 2
A28: 87 | B28: =HYPERLINK("https://github.com/d-wkim/phd/blob/main/data/pdf/sonnery-cottet_2026.pdf","Sonnery-cottet et al., 2026") -> Sonnery-cottet et al., 2026 | C28: BPTB | D28: graft rupture | E28: dichotomous | F28: 273 | G28: 12 | H28: =iferror(P_SD(F28,G28),"") -> 0.79131761 | AG28: Included | AH28: =iferror(VLOOKUP($B28,covariates!$B$3:$Z$1126,6,FALSE),"") -> 24.8 | AI28: =iferror(VLOOKUP($B28,covariates!$B$3:$Z$1126,7,FALSE),"") -> 4.4 | AJ28: =iferror(VLOOKUP($B28,covariates!$B$3:$Z$1126,14,FALSE),"") -> 214 | AK28: =iferror(VLOOKUP($B28,covariates!$B$3:$Z$1126,16,FALSE),"") -> 69 | AL28: =iferror(VLOOKUP($B28,covariates!$B$3:$Z$1126,18,FALSE),"") -> 61.5 | AM28: =iferror(VLOOKUP($B28,covariates!$B$3:$Z$1126,19,FALSE),"") -> 5.1
A29: 87 | B29: =HYPERLINK("https://github.com/d-wkim/phd/blob/main/data/pdf/sonnery-cottet_2026.pdf","Sonnery-cottet et al., 2026") -> Sonnery-cottet et al., 2026 | C29: HT | D29: graft rupture | E29: dichotomous | F29: 283 | G29: 12 | H29: =iferror(P_SD(F29,G29),"") -> 0.77595036 | AG29: Included | AH29: =iferror(VLOOKUP($B29,covariates!$B$3:$Z$1126,6,FALSE),"") -> 24.8 | AI29: =iferror(VLOOKUP($B29,covariates!$B$3:$Z$1126,7,FALSE),"") -> 4.4 | AJ29: =iferror(VLOOKUP($B29,covariates!$B$3:$Z$1126,14,FALSE),"") -> 214 | AK29: =iferror(VLOOKUP($B29,covariates!$B$3:$Z$1126,16,FALSE),"") -> 69 | AL29: =iferror(VLOOKUP($B29,covariates!$B$3:$Z$1126,18,FALSE),"") -> 61.5 | AM29: =iferror(VLOOKUP($B29,covariates!$B$3:$Z$1126,19,FALSE),"") -> 5.1
A30: 90 | B30: =HYPERLINK("https://github.com/d-wkim/phd/blob/main/data/pdf/taylor_2009.pdf","Taylor et al., 2009") -> Taylor et al., 2009 | C30: BPTB | D30: graft rupture | E30: dichotomous | F30: 32 | G30: 3 | H30: =iferror(P_SD(F30,G30),"") -> 0.68272379 | AG30: Included | AH30: =iferror(VLOOKUP($B30,covariates!$B$3:$Z$1126,6,FALSE),"") -> 21.7 | AI30: =iferror(VLOOKUP($B30,covariates!$B$3:$Z$1126,7,FALSE),"") -> 4.597 | AJ30: =iferror(VLOOKUP($B30,covariates!$B$3:$Z$1126,14,FALSE),"") -> 25 | AK30: =iferror(VLOOKUP($B30,covariates!$B$3:$Z$1126,16,FALSE),"") -> 7 | AL30: =iferror(VLOOKUP($B30,covariates!$B$3:$Z$1126,18,FALSE),"") -> 32.4 | AM30: =iferror(VLOOKUP($B30,covariates!$B$3:$Z$1126,19,FALSE),"") -> 2.7
A31: 90 | B31: =HYPERLINK("https://github.com/d-wkim/phd/blob/main/data/pdf/taylor_2009.pdf","Taylor et al., 2009") -> Taylor et al., 2009 | C31: HT | D31: graft rupture | E31: dichotomous | F31: 32 | G31: 4 | H31: =iferror(P_SD(F31,G31),"") -> 0.90913729 | AG31: Included | AH31: =iferror(VLOOKUP($B31,covariates!$B$3:$Z$1126,6,FALSE),"") -> 21.7 | AI31: =iferror(VLOOKUP($B31,covariates!$B$3:$Z$1126,7,FALSE),"") -> 4.597 | AJ31: =iferror(VLOOKUP($B31,covariates!$B$3:$Z$1126,14,FALSE),"") -> 25 | AK31: =iferror(VLOOKUP($B31,covariates!$B$3:$Z$1126,16,FALSE),"") -> 7 | AL31: =iferror(VLOOKUP($B31,covariates!$B$3:$Z$1126,18,FALSE),"") -> 32.4 | AM31: =iferror(VLOOKUP($B31,covariates!$B$3:$Z$1126,19,FALSE),"") -> 2.7
A32: 96 | B32: =HYPERLINK("https://github.com/d-wkim/phd/blob/main/data/pdf/wipfler_2011.pdf","Wipfler et al., 2011") -> Wipfler et al., 2011 | C32: BPTB | D32: graft rupture | E32: dichotomous | F32: 29 | G32: 3 | H32: =iferror(P_SD(F32,G32),"") -> 0.72492603 | AG32: Included | AH32: =iferror(VLOOKUP($B32,covariates!$B$3:$Z$1126,6,FALSE),"") -> 29.87 | AI32: =iferror(VLOOKUP($B32,covariates!$B$3:$Z$1126,7,FALSE),"") -> 7.304 | AJ32: =iferror(VLOOKUP($B32,covariates!$B$3:$Z$1126,14,FALSE),"") -> 19 | AK32: =iferror(VLOOKUP($B32,covariates!$B$3:$Z$1126,16,FALSE),"") -> 12 | AL32: =iferror(VLOOKUP($B32,covariates!$B$3:$Z$1126,18,FALSE),"") -> 108 | AM32: =iferror(VLOOKUP($B32,covariates!$B$3:$Z$1126,19,FALSE),"") -> 9
A33: 96 | B33: =HYPERLINK("https://github.com/d-wkim/phd/blob/main/data/pdf/wipfler_2011.pdf","Wipfler et al., 2011") -> Wipfler et al., 2011 | C33: HT | D33: graft rupture | E33: dichotomous | F33: 25 | G33: 3 | H33: =iferror(P_SD(F33,G33),"") -> 0.79545455 | AG33: Included | AH33: =iferror(VLOOKUP($B33,covariates!$B$3:$Z$1126,6,FALSE),"") -> 29.87 | AI33: =iferror(VLOOKUP($B33,covariates!$B$3:$Z$1126,7,FALSE),"") -> 7.304 | AJ33: =iferror(VLOOKUP($B33,covariates!$B$3:$Z$1126,14,FALSE),"") -> 19 | AK33: =iferror(VLOOKUP($B33,covariates!$B$3:$Z$1126,16,FALSE),"") -> 12 | AL33: =iferror(VLOOKUP($B33,covariates!$B$3:$Z$1126,18,FALSE),"") -> 108 | AM33: =iferror(VLOOKUP($B33,covariates!$B$3:$Z$1126,19,FALSE),"") -> 9
A34: 97 | B34: =HYPERLINK("https://github.com/d-wkim/phd/blob/main/data/pdf/yadav_2025.pdf","Yadav et al., 2025") -> Yadav et al., 2025 | C34: HT | D34: graft rupture | E34: dichotomous | F34: 36 | G34: 1 | H34: =iferror(P_SD(F34,G34),"") -> 0.25714286 | AG34: Included | AH34: =iferror(VLOOKUP($B34,covariates!$B$3:$Z$1126,6,FALSE),"") -> 30.06 | AI34: =iferror(VLOOKUP($B34,covariates!$B$3:$Z$1126,7,FALSE),"") -> 8.87 | AJ34: =iferror(VLOOKUP($B34,covariates!$B$3:$Z$1126,14,FALSE),"") -> 32 | AK34: =iferror(VLOOKUP($B34,covariates!$B$3:$Z$1126,16,FALSE),"") -> 4 | AL34: =iferror(VLOOKUP($B34,covariates!$B$3:$Z$1126,18,FALSE),"") -> 12 | AM34: =iferror(VLOOKUP($B34,covariates!$B$3:$Z$1126,19,FALSE),"") -> 1
A35: 97 | B35: =HYPERLINK("https://github.com/d-wkim/phd/blob/main/data/pdf/yadav_2025.pdf","Yadav et al., 2025") -> Yadav et al., 2025 | C35: QT | D35: graft rupture | E35: dichotomous | F35: 33 | G35: 0 | H35: =iferror(P_SD(F35,G35),"") -> 0.087038828 | AG35: Included | AH35: =iferror(VLOOKUP($B35,covariates!$B$3:$Z$1126,6,FALSE),"") -> 30.06 | AI35: =iferror(VLOOKUP($B35,covariates!$B$3:$Z$1126,7,FALSE),"") -> 8.87 | AJ35: =iferror(VLOOKUP($B35,covariates!$B$3:$Z$1126,14,FALSE),"") -> 32 | AK35: =iferror(VLOOKUP($B35,covariates!$B$3:$Z$1126,16,FALSE),"") -> 4 | AL35: =iferror(VLOOKUP($B35,covariates!$B$3:$Z$1126,18,FALSE),"") -> 12 | AM35: =iferror(VLOOKUP($B35,covariates!$B$3:$Z$1126,19,FALSE),"") -> 1
A36: 3 | B36: =HYPERLINK("https://github.com/d-wkim/phd/blob/main/data/pdf/ahldén_2009.pdf","Ahldén et al., 2009") -> Ahldén et al., 2009 | C36: BPTB | D36: ikdc_objective | E36: dichotomous | O36: 26 | AG36: Excluded | AH36: =iferror(VLOOKUP($B36,covariates!$B$3:$Z$1126,6,FALSE),"") -> 27.412608 | AI36: =iferror(VLOOKUP($B36,covariates!$B$3:$Z$1126,7,FALSE),"") -> 8.902 | AJ36: =iferror(VLOOKUP($B36,covariates!$B$3:$Z$1126,14,FALSE),"") -> 14 | AK36: =iferror(VLOOKUP($B36,covariates!$B$3:$Z$1126,16,FALSE),"") -> 8 | AL36: =iferror(VLOOKUP($B36,covariates!$B$3:$Z$1126,18,FALSE),"") -> 90.271348 | AM36: =iferror(VLOOKUP($B36,covariates!$B$3:$Z$1126,19,FALSE),"") -> 7.5
A37: 3 | B37: =HYPERLINK("https://github.com/d-wkim/phd/blob/main/data/pdf/ahldén_2009.pdf","Ahldén et al., 2009") -> Ahldén et al., 2009 | C37: HT | D37: ikdc_objective | E37: dichotomous | O37: 29 | AG37: Excluded | AH37: =iferror(VLOOKUP($B37,covariates!$B$3:$Z$1126,6,FALSE),"") -> 27.412608 | AI37: =iferror(VLOOKUP($B37,covariates!$B$3:$Z$1126,7,FALSE),"") -> 8.902 | AJ37: =iferror(VLOOKUP($B37,covariates!$B$3:$Z$1126,14,FALSE),"") -> 14 | AK37: =iferror(VLOOKUP($B37,covariates!$B$3:$Z$1126,16,FALSE),"") -> 8 | AL37: =iferror(VLOOKUP($B37,covariates!$B$3:$Z$1126,18,FALSE),"") -> 90.271348 | AM37: =iferror(VLOOKUP($B37,covariates!$B$3:$Z$1126,19,FALSE),"") -> 7.5
A38: 5 | B38: =HYPERLINK("https://github.com/d-wkim/phd/blob/main/data/pdf/anderson_2001.pdf","Anderson et al., 2001") -> Anderson et al., 2001 | C38: BPTB | D38: ikdc_objective | E38: dichotomous | AG38: Excluded | AH38: =iferror(VLOOKUP($B38,covariates!$B$3:$Z$1126,6,FALSE),"") -> 23.6 | AI38: =iferror(VLOOKUP($B38,covariates!$B$3:$Z$1126,7,FALSE),"") -> 7.132 | AJ38: =iferror(VLOOKUP($B38,covariates!$B$3:$Z$1126,14,FALSE),"") -> 23 | AK38: =iferror(VLOOKUP($B38,covariates!$B$3:$Z$1126,16,FALSE),"") -> 12 | AL38: =iferror(VLOOKUP($B38,covariates!$B$3:$Z$1126,18,FALSE),"") -> 34.6 | AM38: =iferror(VLOOKUP($B38,covariates!$B$3:$Z$1126,19,FALSE),"") -> 2.9
A39: 5 | B39: =HYPERLINK("https://github.com/d-wkim/phd/blob/main/data/pdf/anderson_2001.pdf","Anderson et al., 2001") -> Anderson et al., 2001 | C39: HT | D39: ikdc_objective | E39: dichotomous | AG39: Excluded | AH39: =iferror(VLOOKUP($B39,covariates!$B$3:$Z$1126,6,FALSE),"") -> 23.6 | AI39: =iferror(VLOOKUP($B39,covariates!$B$3:$Z$1126,7,FALSE),"") -> 7.132 | AJ39: =iferror(VLOOKUP($B39,covariates!$B$3:$Z$1126,14,FALSE),"") -> 23 | AK39: =iferror(VLOOKUP($B39,covariates!$B$3:$Z$1126,16,FALSE),"") -> 12 | AL39: =iferror(VLOOKUP($B39,covariates!$B$3:$Z$1126,18,FALSE),"") -> 34.6 | AM39: =iferror(VLOOKUP($B39,covariates!$B$3:$Z$1126,19,FALSE),"") -> 2.9
A40: 11 | B40: =HYPERLINK("https://github.com/d-wkim/phd/blob/main/data/pdf/beynnon_2002.pdf","Beynnon et al., 2002") -> Beynnon et al., 2002 | C40: BPTB | D40: ikdc_objective | E40: dichotomous | AG40: Excluded | AH40: =iferror(VLOOKUP($B40,covariates!$B$3:$Z$1126,6,FALSE),"") -> 28.5 | AI40: =iferror(VLOOKUP($B40,covariates!$B$3:$Z$1126,7,FALSE),"") -> 6.959 | AJ40: =iferror(VLOOKUP($B40,covariates!$B$3:$Z$1126,14,FALSE),"") -> 18 | AK40: =iferror(VLOOKUP($B40,covariates!$B$3:$Z$1126,16,FALSE),"") -> 10 | AL40: =iferror(VLOOKUP($B40,covariates!$B$3:$Z$1126,18,FALSE),"") -> 36 | AM40: =iferror(VLOOKUP($B40,covariates!$B$3:$Z$1126,19,FALSE),"") -> 3
A41: 11 | B41: =HYPERLINK("https://github.com/d-wkim/phd/blob/main/data/pdf/beynnon_2002.pdf","Beynnon et al., 2002") -> Beynnon et al., 2002 | C41: HT | D41: ikdc_objective | E41: dichotomous | AG41: Excluded | AH41: =iferror(VLOOKUP($B41,covariates!$B$3:$Z$1126,6,FALSE),"") -> 28.5 | AI41: =iferror(VLOOKUP($B41,covariates!$B$3:$Z$1126,7,FALSE),"") -> 6.959 | AJ41: =iferror(VLOOKUP($B41,covariates!$B$3:$Z$1126,14,FALSE),"") -> 18 | AK41: =iferror(VLOOKUP($B41,covariates!$B$3:$Z$1126,16,FALSE),"") -> 10 | AL41: =iferror(VLOOKUP($B41,covariates!$B$3:$Z$1126,18,FALSE),"") -> 36 | AM41: =iferror(VLOOKUP($B41,covariates!$B$3:$Z$1126,19,FALSE),"") -> 3
A42: 26 | B42: =HYPERLINK("https://github.com/d-wkim/phd/blob/main/data/pdf/feller_webster_2003.pdf","Feller & Webster, 2003") -> Feller & Webster, 2003 | C42: BPTB | D42: ikdc_objective | E42: dichotomous | AG42: Excluded | AH42: =iferror(VLOOKUP($B42,covariates!$B$3:$Z$1126,6,FALSE),"") -> 25.8 | AI42: =iferror(VLOOKUP($B42,covariates!$B$3:$Z$1126,7,FALSE),"") -> 6 | AJ42: =iferror(VLOOKUP($B42,covariates!$B$3:$Z$1126,14,FALSE),"") -> 23 | AK42: =iferror(VLOOKUP($B42,covariates!$B$3:$Z$1126,16,FALSE),"") -> 8 | AL42: =iferror(VLOOKUP($B42,covariates!$B$3:$Z$1126,18,FALSE),"") -> 36 | AM42: =iferror(VLOOKUP($B42,covariates!$B$3:$Z$1126,19,FALSE),"") -> 3
A43: 26 | B43: =HYPERLINK("https://github.com/d-wkim/phd/blob/main/data/pdf/feller_webster_2003.pdf","Feller & Webster, 2003") -> Feller & Webster, 2003 | C43: HT | D43: ikdc_objective | E43: dichotomous | AG43: Excluded | AH43: =iferror(VLOOKUP($B43,covariates!$B$3:$Z$1126,6,FALSE),"") -> 25.8 | AI43: =iferror(VLOOKUP($B43,covariates!$B$3:$Z$1126,7,FALSE),"") -> 6 | AJ43: =iferror(VLOOKUP($B43,covariates!$B$3:$Z$1126,14,FALSE),"") -> 23 | AK43: =iferror(VLOOKUP($B43,covariates!$B$3:$Z$1126,16,FALSE),"") -> 8 | AL43: =iferror(VLOOKUP($B43,covariates!$B$3:$Z$1126,18,FALSE),"") -> 36 | AM43: =iferror(VLOOKUP($B43,covariates!$B$3:$Z$1126,19,FALSE),"") -> 3
A44: 31 | B44: =HYPERLINK("https://github.com/d-wkim/phd/blob/main/data/pdf/gobbi_francisco_2006.pdf","Gobbi & Francisco, 2006") -> Gobbi & Francisco, 2006 | C44: BPTB | D44: ikdc_objective | E44: dichotomous | AG44: Excluded | AH44: =iferror(VLOOKUP($B44,covariates!$B$3:$Z$1126,6,FALSE),"") | AI44: =iferror(VLOOKUP($B44,covariates!$B$3:$Z$1126,7,FALSE),"") | AJ44: =iferror(VLOOKUP($B44,covariates!$B$3:$Z$1126,14,FALSE),"") | AK44: =iferror(VLOOKUP($B44,covariates!$B$3:$Z$1126,16,FALSE),"") | AL44: =iferror(VLOOKUP($B44,covariates!$B$3:$Z$1126,18,FALSE),"") | AM44: =iferror(VLOOKUP($B44,covariates!$B$3:$Z$1126,19,FALSE),"")
A45: 31 | B45: =HYPERLINK("https://github.com/d-wkim/phd/blob/main/data/pdf/gobbi_francisco_2006.pdf","Gobbi & Francisco, 2006") -> Gobbi & Francisco, 2006 | C45: HT | D45: ikdc_objective | E45: dichotomous | AG45: Excluded | AH45: =iferror(VLOOKUP($B45,covariates!$B$3:$Z$1126,6,FALSE),"") | AI45: =iferror(VLOOKUP($B45,covariates!$B$3:$Z$1126,7,FALSE),"") | AJ45: =iferror(VLOOKUP($B45,covariates!$B$3:$Z$1126,14,FALSE),"") | AK45: =iferror(VLOOKUP($B45,covariates!$B$3:$Z$1126,16,FALSE),"") | AL45: =iferror(VLOOKUP($B45,covariates!$B$3:$Z$1126,18,FALSE),"") | AM45: =iferror(VLOOKUP($B45,covariates!$B$3:$Z$1126,19,FALSE),"")
A46: 33 | B46: =HYPERLINK("https://github.com/d-wkim/phd/blob/main/data/pdf/harilainen_2006.pdf","Harilainen et al., 2006") -> Harilainen et al., 2006 | C46: BPTB | D46: ikdc_objective | E46: dichotomous | AG46: Excluded | AH46: =iferror(VLOOKUP($B46,covariates!$B$3:$Z$1126,6,FALSE),"") | AI46: =iferror(VLOOKUP($B46,covariates!$B$3:$Z$1126,7,FALSE),"") | AJ46: =iferror(VLOOKUP($B46,covariates!$B$3:$Z$1126,14,FALSE),"") | AK46: =iferror(VLOOKUP($B46,covariates!$B$3:$Z$1126,16,FALSE),"") | AL46: =iferror(VLOOKUP($B46,covariates!$B$3:$Z$1126,18,FALSE),"") -> 60.6 | AM46: =iferror(VLOOKUP($B46,covariates!$B$3:$Z$1126,19,FALSE),"") -> 5.1
A47: 33 | B47: =HYPERLINK("https://github.com/d-wkim/phd/blob/main/data/pdf/harilainen_2006.pdf","Harilainen et al., 2006") -> Harilainen et al., 2006 | C47: HT | D47: ikdc_objective | E47: dichotomous | AG47: Excluded | AH47: =iferror(VLOOKUP($B47,covariates!$B$3:$Z$1126,6,FALSE),"") | AI47: =iferror(VLOOKUP($B47,covariates!$B$3:$Z$1126,7,FALSE),"") | AJ47: =iferror(VLOOKUP($B47,covariates!$B$3:$Z$1126,14,FALSE),"") | AK47: =iferror(VLOOKUP($B47,covariates!$B$3:$Z$1126,16,FALSE),"") | AL47: =iferror(VLOOKUP($B47,covariates!$B$3:$Z$1126,18,FALSE),"") -> 60.6 | AM47: =iferror(VLOOKUP($B47,covariates!$B$3:$Z$1126,19,FALSE),"") -> 5.1
A48: 45 | B48: =HYPERLINK("https://github.com/d-wkim/phd/blob/main/data/pdf/konrads_2016.pdf","Konrads et al., 2016") -> Konrads et al., 2016 | C48: BPTB | D48: ikdc_objective | E48: dichotomous | AG48: Excluded | AH48: =iferror(VLOOKUP($B48,covariates!$B$3:$Z$1126,6,FALSE),"") -> 29.8 | AI48: =iferror(VLOOKUP($B48,covariates!$B$3:$Z$1126,7,FALSE),"") -> 6.33 | AJ48: =iferror(VLOOKUP($B48,covariates!$B$3:$Z$1126,14,FALSE),"") -> 22 | AK48: =iferror(VLOOKUP($B48,covariates!$B$3:$Z$1126,16,FALSE),"") -> 9 | AL48: =iferror(VLOOKUP($B48,covariates!$B$3:$Z$1126,18,FALSE),"") -> 120 | AM48: =iferror(VLOOKUP($B48,covariates!$B$3:$Z$1126,19,FALSE),"") -> 10
A49: 45 | B49: =HYPERLINK("https://github.com/d-wkim/phd/blob/main/data/pdf/konrads_2016.pdf","Konrads et al., 2016") -> Konrads et al., 2016 | C49: HT | D49: ikdc_objective | E49: dichotomous | AG49: Excluded | AH49: =iferror(VLOOKUP($B49,covariates!$B$3:$Z$1126,6,FALSE),"") -> 29.8 | AI49: =iferror(VLOOKUP($B49,covariates!$B$3:$Z$1126,7,FALSE),"") -> 6.33 | AJ49: =iferror(VLOOKUP($B49,covariates!$B$3:$Z$1126,14,FALSE),"") -> 22 | AK49: =iferror(VLOOKUP($B49,covariates!$B$3:$Z$1126,16,FALSE),"") -> 9 | AL49: =iferror(VLOOKUP($B49,covariates!$B$3:$Z$1126,18,FALSE),"") -> 120 | AM49: =iferror(VLOOKUP($B49,covariates!$B$3:$Z$1126,19,FALSE),"") -> 10
A50: 46 | B50: =HYPERLINK("https://github.com/d-wkim/phd/blob/main/data/pdf/laoruengthana_2009.pdf","Laoruengthana et al., 2009") -> Laoruengthana et al., 2009 | C50: BPTB | D50: ikdc_objective | E50: dichotomous | AG50: Excluded | AH50: =iferror(VLOOKUP($B50,covariates!$B$3:$Z$1126,6,FALSE),"") -> 29.93 | AI50: =iferror(VLOOKUP($B50,covariates!$B$3:$Z$1126,7,FALSE),"") -> 8.911 | AJ50: =iferror(VLOOKUP($B50,covariates!$B$3:$Z$1126,14,FALSE),"") | AK50: =iferror(VLOOKUP($B50,covariates!$B$3:$Z$1126,16,FALSE),"") | AL50: =iferror(VLOOKUP($B50,covariates!$B$3:$Z$1126,18,FALSE),"") -> 19 | AM50: =iferror(VLOOKUP($B50,covariates!$B$3:$Z$1126,19,FALSE),"") -> 1.6
A51: 46 | B51: =HYPERLINK("https://github.com/d-wkim/phd/blob/main/data/pdf/laoruengthana_2009.pdf","Laoruengthana et al., 2009") -> Laoruengthana et al., 2009 | C51: HT | D51: ikdc_objective | E51: dichotomous | AG51: Excluded | AH51: =iferror(VLOOKUP($B51,covariates!$B$3:$Z$1126,6,FALSE),"") -> 29.93 | AI51: =iferror(VLOOKUP($B51,covariates!$B$3:$Z$1126,7,FALSE),"") -> 8.911 | AJ51: =iferror(VLOOKUP($B51,covariates!$B$3:$Z$1126,14,FALSE),"") | AK51: =iferror(VLOOKUP($B51,covariates!$B$3:$Z$1126,16,FALSE),"") | AL51: =iferror(VLOOKUP($B51,covariates!$B$3:$Z$1126,18,FALSE),"") -> 19 | AM51: =iferror(VLOOKUP($B51,covariates!$B$3:$Z$1126,19,FALSE),"") -> 1.6
A52: 47 | B52: =HYPERLINK("https://github.com/d-wkim/phd/blob/main/data/pdf/lawhorn_2012.pdf","Lawhorn et al., 2012") -> Lawhorn et al., 2012 | C52: HT | D52: ikdc_objective | E52: dichotomous | AG52: Excluded | AH52: =iferror(VLOOKUP($B52,covariates!$B$3:$Z$1126,6,FALSE),"") -> 32 | AI52: =iferror(VLOOKUP($B52,covariates!$B$3:$Z$1126,7,FALSE),"") -> 8.433 | AJ52: =iferror(VLOOKUP($B52,covariates!$B$3:$Z$1126,14,FALSE),"") -> 32 | AK52: =iferror(VLOOKUP($B52,covariates!$B$3:$Z$1126,16,FALSE),"") -> 22 | AL52: =iferror(VLOOKUP($B52,covariates!$B$3:$Z$1126,18,FALSE),"") -> 24 | AM52: =iferror(VLOOKUP($B52,covariates!$B$3:$Z$1126,19,FALSE),"") -> 2
A53: 47 | B53: =HYPERLINK("https://github.com/d-wkim/phd/blob/main/data/pdf/lawhorn_2012.pdf","Lawhorn et al., 2012") -> Lawhorn et al., 2012 | C53: TA | D53: ikdc_objective | E53: dichotomous | AG53: Excluded | AH53: =iferror(VLOOKUP($B53,covariates!$B$3:$Z$1126,6,FALSE),"") -> 32 | AI53: =iferror(VLOOKUP($B53,covariates!$B$3:$Z$1126,7,FALSE),"") -> 8.433 | AJ53: =iferror(VLOOKUP($B53,covariates!$B$3:$Z$1126,14,FALSE),"") -> 32 | AK53: =iferror(VLOOKUP($B53,covariates!$B$3:$Z$1126,16,FALSE),"") -> 22 | AL53: =iferror(VLOOKUP($B53,covariates!$B$3:$Z$1126,18,FALSE),"") -> 24 | AM53: =iferror(VLOOKUP($B53,covariates!$B$3:$Z$1126,19,FALSE),"") -> 2
A54: 49 | B54: =HYPERLINK("https://github.com/d-wkim/phd/blob/main/data/pdf/laxdal_2005.pdf","Laxdal et al., 2005") -> Laxdal et al., 2005 | C54: BPTB | D54: ikdc_objective | E54: dichotomous | AG54: Excluded | AH54: =iferror(VLOOKUP($B54,covariates!$B$3:$Z$1126,6,FALSE),"") -> 28 | AI54: =iferror(VLOOKUP($B54,covariates!$B$3:$Z$1126,7,FALSE),"") -> 8.347 | AJ54: =iferror(VLOOKUP($B54,covariates!$B$3:$Z$1126,14,FALSE),"") | AK54: =iferror(VLOOKUP($B54,covariates!$B$3:$Z$1126,16,FALSE),"") | AL54: =iferror(VLOOKUP($B54,covariates!$B$3:$Z$1126,18,FALSE),"") -> 26 | AM54: =iferror(VLOOKUP($B54,covariates!$B$3:$Z$1126,19,FALSE),"") -> 2.2
A55: 49 | B55: =HYPERLINK("https://github.com/d-wkim/phd/blob/main/data/pdf/laxdal_2005.pdf","Laxdal et al., 2005") -> Laxdal et al., 2005 | C55: HT | D55: ikdc_objective | E55: dichotomous | AG55: Excluded | AH55: =iferror(VLOOKUP($B55,covariates!$B$3:$Z$1126,6,FALSE),"") -> 28 | AI55: =iferror(VLOOKUP($B55,covariates!$B$3:$Z$1126,7,FALSE),"") -> 8.347 | AJ55: =iferror(VLOOKUP($B55,covariates!$B$3:$Z$1126,14,FALSE),"") | AK55: =iferror(VLOOKUP($B55,covariates!$B$3:$Z$1126,16,FALSE),"") | AL55: =iferror(VLOOKUP($B55,covariates!$B$3:$Z$1126,18,FALSE),"") -> 26 | AM55: =iferror(VLOOKUP($B55,covariates!$B$3:$Z$1126,19,FALSE),"") -> 2.2
A56: 52 | B56: =HYPERLINK("https://github.com/d-wkim/phd/blob/main/data/pdf/lidén_2007.pdf","Lidén et al., 2007") -> Lidén et al., 2007 | C56: BPTB | D56: ikdc_objective | E56: dichotomous | AG56: Excluded | AH56: =iferror(VLOOKUP($B56,covariates!$B$3:$Z$1126,6,FALSE),"") -> 28 | AI56: =iferror(VLOOKUP($B56,covariates!$B$3:$Z$1126,7,FALSE),"") -> 8.368 | AJ56: =iferror(VLOOKUP($B56,covariates!$B$3:$Z$1126,14,FALSE),"") -> 23 | AK56: =iferror(VLOOKUP($B56,covariates!$B$3:$Z$1126,16,FALSE),"") -> 11 | AL56: =iferror(VLOOKUP($B56,covariates!$B$3:$Z$1126,18,FALSE),"") -> 87.106182 | AM56: =iferror(VLOOKUP($B56,covariates!$B$3:$Z$1126,19,FALSE),"") -> 7.3
A57: 52 | B57: =HYPERLINK("https://github.com/d-wkim/phd/blob/main/data/pdf/lidén_2007.pdf","Lidén et al., 2007") -> Lidén et al., 2007 | C57: HT | D57: ikdc_objective | E57: dichotomous | AG57: Excluded | AH57: =iferror(VLOOKUP($B57,covariates!$B$3:$Z$1126,6,FALSE),"") -> 28 | AI57: =iferror(VLOOKUP($B57,covariates!$B$3:$Z$1126,7,FALSE),"") -> 8.368 | AJ57: =iferror(VLOOKUP($B57,covariates!$B$3:$Z$1126,14,FALSE),"") -> 23 | AK57: =iferror(VLOOKUP($B57,covariates!$B$3:$Z$1126,16,FALSE),"") -> 11 | AL57: =iferror(VLOOKUP($B57,covariates!$B$3:$Z$1126,18,FALSE),"") -> 87.106182 | AM57: =iferror(VLOOKUP($B57,covariates!$B$3:$Z$1126,19,FALSE),"") -> 7.3
A58: 57 | B58: =HYPERLINK("https://github.com/d-wkim/phd/blob/main/data/pdf/maletis_2007.pdf","Maletis et al., 2007") -> Maletis et al., 2007 | C58: BPTB | D58: ikdc_objective | E58: dichotomous | AG58: Excluded | AH58: =iferror(VLOOKUP($B58,covariates!$B$3:$Z$1126,6,FALSE),"") | AI58: =iferror(VLOOKUP($B58,covariates!$B$3:$Z$1126,7,FALSE),"") | AJ58: =iferror(VLOOKUP($B58,covariates!$B$3:$Z$1126,14,FALSE),"") | AK58: =iferror(VLOOKUP($B58,covariates!$B$3:$Z$1126,16,FALSE),"") | AL58: =iferror(VLOOKUP($B58,covariates!$B$3:$Z$1126,18,FALSE),"") | AM58: =iferror(VLOOKUP($B58,covariates!$B$3:$Z$1126,19,FALSE),"")
A59: 57 | B59: =HYPERLINK("https://github.com/d-wkim/phd/blob/main/data/pdf/maletis_2007.pdf","Maletis et al., 2007") -> Maletis et al., 2007 | C59: HT | D59: ikdc_objective | E59: dichotomous | AG59: Excluded | AH59: =iferror(VLOOKUP($B59,covariates!$B$3:$Z$1126,6,FALSE),"") | AI59: =iferror(VLOOKUP($B59,covariates!$B$3:$Z$1126,7,FALSE),"") | AJ59: =iferror(VLOOKUP($B59,covariates!$B$3:$Z$1126,14,FALSE),"") | AK59: =iferror(VLOOKUP($B59,covariates!$B$3:$Z$1126,16,FALSE),"") | AL59: =iferror(VLOOKUP($B59,covariates!$B$3:$Z$1126,18,FALSE),"") | AM59: =iferror(VLOOKUP($B59,covariates!$B$3:$Z$1126,19,FALSE),"")
A60: 67 | B60: =HYPERLINK("https://github.com/d-wkim/phd/blob/main/data/pdf/mohtadi_chan_2019.pdf","Mohtadi & Chan, 2019") -> Mohtadi & Chan, 2019 | C60: BPTB | D60: ikdc_objective | E60: dichotomous | AG60: Excluded | AH60: =iferror(VLOOKUP($B60,covariates!$B$3:$Z$1126,6,FALSE),"") | AI60: =iferror(VLOOKUP($B60,covariates!$B$3:$Z$1126,7,FALSE),"") | AJ60: =iferror(VLOOKUP($B60,covariates!$B$3:$Z$1126,14,FALSE),"") | AK60: =iferror(VLOOKUP($B60,covariates!$B$3:$Z$1126,16,FALSE),"") | AL60: =iferror(VLOOKUP($B60,covariates!$B$3:$Z$1126,18,FALSE),"") | AM60: =iferror(VLOOKUP($B60,covariates!$B$3:$Z$1126,19,FALSE),"")
A61: 67 | B61: =HYPERLINK("https://github.com/d-wkim/phd/blob/main/data/pdf/mohtadi_chan_2019.pdf","Mohtadi & Chan, 2019") -> Mohtadi & Chan, 2019 | C61: HT | D61: ikdc_objective | E61: dichotomous | AG61: Excluded | AH61: =iferror(VLOOKUP($B61,covariates!$B$3:$Z$1126,6,FALSE),"") | AI61: =iferror(VLOOKUP($B61,covariates!$B$3:$Z$1126,7,FALSE),"") | AJ61: =iferror(VLOOKUP($B61,covariates!$B$3:$Z$1126,14,FALSE),"") | AK61: =iferror(VLOOKUP($B61,covariates!$B$3:$Z$1126,16,FALSE),"") | AL61: =iferror(VLOOKUP($B61,covariates!$B$3:$Z$1126,18,FALSE),"") | AM61: =iferror(VLOOKUP($B61,covariates!$B$3:$Z$1126,19,FALSE),"")
A62: 70 | B62: =HYPERLINK("https://github.com/d-wkim/phd/blob/main/data/pdf/noh_2011.pdf","Noh et al., 2011") -> Noh et al., 2011 | C62: HT | D62: ikdc_objective | E62: dichotomous | AG62: Excluded | AH62: =iferror(VLOOKUP($B62,covariates!$B$3:$Z$1126,6,FALSE),"") -> 25.813974 | AI62: =iferror(VLOOKUP($B62,covariates!$B$3:$Z$1126,7,FALSE),"") -> 7.455 | AJ62: =iferror(VLOOKUP($B62,covariates!$B$3:$Z$1126,14,FALSE),"") -> 30 | AK62: =iferror(VLOOKUP($B62,covariates!$B$3:$Z$1126,16,FALSE),"") -> 3 | AL62: =iferror(VLOOKUP($B62,covariates!$B$3:$Z$1126,18,FALSE),"") -> 28.1 | AM62: =iferror(VLOOKUP($B62,covariates!$B$3:$Z$1126,19,FALSE),"") -> 2.3
A63: 70 | B63: =HYPERLINK("https://github.com/d-wkim/phd/blob/main/data/pdf/noh_2011.pdf","Noh et al., 2011") -> Noh et al., 2011 | C63: AT | D63: ikdc_objective | E63: dichotomous | AG63: Excluded | AH63: =iferror(VLOOKUP($B63,covariates!$B$3:$Z$1126,6,FALSE),"") -> 25.813974 | AI63: =iferror(VLOOKUP($B63,covariates!$B$3:$Z$1126,7,FALSE),"") -> 7.455 | AJ63: =iferror(VLOOKUP($B63,covariates!$B$3:$Z$1126,14,FALSE),"") -> 30 | AK63: =iferror(VLOOKUP($B63,covariates!$B$3:$Z$1126,16,FALSE),"") -> 3 | AL63: =iferror(VLOOKUP($B63,covariates!$B$3:$Z$1126,18,FALSE),"") -> 28.1 | AM63: =iferror(VLOOKUP($B63,covariates!$B$3:$Z$1126,19,FALSE),"") -> 2.3
A64: 72 | B64: =HYPERLINK("https://github.com/d-wkim/phd/blob/main/data/pdf/oneill_1996.pdf","Oneill et al., 1996") -> Oneill et al., 1996 | C64: BPTB | D64: ikdc_objective | E64: dichotomous | AG64: Excluded | AH64: =iferror(VLOOKUP($B64,covariates!$B$3:$Z$1126,6,FALSE),"") | AI64: =iferror(VLOOKUP($B64,covariates!$B$3:$Z$1126,7,FALSE),"") | AJ64: =iferror(VLOOKUP($B64,covariates!$B$3:$Z$1126,14,FALSE),"") | AK64: =iferror(VLOOKUP($B64,covariates!$B$3:$Z$1126,16,FALSE),"") | AL64: =iferror(VLOOKUP($B64,covariates!$B$3:$Z$1126,18,FALSE),"") | AM64: =iferror(VLOOKUP($B64,covariates!$B$3:$Z$1126,19,FALSE),"")
A65: 72 | B65: =HYPERLINK("https://github.com/d-wkim/phd/blob/main/data/pdf/oneill_1996.pdf","Oneill et al., 1996") -> Oneill et al., 1996 | C65: HT | D65: ikdc_objective | E65: dichotomous | AG65: Excluded | AH65: =iferror(VLOOKUP($B65,covariates!$B$3:$Z$1126,6,FALSE),"") | AI65: =iferror(VLOOKUP($B65,covariates!$B$3:$Z$1126,7,FALSE),"") | AJ65: =iferror(VLOOKUP($B65,covariates!$B$3:$Z$1126,14,FALSE),"") | AK65: =iferror(VLOOKUP($B65,covariates!$B$3:$Z$1126,16,FALSE),"") | AL65: =iferror(VLOOKUP($B65,covariates!$B$3:$Z$1126,18,FALSE),"") | AM65: =iferror(VLOOKUP($B65,covariates!$B$3:$Z$1126,19,FALSE),"")
A66: 76 | B66: =HYPERLINK("https://github.com/d-wkim/phd/blob/main/data/pdf/pinczewski_2007.pdf","Pinczewski et al., 2007") -> Pinczewski et al., 2007 | C66: BPTB | D66: ikdc_objective | E66: dichotomous | AG66: Excluded | AH66: =iferror(VLOOKUP($B66,covariates!$B$3:$Z$1126,6,FALSE),"") -> 25 | AI66: =iferror(VLOOKUP($B66,covariates!$B$3:$Z$1126,7,FALSE),"") -> 5.485 | AJ66: =iferror(VLOOKUP($B66,covariates!$B$3:$Z$1126,14,FALSE),"") -> 48 | AK66: =iferror(VLOOKUP($B66,covariates!$B$3:$Z$1126,16,FALSE),"") -> 42 | AL66: =iferror(VLOOKUP($B66,covariates!$B$3:$Z$1126,18,FALSE),"") -> 120 | AM66: =iferror(VLOOKUP($B66,covariates!$B$3:$Z$1126,19,FALSE),"") -> 10
A67: 76 | B67: =HYPERLINK("https://github.com/d-wkim/phd/blob/main/data/pdf/pinczewski_2007.pdf","Pinczewski et al., 2007") -> Pinczewski et al., 2007 | C67: HT | D67: ikdc_objective | E67: dichotomous | AG67: Excluded | AH67: =iferror(VLOOKUP($B67,covariates!$B$3:$Z$1126,6,FALSE),"") -> 25 | AI67: =iferror(VLOOKUP($B67,covariates!$B$3:$Z$1126,7,FALSE),"") -> 5.485 | AJ67: =iferror(VLOOKUP($B67,covariates!$B$3:$Z$1126,14,FALSE),"") -> 48 | AK67: =iferror(VLOOKUP($B67,covariates!$B$3:$Z$1126,16,FALSE),"") -> 42 | AL67: =iferror(VLOOKUP($B67,covariates!$B$3:$Z$1126,18,FALSE),"") -> 120 | AM67: =iferror(VLOOKUP($B67,covariates!$B$3:$Z$1126,19,FALSE),"") -> 10
A68: 82 | B68: =HYPERLINK("https://github.com/d-wkim/phd/blob/main/data/pdf/sajovic_2018.pdf","Sajovic et al., 2018") -> Sajovic et al., 2018 | C68: BPTB | D68: ikdc_objective | E68: dichotomous | H68: =iferror(RANGE_SD(F68,I68,M68),"") | AG68: Excluded | AH68: =iferror(VLOOKUP($B68,covariates!$B$3:$Z$1126,6,FALSE),"") -> 45.5 | AI68: =iferror(VLOOKUP($B68,covariates!$B$3:$Z$1126,7,FALSE),"") -> 8.7 | AJ68: =iferror(VLOOKUP($B68,covariates!$B$3:$Z$1126,14,FALSE),"") -> 15 | AK68: =iferror(VLOOKUP($B68,covariates!$B$3:$Z$1126,16,FALSE),"") -> 9 | AL68: =iferror(VLOOKUP($B68,covariates!$B$3:$Z$1126,18,FALSE),"") -> 204 | AM68: =iferror(VLOOKUP($B68,covariates!$B$3:$Z$1126,19,FALSE),"") -> 17
A69: 82 | B69: =HYPERLINK("https://github.com/d-wkim/phd/blob/main/data/pdf/sajovic_2018.pdf","Sajovic et al., 2018") -> Sajovic et al., 2018 | C69: HT | D69: ikdc_objective | E69: dichotomous | H69: =iferror(RANGE_SD(F69,I69,M69),"") | AG69: Excluded | AH69: =iferror(VLOOKUP($B69,covariates!$B$3:$Z$1126,6,FALSE),"") -> 45.5 | AI69: =iferror(VLOOKUP($B69,covariates!$B$3:$Z$1126,7,FALSE),"") -> 8.7 | AJ69: =iferror(VLOOKUP($B69,covariates!$B$3:$Z$1126,14,FALSE),"") -> 15 | AK69: =iferror(VLOOKUP($B69,covariates!$B$3:$Z$1126,16,FALSE),"") -> 9 | AL69: =iferror(VLOOKUP($B69,covariates!$B$3:$Z$1126,18,FALSE),"") -> 204 | AM69: =iferror(VLOOKUP($B69,covariates!$B$3:$Z$1126,19,FALSE),"") -> 17
A70: 90 | B70: =HYPERLINK("https://github.com/d-wkim/phd/blob/main/data/pdf/taylor_2009.pdf","Taylor et al., 2009") -> Taylor et al., 2009 | C70: BPTB | D70: ikdc_objective | E70: dichotomous | H70: =iferror(RANGE_SD(F70,I70,M70),"") | AG70: Excluded | AH70: =iferror(VLOOKUP($B70,covariates!$B$3:$Z$1126,6,FALSE),"") -> 21.7 | AI70: =iferror(VLOOKUP($B70,covariates!$B$3:$Z$1126,7,FALSE),"") -> 4.597 | AJ70: =iferror(VLOOKUP($B70,covariates!$B$3:$Z$1126,14,FALSE),"") -> 25 | AK70: =iferror(VLOOKUP($B70,covariates!$B$3:$Z$1126,16,FALSE),"") -> 7 | AL70: =iferror(VLOOKUP($B70,covariates!$B$3:$Z$1126,18,FALSE),"") -> 32.4 | AM70: =iferror(VLOOKUP($B70,covariates!$B$3:$Z$1126,19,FALSE),"") -> 2.7
A71: 90 | B71: =HYPERLINK("https://github.com/d-wkim/phd/blob/main/data/pdf/taylor_2009.pdf","Taylor et al., 2009") -> Taylor et al., 2009 | C71: HT | D71: ikdc_objective | E71: dichotomous | H71: =iferror(RANGE_SD(F71,I71,M71),"") | AG71: Excluded | AH71: =iferror(VLOOKUP($B71,covariates!$B$3:$Z$1126,6,FALSE),"") -> 21.7 | AI71: =iferror(VLOOKUP($B71,covariates!$B$3:$Z$1126,7,FALSE),"") -> 4.597 | AJ71: =iferror(VLOOKUP($B71,covariates!$B$3:$Z$1126,14,FALSE),"") -> 25 | AK71: =iferror(VLOOKUP($B71,covariates!$B$3:$Z$1126,16,FALSE),"") -> 7 | AL71: =iferror(VLOOKUP($B71,covariates!$B$3:$Z$1126,18,FALSE),"") -> 32.4 | AM71: =iferror(VLOOKUP($B71,covariates!$B$3:$Z$1126,19,FALSE),"") -> 2.7
A72: 95 | B72: =HYPERLINK("https://github.com/d-wkim/phd/blob/main/data/pdf/webster_2001.pdf","Webster et al., 2001") -> Webster et al., 2001 | C72: BPTB | D72: ikdc_objective | E72: dichotomous | AG72: Excluded | AH72: =iferror(VLOOKUP($B72,covariates!$B$3:$Z$1126,6,FALSE),"") -> 26 | AI72: =iferror(VLOOKUP($B72,covariates!$B$3:$Z$1126,7,FALSE),"") -> 6.3 | AJ72: =iferror(VLOOKUP($B72,covariates!$B$3:$Z$1126,14,FALSE),"") -> 20 | AK72: =iferror(VLOOKUP($B72,covariates!$B$3:$Z$1126,16,FALSE),"") -> 8 | AL72: =iferror(VLOOKUP($B72,covariates!$B$3:$Z$1126,18,FALSE),"") -> 24 | AM72: =iferror(VLOOKUP($B72,covariates!$B$3:$Z$1126,19,FALSE),"") -> 2
A73: 95 | B73: =HYPERLINK("https://github.com/d-wkim/phd/blob/main/data/pdf/webster_2001.pdf","Webster et al., 2001") -> Webster et al., 2001 | C73: HT | D73: ikdc_objective | E73: dichotomous | AG73: Excluded | AH73: =iferror(VLOOKUP($B73,covariates!$B$3:$Z$1126,6,FALSE),"") -> 26 | AI73: =iferror(VLOOKUP($B73,covariates!$B$3:$Z$1126,7,FALSE),"") -> 6.3 | AJ73: =iferror(VLOOKUP($B73,covariates!$B$3:$Z$1126,14,FALSE),"") -> 20 | AK73: =iferror(VLOOKUP($B73,covariates!$B$3:$Z$1126,16,FALSE),"") -> 8 | AL73: =iferror(VLOOKUP($B73,covariates!$B$3:$Z$1126,18,FALSE),"") -> 24 | AM73: =iferror(VLOOKUP($B73,covariates!$B$3:$Z$1126,19,FALSE),"") -> 2
A74: 10 | B74: =HYPERLINK("https://github.com/d-wkim/phd/blob/main/data/pdf/barié_2020.pdf","Barié et al., 2020") -> Barié et al., 2020 | C74: BPTB | D74: ikdc_subjective | E74: continuous | F74: 43 | G74: 91 | H74: 7.3 | N74: 0.91 | V74: 1.113 | Y74: 1.239 | AG74: Included | AH74: =iferror(VLOOKUP($B74,covariates!$B$3:$Z$1126,6,FALSE),"") -> 30.6 | AI74: =iferror(VLOOKUP($B74,covariates!$B$3:$Z$1126,7,FALSE),"") -> 7.5 | AJ74: =iferror(VLOOKUP($B74,covariates!$B$3:$Z$1126,14,FALSE),"") -> 17 | AK74: =iferror(VLOOKUP($B74,covariates!$B$3:$Z$1126,16,FALSE),"") -> 13 | AL74: =iferror(VLOOKUP($B74,covariates!$B$3:$Z$1126,18,FALSE),"") -> 122.4 | AM74: =iferror(VLOOKUP($B74,covariates!$B$3:$Z$1126,19,FALSE),"") -> 10.2
A75: 10 | B75: =HYPERLINK("https://github.com/d-wkim/phd/blob/main/data/pdf/barié_2020.pdf","Barié et al., 2020") -> Barié et al., 2020 | C75: QT | D75: ikdc_subjective | E75: continuous | F75: 43 | G75: 92 | H75: 11.5 | N75: 0.92 | V75: 1.754 | Y75: 3.077 | AG75: Included | AH75: =iferror(VLOOKUP($B75,covariates!$B$3:$Z$1126,6,FALSE),"") -> 30.6 | AI75: =iferror(VLOOKUP($B75,covariates!$B$3:$Z$1126,7,FALSE),"") -> 7.5 | AJ75: =iferror(VLOOKUP($B75,covariates!$B$3:$Z$1126,14,FALSE),"") -> 17 | AK75: =iferror(VLOOKUP($B75,covariates!$B$3:$Z$1126,16,FALSE),"") -> 13 | AL75: =iferror(VLOOKUP($B75,covariates!$B$3:$Z$1126,18,FALSE),"") -> 122.4 | AM75: =iferror(VLOOKUP($B75,covariates!$B$3:$Z$1126,19,FALSE),"") -> 10.2
A76: 12 | B76: =HYPERLINK("https://github.com/d-wkim/phd/blob/main/data/pdf/bi_2018.pdf","Bi et al., 2018") -> Bi et al., 2018 | C76: HT | D76: ikdc_subjective | E76: continuous | F76: 62 | G76: 90.4 | H76: 7.1 | N76: 0.904 | V76: 0.902 | Y76: 0.814 | AG76: Included | AH76: =iferror(VLOOKUP($B76,covariates!$B$3:$Z$1126,6,FALSE),"") -> 27.9 | AI76: =iferror(VLOOKUP($B76,covariates!$B$3:$Z$1126,7,FALSE),"") -> 6.7 | AJ76: =iferror(VLOOKUP($B76,covariates!$B$3:$Z$1126,14,FALSE),"") -> 31 | AK76: =iferror(VLOOKUP($B76,covariates!$B$3:$Z$1126,16,FALSE),"") -> 31 | AL76: =iferror(VLOOKUP($B76,covariates!$B$3:$Z$1126,18,FALSE),"") -> 30.3 | AM76: =iferror(VLOOKUP($B76,covariates!$B$3:$Z$1126,19,FALSE),"") -> 2.5
A77: 12 | B77: =HYPERLINK("https://github.com/d-wkim/phd/blob/main/data/pdf/bi_2018.pdf","Bi et al., 2018") -> Bi et al., 2018 | C77: PLT | D77: ikdc_subjective | E77: continuous | F77: 62 | G77: 89.3 | H77: 8.4 | N77: 0.893 | V77: 1.067 | Y77: 1.138 | AG77: Included | AH77: =iferror(VLOOKUP($B77,covariates!$B$3:$Z$1126,6,FALSE),"") -> 27.9 | AI77: =iferror(VLOOKUP($B77,covariates!$B$3:$Z$1126,7,FALSE),"") -> 6.7 | AJ77: =iferror(VLOOKUP($B77,covariates!$B$3:$Z$1126,14,FALSE),"") -> 31 | AK77: =iferror(VLOOKUP($B77,covariates!$B$3:$Z$1126,16,FALSE),"") -> 31 | AL77: =iferror(VLOOKUP($B77,covariates!$B$3:$Z$1126,18,FALSE),"") -> 30.3 | AM77: =iferror(VLOOKUP($B77,covariates!$B$3:$Z$1126,19,FALSE),"") -> 2.5
A78: 13 | B78: =HYPERLINK("https://github.com/d-wkim/phd/blob/main/data/pdf/björnsson_2016.pdf","Björnsson et al., 2016") -> Björnsson et al., 2016 | C78: BPTB | D78: ikdc_subjective | E78: continuous | F78: 61 | G78: 67.3 | H78: 20.8 | N78: 0.673 | V78: 2.663 | Y78: 7.092 | AG78: Included | AH78: =iferror(VLOOKUP($B78,covariates!$B$3:$Z$1126,6,FALSE),"") -> 28.2 | AI78: =iferror(VLOOKUP($B78,covariates!$B$3:$Z$1126,7,FALSE),"") -> 9.1 | AJ78: =iferror(VLOOKUP($B78,covariates!$B$3:$Z$1126,14,FALSE),"") -> 42 | AK78: =iferror(VLOOKUP($B78,covariates!$B$3:$Z$1126,16,FALSE),"") -> 19 | AL78: =iferror(VLOOKUP($B78,covariates!$B$3:$Z$1126,18,FALSE),"") -> 202.6 | AM78: =iferror(VLOOKUP($B78,covariates!$B$3:$Z$1126,19,FALSE),"") -> 16.9
A79: 13 | B79: =HYPERLINK("https://github.com/d-wkim/phd/blob/main/data/pdf/björnsson_2016.pdf","Björnsson et al., 2016") -> Björnsson et al., 2016 | C79: HT | D79: ikdc_subjective | E79: continuous | F79: 86 | G79: 74 | H79: 18.8 | N79: 0.74 | V79: 2.027 | Y79: 4.109 | AG79: Included | AH79: =iferror(VLOOKUP($B79,covariates!$B$3:$Z$1126,6,FALSE),"") -> 28.2 | AI79: =iferror(VLOOKUP($B79,covariates!$B$3:$Z$1126,7,FALSE),"") -> 9.1 | AJ79: =iferror(VLOOKUP($B79,covariates!$B$3:$Z$1126,14,FALSE),"") -> 42 | AK79: =iferror(VLOOKUP($B79,covariates!$B$3:$Z$1126,16,FALSE),"") -> 19 | AL79: =iferror(VLOOKUP($B79,covariates!$B$3:$Z$1126,18,FALSE),"") -> 202.6 | AM79: =iferror(VLOOKUP($B79,covariates!$B$3:$Z$1126,19,FALSE),"") -> 16.9
A80: 14 | B80: =HYPERLINK("https://github.com/d-wkim/phd/blob/main/data/pdf/bottoni_2015.pdf","Bottoni et al., 2015") -> Bottoni et al., 2015 | C80: HT | D80: ikdc_subjective | E80: continuous | F80: 44 | G80: 79.5 | H80: 24.7 | N80: 0.795 | V80: 3.724 | Y80: 13.868 | AG80: Included | AH80: =iferror(VLOOKUP($B80,covariates!$B$3:$Z$1126,6,FALSE),"") -> 28.9 | AI80: =iferror(VLOOKUP($B80,covariates!$B$3:$Z$1126,7,FALSE),"") -> 5.8 | AJ80: =iferror(VLOOKUP($B80,covariates!$B$3:$Z$1126,14,FALSE),"") -> 41 | AK80: =iferror(VLOOKUP($B80,covariates!$B$3:$Z$1126,16,FALSE),"") -> 7 | AL80: =iferror(VLOOKUP($B80,covariates!$B$3:$Z$1126,18,FALSE),"") -> 120 | AM80: =iferror(VLOOKUP($B80,covariates!$B$3:$Z$1126,19,FALSE),"") -> 10
A81: 14 | B81: =HYPERLINK("https://github.com/d-wkim/phd/blob/main/data/pdf/bottoni_2015.pdf","Bottoni et al., 2015") -> Bottoni et al., 2015 | C81: TA | D81: ikdc_subjective | E81: continuous | F81: 36 | G81: 81.1 | H81: 23.1 | N81: 0.811 | V81: 3.85 | Y81: 14.823 | AG81: Included | AH81: =iferror(VLOOKUP($B81,covariates!$B$3:$Z$1126,6,FALSE),"") -> 28.9 | AI81: =iferror(VLOOKUP($B81,covariates!$B$3:$Z$1126,7,FALSE),"") -> 5.8 | AJ81: =iferror(VLOOKUP($B81,covariates!$B$3:$Z$1126,14,FALSE),"") -> 41 | AK81: =iferror(VLOOKUP($B81,covariates!$B$3:$Z$1126,16,FALSE),"") -> 7 | AL81: =iferror(VLOOKUP($B81,covariates!$B$3:$Z$1126,18,FALSE),"") -> 120 | AM81: =iferror(VLOOKUP($B81,covariates!$B$3:$Z$1126,19,FALSE),"") -> 10
A82: 18 | B82: =HYPERLINK("https://github.com/d-wkim/phd/blob/main/data/pdf/butt_2024.pdf","Butt et al., 2024") -> Butt et al., 2024 | C82: HT | D82: ikdc_subjective | E82: continuous | F82: 30 | G82: 89.7 | H82: 5.7 | N82: 0.897 | V82: 1.041 | Y82: 1.084 | AG82: Included | AH82: =iferror(VLOOKUP($B82,covariates!$B$3:$Z$1126,6,FALSE),"") -> 29.17 | AI82: =iferror(VLOOKUP($B82,covariates!$B$3:$Z$1126,7,FALSE),"") -> 5.03 | AJ82: =iferror(VLOOKUP($B82,covariates!$B$3:$Z$1126,14,FALSE),"") -> 29 | AK82: =iferror(VLOOKUP($B82,covariates!$B$3:$Z$1126,16,FALSE),"") -> 1 | AL82: =iferror(VLOOKUP($B82,covariates!$B$3:$Z$1126,18,FALSE),"") -> 60 | AM82: =iferror(VLOOKUP($B82,covariates!$B$3:$Z$1126,19,FALSE),"") -> 5
A83: 18 | B83: =HYPERLINK("https://github.com/d-wkim/phd/blob/main/data/pdf/butt_2024.pdf","Butt et al., 2024") -> Butt et al., 2024 | C83: PLT | D83: ikdc_subjective | E83: continuous | F83: 30 | G83: 89.9 | H83: 9.8 | N83: 0.899 | V83: 1.789 | Y83: 3.201 | AG83: Included | AH83: =iferror(VLOOKUP($B83,covariates!$B$3:$Z$1126,6,FALSE),"") -> 29.17 | AI83: =iferror(VLOOKUP($B83,covariates!$B$3:$Z$1126,7,FALSE),"") -> 5.03 | AJ83: =iferror(VLOOKUP($B83,covariates!$B$3:$Z$1126,14,FALSE),"") -> 29 | AK83: =iferror(VLOOKUP($B83,covariates!$B$3:$Z$1126,16,FALSE),"") -> 1 | AL83: =iferror(VLOOKUP($B83,covariates!$B$3:$Z$1126,18,FALSE),"") -> 60 | AM83: =iferror(VLOOKUP($B83,covariates!$B$3:$Z$1126,19,FALSE),"") -> 5
A84: 19 | B84: =HYPERLINK("https://github.com/d-wkim/phd/blob/main/data/pdf/calvert_2025.pdf","Calvert et al., 2025") -> Calvert et al., 2025 | C84: HT | D84: ikdc_subjective | E84: continuous | F84: 92 | G84: 92 | H84: 8 | N84: 0.92 | V84: 0.834 | Y84: 0.696 | AG84: Included | AH84: =iferror(VLOOKUP($B84,covariates!$B$3:$Z$1126,6,FALSE),"") -> 29.4 | AI84: =iferror(VLOOKUP($B84,covariates!$B$3:$Z$1126,7,FALSE),"") -> 7.7 | AJ84: =iferror(VLOOKUP($B84,covariates!$B$3:$Z$1126,14,FALSE),"") -> 28 | AK84: =iferror(VLOOKUP($B84,covariates!$B$3:$Z$1126,16,FALSE),"") -> 27 | AL84: =iferror(VLOOKUP($B84,covariates!$B$3:$Z$1126,18,FALSE),"") -> 24 | AM84: =iferror(VLOOKUP($B84,covariates!$B$3:$Z$1126,19,FALSE),"") -> 2
A85: 19 | B85: =HYPERLINK("https://github.com/d-wkim/phd/blob/main/data/pdf/calvert_2025.pdf","Calvert et al., 2025") -> Calvert et al., 2025 | C85: QT | D85: ikdc_subjective | E85: continuous | F85: 89 | G85: 89 | H85: 10 | N85: 0.89 | V85: 1.06 | Y85: 1.124 | AG85: Included | AH85: =iferror(VLOOKUP($B85,covariates!$B$3:$Z$1126,6,FALSE),"") -> 29.4 | AI85: =iferror(VLOOKUP($B85,covariates!$B$3:$Z$1126,7,FALSE),"") -> 7.7 | AJ85: =iferror(VLOOKUP($B85,covariates!$B$3:$Z$1126,14,FALSE),"") -> 28 | AK85: =iferror(VLOOKUP($B85,covariates!$B$3:$Z$1126,16,FALSE),"") -> 27 | AL85: =iferror(VLOOKUP($B85,covariates!$B$3:$Z$1126,18,FALSE),"") -> 24 | AM85: =iferror(VLOOKUP($B85,covariates!$B$3:$Z$1126,19,FALSE),"") -> 2
A86: 32 | B86: =HYPERLINK("https://github.com/d-wkim/phd/blob/main/data/pdf/guglielmetti_2021.pdf","Guglielmetti et al., 2021") -> Guglielmetti et al., 2021 | C86: BPTB | D86: ikdc_subjective | E86: continuous | F86: 31 | G86: 88.75 | H86: 9.27 | N86: 0.8875 | V86: 1.665 | Y86: 2.772 | AG86: Included | AH86: =iferror(VLOOKUP($B86,covariates!$B$3:$Z$1126,6,FALSE),"") -> 25.2 | AI86: =iferror(VLOOKUP($B86,covariates!$B$3:$Z$1126,7,FALSE),"") -> 5.48 | AJ86: =iferror(VLOOKUP($B86,covariates!$B$3:$Z$1126,14,FALSE),"") -> 23 | AK86: =iferror(VLOOKUP($B86,covariates!$B$3:$Z$1126,16,FALSE),"") -> 8 | AL86: =iferror(VLOOKUP($B86,covariates!$B$3:$Z$1126,18,FALSE),"") -> 24 | AM86: =iferror(VLOOKUP($B86,covariates!$B$3:$Z$1126,19,FALSE),"") -> 2
A87: 32 | B87: =HYPERLINK("https://github.com/d-wkim/phd/blob/main/data/pdf/guglielmetti_2021.pdf","Guglielmetti et al., 2021") -> Guglielmetti et al., 2021 | C87: HT | D87: ikdc_subjective | E87: continuous | F87: 31 | G87: 91 | H87: 9.07 | N87: 0.91 | V87: 1.629 | Y87: 2.654 | AG87: Included | AH87: =iferror(VLOOKUP($B87,covariates!$B$3:$Z$1126,6,FALSE),"") -> 25.2 | AI87: =iferror(VLOOKUP($B87,covariates!$B$3:$Z$1126,7,FALSE),"") -> 5.48 | AJ87: =iferror(VLOOKUP($B87,covariates!$B$3:$Z$1126,14,FALSE),"") -> 23 | AK87: =iferror(VLOOKUP($B87,covariates!$B$3:$Z$1126,16,FALSE),"") -> 8 | AL87: =iferror(VLOOKUP($B87,covariates!$B$3:$Z$1126,18,FALSE),"") -> 24 | AM87: =iferror(VLOOKUP($B87,covariates!$B$3:$Z$1126,19,FALSE),"") -> 2
A88: 36 | B88: =HYPERLINK("https://github.com/d-wkim/phd/blob/main/data/pdf/horstmann_2022.pdf","Horstmann et al., 2022") -> Horstmann et al., 2022 | C88: HT | D88: ikdc_subjective | E88: continuous | F88: 26 | G88: 83.7 | H88: 12.7 | N88: 0.837 | V88: 2.491 | Y88: 6.205 | AG88: Included | AH88: =iferror(VLOOKUP($B88,covariates!$B$3:$Z$1126,6,FALSE),"") -> 32.7 | AI88: =iferror(VLOOKUP($B88,covariates!$B$3:$Z$1126,7,FALSE),"") -> 11.4 | AJ88: =iferror(VLOOKUP($B88,covariates!$B$3:$Z$1126,14,FALSE),"") -> 12 | AK88: =iferror(VLOOKUP($B88,covariates!$B$3:$Z$1126,16,FALSE),"") -> 15 | AL88: =iferror(VLOOKUP($B88,covariates!$B$3:$Z$1126,18,FALSE),"") -> 24 | AM88: =iferror(VLOOKUP($B88,covariates!$B$3:$Z$1126,19,FALSE),"") -> 2
A89: 36 | B89: =HYPERLINK("https://github.com/d-wkim/phd/blob/main/data/pdf/horstmann_2022.pdf","Horstmann et al., 2022") -> Horstmann et al., 2022 | C89: QT | D89: ikdc_subjective | E89: continuous | F89: 23 | G89: 89.3 | H89: 12.2 | N89: 0.893 | V89: 2.544 | Y89: 6.472 | AG89: Included | AH89: =iferror(VLOOKUP($B89,covariates!$B$3:$Z$1126,6,FALSE),"") -> 32.7 | AI89: =iferror(VLOOKUP($B89,covariates!$B$3:$Z$1126,7,FALSE),"") -> 11.4 | AJ89: =iferror(VLOOKUP($B89,covariates!$B$3:$Z$1126,14,FALSE),"") -> 12 | AK89: =iferror(VLOOKUP($B89,covariates!$B$3:$Z$1126,16,FALSE),"") -> 15 | AL89: =iferror(VLOOKUP($B89,covariates!$B$3:$Z$1126,18,FALSE),"") -> 24 | AM89: =iferror(VLOOKUP($B89,covariates!$B$3:$Z$1126,19,FALSE),"") -> 2
A90: 38 | B90: =HYPERLINK("https://github.com/d-wkim/phd/blob/main/data/pdf/iliopoulos_2017.pdf","Iliopoulos et al., 2017") -> Iliopoulos et al., 2017 | C90: BPTB | D90: ikdc_subjective | E90: continuous | F90: 45 | G90: 83.2 | H90: 2.8 | N90: 0.832 | V90: 0.417 | Y90: 0.174 | AG90: Included | AH90: =iferror(VLOOKUP($B90,covariates!$B$3:$Z$1126,6,FALSE),"") -> 24.8 | AI90: =iferror(VLOOKUP($B90,covariates!$B$3:$Z$1126,7,FALSE),"") -> 5 | AJ90: =iferror(VLOOKUP($B90,covariates!$B$3:$Z$1126,14,FALSE),"") -> 10 | AK90: =iferror(VLOOKUP($B90,covariates!$B$3:$Z$1126,16,FALSE),"") -> 0 | AL90: =iferror(VLOOKUP($B90,covariates!$B$3:$Z$1126,18,FALSE),"") -> 9 | AM90: =iferror(VLOOKUP($B90,covariates!$B$3:$Z$1126,19,FALSE),"") -> 0.8
A91: 38 | B91: =HYPERLINK("https://github.com/d-wkim/phd/blob/main/data/pdf/iliopoulos_2017.pdf","Iliopoulos et al., 2017") -> Iliopoulos et al., 2017 | C91: HT | D91: ikdc_subjective | E91: continuous | F91: 45 | G91: 82.78 | H91: 2.8 | N91: 0.8278 | V91: 0.417 | Y91: 0.174 | AG91: Included | AH91: =iferror(VLOOKUP($B91,covariates!$B$3:$Z$1126,6,FALSE),"") -> 24.8 | AI91: =iferror(VLOOKUP($B91,covariates!$B$3:$Z$1126,7,FALSE),"") -> 5 | AJ91: =iferror(VLOOKUP($B91,covariates!$B$3:$Z$1126,14,FALSE),"") -> 10 | AK91: =iferror(VLOOKUP($B91,covariates!$B$3:$Z$1126,16,FALSE),"") -> 0 | AL91: =iferror(VLOOKUP($B91,covariates!$B$3:$Z$1126,18,FALSE),"") -> 9 | AM91: =iferror(VLOOKUP($B91,covariates!$B$3:$Z$1126,19,FALSE),"") -> 0.8
A92: 44 | B92: =HYPERLINK("https://github.com/d-wkim/phd/blob/main/data/pdf/komzak_2022.pdf","Komzak et al., 2022") -> Komzak et al., 2022 | C92: BPTB | D92: ikdc_subjective | E92: continuous | F92: 36 | G92: 74.2 | H92: 10.2 | N92: 0.742 | V92: 1.7 | Y92: 2.89 | AG92: Included | AH92: =iferror(VLOOKUP($B92,covariates!$B$3:$Z$1126,6,FALSE),"") -> 31 | AI92: =iferror(VLOOKUP($B92,covariates!$B$3:$Z$1126,7,FALSE),"") -> 9.459 | AJ92: =iferror(VLOOKUP($B92,covariates!$B$3:$Z$1126,14,FALSE),"") -> 23 | AK92: =iferror(VLOOKUP($B92,covariates!$B$3:$Z$1126,16,FALSE),"") -> 17 | AL92: =iferror(VLOOKUP($B92,covariates!$B$3:$Z$1126,18,FALSE),"") -> 28 | AM92: =iferror(VLOOKUP($B92,covariates!$B$3:$Z$1126,19,FALSE),"") -> 2.3
A93: 44 | B93: =HYPERLINK("https://github.com/d-wkim/phd/blob/main/data/pdf/komzak_2022.pdf","Komzak et al., 2022") -> Komzak et al., 2022 | C93: QT | D93: ikdc_subjective | E93: continuous | F93: 36 | G93: 78.3 | H93: 10.5 | N93: 0.783 | V93: 1.75 | Y93: 3.063 | AG93: Included | AH93: =iferror(VLOOKUP($B93,covariates!$B$3:$Z$1126,6,FALSE),"") -> 31 | AI93: =iferror(VLOOKUP($B93,covariates!$B$3:$Z$1126,7,FALSE),"") -> 9.459 | AJ93: =iferror(VLOOKUP($B93,covariates!$B$3:$Z$1126,14,FALSE),"") -> 23 | AK93: =iferror(VLOOKUP($B93,covariates!$B$3:$Z$1126,16,FALSE),"") -> 17 | AL93: =iferror(VLOOKUP($B93,covariates!$B$3:$Z$1126,18,FALSE),"") -> 28 | AM93: =iferror(VLOOKUP($B93,covariates!$B$3:$Z$1126,19,FALSE),"") -> 2.3
A94: 51 | B94: =HYPERLINK("https://github.com/d-wkim/phd/blob/main/data/pdf/li_2015.pdf","Li et al., 2015") -> Li et al., 2015 | C94: HT | D94: ikdc_subjective | E94: continuous | F94: 32 | G94: 87.5 | H94: 3.2 | N94: 0.875 | V94: 0.566 | Y94: 0.32 | AG94: Included | AH94: =iferror(VLOOKUP($B94,covariates!$B$3:$Z$1126,6,FALSE),"") -> 29.8 | AI94: =iferror(VLOOKUP($B94,covariates!$B$3:$Z$1126,7,FALSE),"") -> 7.9 | AJ94: =iferror(VLOOKUP($B94,covariates!$B$3:$Z$1126,14,FALSE),"") -> 17 | AK94: =iferror(VLOOKUP($B94,covariates!$B$3:$Z$1126,16,FALSE),"") -> 15 | AL94: =iferror(VLOOKUP($B94,covariates!$B$3:$Z$1126,18,FALSE),"") -> 69.6 | AM94: =iferror(VLOOKUP($B94,covariates!$B$3:$Z$1126,19,FALSE),"") -> 5.8
A95: 51 | B95: =HYPERLINK("https://github.com/d-wkim/phd/blob/main/data/pdf/li_2015.pdf","Li et al., 2015") -> Li et al., 2015 | C95: TA | D95: ikdc_subjective | E95: continuous | F95: 32 | G95: 83.8 | H95: 6.9 | N95: 0.838 | V95: 1.22 | Y95: 1.488 | AG95: Included | AH95: =iferror(VLOOKUP($B95,covariates!$B$3:$Z$1126,6,FALSE),"") -> 29.8 | AI95: =iferror(VLOOKUP($B95,covariates!$B$3:$Z$1126,7,FALSE),"") -> 7.9 | AJ95: =iferror(VLOOKUP($B95,covariates!$B$3:$Z$1126,14,FALSE),"") -> 17 | AK95: =iferror(VLOOKUP($B95,covariates!$B$3:$Z$1126,16,FALSE),"") -> 15 | AL95: =iferror(VLOOKUP($B95,covariates!$B$3:$Z$1126,18,FALSE),"") -> 69.6 | AM95: =iferror(VLOOKUP($B95,covariates!$B$3:$Z$1126,19,FALSE),"") -> 5.8
A96: 53 | B96: =HYPERLINK("https://github.com/d-wkim/phd/blob/main/data/pdf/lind_2020.pdf","Lind et al., 2020") -> Lind et al., 2020 | C96: HT | D96: ikdc_subjective | E96: continuous | F96: 49 | G96: 78 | H96: 18 | N96: 0.78 | V96: 2.571 | Y96: 6.61 | AG96: Included | AH96: =iferror(VLOOKUP($B96,covariates!$B$3:$Z$1126,6,FALSE),"") -> 27.1 | AI96: =iferror(VLOOKUP($B96,covariates!$B$3:$Z$1126,7,FALSE),"") -> 6.1 | AJ96: =iferror(VLOOKUP($B96,covariates!$B$3:$Z$1126,14,FALSE),"") -> 25 | AK96: =iferror(VLOOKUP($B96,covariates!$B$3:$Z$1126,16,FALSE),"") -> 24 | AL96: =iferror(VLOOKUP($B96,covariates!$B$3:$Z$1126,18,FALSE),"") -> 24 | AM96: =iferror(VLOOKUP($B96,covariates!$B$3:$Z$1126,19,FALSE),"") -> 2
A97: 53 | B97: =HYPERLINK("https://github.com/d-wkim/phd/blob/main/data/pdf/lind_2020.pdf","Lind et al., 2020") -> Lind et al., 2020 | C97: QT | D97: ikdc_subjective | E97: continuous | F97: 47 | G97: 82 | H97: 14 | N97: 0.82 | V97: 2.042 | Y97: 4.17 | AG97: Included | AH97: =iferror(VLOOKUP($B97,covariates!$B$3:$Z$1126,6,FALSE),"") -> 27.1 | AI97: =iferror(VLOOKUP($B97,covariates!$B$3:$Z$1126,7,FALSE),"") -> 6.1 | AJ97: =iferror(VLOOKUP($B97,covariates!$B$3:$Z$1126,14,FALSE),"") -> 25 | AK97: =iferror(VLOOKUP($B97,covariates!$B$3:$Z$1126,16,FALSE),"") -> 24 | AL97: =iferror(VLOOKUP($B97,covariates!$B$3:$Z$1126,18,FALSE),"") -> 24 | AM97: =iferror(VLOOKUP($B97,covariates!$B$3:$Z$1126,19,FALSE),"") -> 2
A98: 54 | B98: =HYPERLINK("https://github.com/d-wkim/phd/blob/main/data/pdf/lucidi_2025.pdf","Lucidi et al., 2025") -> Lucidi et al., 2025 | C98: BPTB | D98: ikdc_subjective | E98: continuous | F98: 19 | G98: 78.4 | H98: 13.7 | N98: 0.784 | V98: 3.143 | Y98: 9.878 | AG98: Included | AH98: =iferror(VLOOKUP($B98,covariates!$B$3:$Z$1126,6,FALSE),"") -> 52.8 | AI98: =iferror(VLOOKUP($B98,covariates!$B$3:$Z$1126,7,FALSE),"") -> 7.3 | AJ98: =iferror(VLOOKUP($B98,covariates!$B$3:$Z$1126,14,FALSE),"") | AK98: =iferror(VLOOKUP($B98,covariates!$B$3:$Z$1126,16,FALSE),"") | AL98: =iferror(VLOOKUP($B98,covariates!$B$3:$Z$1126,18,FALSE),"") -> 240 | AM98: =iferror(VLOOKUP($B98,covariates!$B$3:$Z$1126,19,FALSE),"") -> 20
A99: 54 | B99: =HYPERLINK("https://github.com/d-wkim/phd/blob/main/data/pdf/lucidi_2025.pdf","Lucidi et al., 2025") -> Lucidi et al., 2025 | C99: HT | D99: ikdc_subjective | E99: continuous | F99: 20 | G99: 81.6 | H99: 11.9 | N99: 0.816 | V99: 2.661 | Y99: 7.081 | AG99: Included | AH99: =iferror(VLOOKUP($B99,covariates!$B$3:$Z$1126,6,FALSE),"") -> 52.8 | AI99: =iferror(VLOOKUP($B99,covariates!$B$3:$Z$1126,7,FALSE),"") -> 7.3 | AJ99: =iferror(VLOOKUP($B99,covariates!$B$3:$Z$1126,14,FALSE),"") | AK99: =iferror(VLOOKUP($B99,covariates!$B$3:$Z$1126,16,FALSE),"") | AL99: =iferror(VLOOKUP($B99,covariates!$B$3:$Z$1126,18,FALSE),"") -> 240 | AM99: =iferror(VLOOKUP($B99,covariates!$B$3:$Z$1126,19,FALSE),"") -> 20
A100: 55 | B100: =HYPERLINK("https://github.com/d-wkim/phd/blob/main/data/pdf/lui_2012.pdf","Lui et al., 2012") -> Lui et al., 2012 | C100: BPTB | D100: ikdc_subjective | E100: continuous | F100: 14 | G100: 71.9 | H100: 15.2 | N100: 0.719 | V100: 4.062 | Y100: 16.5 | AG100: Included | AH100: =iferror(VLOOKUP($B100,covariates!$B$3:$Z$1126,6,FALSE),"") -> 26.5 | AI100: =iferror(VLOOKUP($B100,covariates!$B$3:$Z$1126,7,FALSE),"") -> 5 | AJ100: =iferror(VLOOKUP($B100,covariates!$B$3:$Z$1126,14,FALSE),"") -> 14 | AK100: =iferror(VLOOKUP($B100,covariates!$B$3:$Z$1126,16,FALSE),"") -> 0 | AL100: =iferror(VLOOKUP($B100,covariates!$B$3:$Z$1126,18,FALSE),"") -> 12 | AM100: =iferror(VLOOKUP($B100,covariates!$B$3:$Z$1126,19,FALSE),"") -> 1
...

Sheet Sheet42
A1: study | B1: subgroup | C1: n
A2: =HYPERLINK("https://github.com/d-wkim/phd/blob/main/data/pdf/ageberg_2009.pdf","Ageberg et al., 2009") -> Ageberg et al., 2009 | B2: BPTB | C2: 16 | D2: =IFERROR(__xludf.DUMMYFUNCTION("join(""; "",A2:C2)"),"Ageberg et al., 2009; BPTB; 16") -> Ageberg et al., 2009; BPTB; 16 | E2: {=unique(D2:D349)} -> Ageberg et al., 2009; BPTB; 16 | F2: =IFERROR(__xludf.DUMMYFUNCTION("split(E2,"";"",FALSE)"),"Ageberg et al., 2009") -> Ageberg et al., 2009 | G2: =IFERROR(__xludf.DUMMYFUNCTION("""COMPUTED_VALUE""")," BPTB") -> BPTB | H2: =IFERROR(__xludf.DUMMYFUNCTION("""COMPUTED_VALUE"""),16.0) -> 16 | J2: Ageberg et al., 2009 | K2: BPTB | L2: 16
A3: =HYPERLINK("https://github.com/d-wkim/phd/blob/main/data/pdf/ageberg_2009.pdf","Ageberg et al., 2009") -> Ageberg et al., 2009 | B3: HT | C3: 20 | D3: =IFERROR(__xludf.DUMMYFUNCTION("join(""; "",A3:C3)"),"Ageberg et al., 2009; HT; 20") -> Ageberg et al., 2009; HT; 20 | E3: Ageberg et al., 2009; HT; 20 | F3: =IFERROR(__xludf.DUMMYFUNCTION("split(E3,"";"",FALSE)"),"Ageberg et al., 2009") -> Ageberg et al., 2009 | G3: =IFERROR(__xludf.DUMMYFUNCTION("""COMPUTED_VALUE""")," HT") -> HT | H3: =IFERROR(__xludf.DUMMYFUNCTION("""COMPUTED_VALUE"""),20.0) -> 20 | J3: Ageberg et al., 2009 | K3: HT | L3: 20
A4: =HYPERLINK("https://github.com/d-wkim/phd/blob/main/data/pdf/aglietti_2004.pdf","Aglietti et al., 2004") -> Aglietti et al., 2004 | B4: BPTB | C4: 60 | D4: =IFERROR(__xludf.DUMMYFUNCTION("join(""; "",A4:C4)"),"Aglietti et al., 2004; BPTB; 60") -> Aglietti et al., 2004; BPTB; 60 | E4: Aglietti et al., 2004; BPTB; 60 | F4: =IFERROR(__xludf.DUMMYFUNCTION("split(E4,"";"",FALSE)"),"Aglietti et al., 2004") -> Aglietti et al., 2004 | G4: =IFERROR(__xludf.DUMMYFUNCTION("""COMPUTED_VALUE""")," BPTB") -> BPTB | H4: =IFERROR(__xludf.DUMMYFUNCTION("""COMPUTED_VALUE"""),60.0) -> 60 | J4: Aglietti et al., 2004 | K4: BPTB | L4: 60
A5: =HYPERLINK("https://github.com/d-wkim/phd/blob/main/data/pdf/aglietti_2004.pdf","Aglietti et al., 2004") -> Aglietti et al., 2004 | B5: BPTB | C5: 60 | D5: =IFERROR(__xludf.DUMMYFUNCTION("join(""; "",A5:C5)"),"Aglietti et al., 2004; BPTB; 60") -> Aglietti et al., 2004; BPTB; 60 | E5: Aglietti et al., 2004; HT; 60 | F5: =IFERROR(__xludf.DUMMYFUNCTION("split(E5,"";"",FALSE)"),"Aglietti et al., 2004") -> Aglietti et al., 2004 | G5: =IFERROR(__xludf.DUMMYFUNCTION("""COMPUTED_VALUE""")," HT") -> HT | H5: =IFERROR(__xludf.DUMMYFUNCTION("""COMPUTED_VALUE"""),60.0) -> 60 | J5: Aglietti et al., 2004 | K5: HT | L5: 60
A6: =HYPERLINK("https://github.com/d-wkim/phd/blob/main/data/pdf/aglietti_2004.pdf","Aglietti et al., 2004") -> Aglietti et al., 2004 | B6: BPTB | C6: 60 | D6: =IFERROR(__xludf.DUMMYFUNCTION("join(""; "",A6:C6)"),"Aglietti et al., 2004; BPTB; 60") -> Aglietti et al., 2004; BPTB; 60 | E6: Ahldén et al., 2009; BPTB; 25 | F6: =IFERROR(__xludf.DUMMYFUNCTION("split(E6,"";"",FALSE)"),"Ahldén et al., 2009") -> Ahldén et al., 2009 | G6: =IFERROR(__xludf.DUMMYFUNCTION("""COMPUTED_VALUE""")," BPTB") -> BPTB | H6: =IFERROR(__xludf.DUMMYFUNCTION("""COMPUTED_VALUE"""),25.0) -> 25 | J6: Ahldén et al., 2009 | K6: BPTB | L6: 25
A7: =HYPERLINK("https://github.com/d-wkim/phd/blob/main/data/pdf/aglietti_2004.pdf","Aglietti et al., 2004") -> Aglietti et al., 2004 | B7: HT | C7: 60 | D7: =IFERROR(__xludf.DUMMYFUNCTION("join(""; "",A7:C7)"),"Aglietti et al., 2004; HT; 60") -> Aglietti et al., 2004; HT; 60 | E7: Ahldén et al., 2009; HT; 22 | F7: =IFERROR(__xludf.DUMMYFUNCTION("split(E7,"";"",FALSE)"),"Ahldén et al., 2009") -> Ahldén et al., 2009 | G7: =IFERROR(__xludf.DUMMYFUNCTION("""COMPUTED_VALUE""")," HT") -> HT | H7: =IFERROR(__xludf.DUMMYFUNCTION("""COMPUTED_VALUE"""),22.0) -> 22 | J7: Ahldén et al., 2009 | K7: HT | L7: 22
A8: =HYPERLINK("https://github.com/d-wkim/phd/blob/main/data/pdf/aglietti_2004.pdf","Aglietti et al., 2004") -> Aglietti et al., 2004 | B8: HT | C8: 60 | D8: =IFERROR(__xludf.DUMMYFUNCTION("join(""; "",A8:C8)"),"Aglietti et al., 2004; HT; 60") -> Aglietti et al., 2004; HT; 60 | E8: Anderson et al., 2001; BPTB; 35 | F8: =IFERROR(__xludf.DUMMYFUNCTION("split(E8,"";"",FALSE)"),"Anderson et al., 2001") -> Anderson et al., 2001 | G8: =IFERROR(__xludf.DUMMYFUNCTION("""COMPUTED_VALUE""")," BPTB") -> BPTB | H8: =IFERROR(__xludf.DUMMYFUNCTION("""COMPUTED_VALUE"""),35.0) -> 35 | J8: Anderson et al., 2001 | K8: BPTB | L8: 35
A9: =HYPERLINK("https://github.com/d-wkim/phd/blob/main/data/pdf/aglietti_2004.pdf","Aglietti et al., 2004") -> Aglietti et al., 2004 | B9: HT | C9: 60 | D9: =IFERROR(__xludf.DUMMYFUNCTION("join(""; "",A9:C9)"),"Aglietti et al., 2004; HT; 60") -> Aglietti et al., 2004; HT; 60 | E9: Anderson et al., 2001; HT; 33 | F9: =IFERROR(__xludf.DUMMYFUNCTION("split(E9,"";"",FALSE)"),"Anderson et al., 2001") -> Anderson et al., 2001 | G9: =IFERROR(__xludf.DUMMYFUNCTION("""COMPUTED_VALUE""")," HT") -> HT | H9: =IFERROR(__xludf.DUMMYFUNCTION("""COMPUTED_VALUE"""),33.0) -> 33 | J9: Anderson et al., 2001 | K9: HT | L9: 33
A10: =HYPERLINK("https://github.com/d-wkim/phd/blob/main/data/pdf/ahldén_2009.pdf","Ahldén et al., 2009") -> Ahldén et al., 2009 | B10: BPTB | C10: 25 | D10: =IFERROR(__xludf.DUMMYFUNCTION("join(""; "",A10:C10)"),"Ahldén et al., 2009; BPTB; 25") -> Ahldén et al., 2009; BPTB; 25 | E10: Anz et al., 2023; BPTB; 16 | F10: =IFERROR(__xludf.DUMMYFUNCTION("split(E10,"";"",FALSE)"),"Anz et al., 2023") -> Anz et al., 2023 | G10: =IFERROR(__xludf.DUMMYFUNCTION("""COMPUTED_VALUE""")," BPTB") -> BPTB | H10: =IFERROR(__xludf.DUMMYFUNCTION("""COMPUTED_VALUE"""),16.0) -> 16 | J10: Anz et al., 2023 | K10: BPTB | L10: 16
A11: =HYPERLINK("https://github.com/d-wkim/phd/blob/main/data/pdf/ahldén_2009.pdf","Ahldén et al., 2009") -> Ahldén et al., 2009 | B11: BPTB | C11: 25 | D11: =IFERROR(__xludf.DUMMYFUNCTION("join(""; "",A11:C11)"),"Ahldén et al., 2009; BPTB; 25") -> Ahldén et al., 2009; BPTB; 25 | E11: Anz et al., 2023; HT; 16 | F11: =IFERROR(__xludf.DUMMYFUNCTION("split(E11,"";"",FALSE)"),"Anz et al., 2023") -> Anz et al., 2023 | G11: =IFERROR(__xludf.DUMMYFUNCTION("""COMPUTED_VALUE""")," HT") -> HT | H11: =IFERROR(__xludf.DUMMYFUNCTION("""COMPUTED_VALUE"""),16.0) -> 16 | J11: Anz et al., 2023 | K11: HT | L11: 16
A12: =HYPERLINK("https://github.com/d-wkim/phd/blob/main/data/pdf/ahldén_2009.pdf","Ahldén et al., 2009") -> Ahldén et al., 2009 | B12: BPTB | C12: 25 | D12: =IFERROR(__xludf.DUMMYFUNCTION("join(""; "",A12:C12)"),"Ahldén et al., 2009; BPTB; 25") -> Ahldén et al., 2009; BPTB; 25 | E12: Aune et al., 2001; BPTB; 32 | F12: =IFERROR(__xludf.DUMMYFUNCTION("split(E12,"";"",FALSE)"),"Aune et al., 2001") -> Aune et al., 2001 | G12: =IFERROR(__xludf.DUMMYFUNCTION("""COMPUTED_VALUE""")," BPTB") -> BPTB | H12: =IFERROR(__xludf.DUMMYFUNCTION("""COMPUTED_VALUE"""),32.0) -> 32 | J12: Aune et al., 2001 | K12: BPTB | L12: 32
A13: =HYPERLINK("https://github.com/d-wkim/phd/blob/main/data/pdf/ahldén_2009.pdf","Ahldén et al., 2009") -> Ahldén et al., 2009 | B13: HT | C13: 22 | D13: =IFERROR(__xludf.DUMMYFUNCTION("join(""; "",A13:C13)"),"Ahldén et al., 2009; HT; 22") -> Ahldén et al., 2009; HT; 22 | E13: Aune et al., 2001; HT; 29 | F13: =IFERROR(__xludf.DUMMYFUNCTION("split(E13,"";"",FALSE)"),"Aune et al., 2001") -> Aune et al., 2001 | G13: =IFERROR(__xludf.DUMMYFUNCTION("""COMPUTED_VALUE""")," HT") -> HT | H13: =IFERROR(__xludf.DUMMYFUNCTION("""COMPUTED_VALUE"""),29.0) -> 29 | J13: Aune et al., 2001 | K13: HT | L13: 29
A14: =HYPERLINK("https://github.com/d-wkim/phd/blob/main/data/pdf/ahldén_2009.pdf","Ahldén et al., 2009") -> Ahldén et al., 2009 | B14: HT | C14: 22 | D14: =IFERROR(__xludf.DUMMYFUNCTION("join(""; "",A14:C14)"),"Ahldén et al., 2009; HT; 22") -> Ahldén et al., 2009; HT; 22 | E14: Barenius et al., 2010; BPTB; 78 | F14: =IFERROR(__xludf.DUMMYFUNCTION("split(E14,"";"",FALSE)"),"Barenius et al., 2010") -> Barenius et al., 2010 | G14: =IFERROR(__xludf.DUMMYFUNCTION("""COMPUTED_VALUE""")," BPTB") -> BPTB | H14: =IFERROR(__xludf.DUMMYFUNCTION("""COMPUTED_VALUE"""),78.0) -> 78 | J14: Barenius et al., 2010 | K14: BPTB | L14: 78
A15: =HYPERLINK("https://github.com/d-wkim/phd/blob/main/data/pdf/ahldén_2009.pdf","Ahldén et al., 2009") -> Ahldén et al., 2009 | B15: HT | C15: 22 | D15: =IFERROR(__xludf.DUMMYFUNCTION("join(""; "",A15:C15)"),"Ahldén et al., 2009; HT; 22") -> Ahldén et al., 2009; HT; 22 | E15: Barenius et al., 2010; HT; 75 | F15: =IFERROR(__xludf.DUMMYFUNCTION("split(E15,"";"",FALSE)"),"Barenius et al., 2010") -> Barenius et al., 2010 | G15: =IFERROR(__xludf.DUMMYFUNCTION("""COMPUTED_VALUE""")," HT") -> HT | H15: =IFERROR(__xludf.DUMMYFUNCTION("""COMPUTED_VALUE"""),75.0) -> 75 | J15: Barenius et al., 2010 | K15: HT | L15: 75
A16: =HYPERLINK("https://github.com/d-wkim/phd/blob/main/data/pdf/anderson_2001.pdf","Anderson et al., 2001") -> Anderson et al., 2001 | B16: BPTB | C16: 35 | D16: =IFERROR(__xludf.DUMMYFUNCTION("join(""; "",A16:C16)"),"Anderson et al., 2001; BPTB; 35") -> Anderson et al., 2001; BPTB; 35 | E16: Barié et al., 2020; BPTB; 43 | F16: =IFERROR(__xludf.DUMMYFUNCTION("split(E16,"";"",FALSE)"),"Barié et al., 2020") -> Barié et al., 2020 | G16: =IFERROR(__xludf.DUMMYFUNCTION("""COMPUTED_VALUE""")," BPTB") -> BPTB | H16: =IFERROR(__xludf.DUMMYFUNCTION("""COMPUTED_VALUE"""),43.0) -> 43 | J16: Barié et al., 2020 | K16: BPTB | L16: 43
A17: =HYPERLINK("https://github.com/d-wkim/phd/blob/main/data/pdf/anderson_2001.pdf","Anderson et al., 2001") -> Anderson et al., 2001 | B17: BPTB | C17: 35 | D17: =IFERROR(__xludf.DUMMYFUNCTION("join(""; "",A17:C17)"),"Anderson et al., 2001; BPTB; 35") -> Anderson et al., 2001; BPTB; 35 | E17: Barié et al., 2020; QT; 43 | F17: =IFERROR(__xludf.DUMMYFUNCTION("split(E17,"";"",FALSE)"),"Barié et al., 2020") -> Barié et al., 2020 | G17: =IFERROR(__xludf.DUMMYFUNCTION("""COMPUTED_VALUE""")," QT") -> QT | H17: =IFERROR(__xludf.DUMMYFUNCTION("""COMPUTED_VALUE"""),43.0) -> 43 | J17: Barié et al., 2020 | K17: QT | L17: 43
A18: =HYPERLINK("https://github.com/d-wkim/phd/blob/main/data/pdf/anderson_2001.pdf","Anderson et al., 2001") -> Anderson et al., 2001 | B18: HT | C18: 33 | D18: =IFERROR(__xludf.DUMMYFUNCTION("join(""; "",A18:C18)"),"Anderson et al., 2001; HT; 33") -> Anderson et al., 2001; HT; 33 | E18: Beynnon et al., 2002; BPTB; 22 | F18: =IFERROR(__xludf.DUMMYFUNCTION("split(E18,"";"",FALSE)"),"Beynnon et al., 2002") -> Beynnon et al., 2002 | G18: =IFERROR(__xludf.DUMMYFUNCTION("""COMPUTED_VALUE""")," BPTB") -> BPTB | H18: =IFERROR(__xludf.DUMMYFUNCTION("""COMPUTED_VALUE"""),22.0) -> 22 | J18: Beynnon et al., 2002 | K18: BPTB | L18: 22
A19: =HYPERLINK("https://github.com/d-wkim/phd/blob/main/data/pdf/anderson_2001.pdf","Anderson et al., 2001") -> Anderson et al., 2001 | B19: HT | C19: 33 | D19: =IFERROR(__xludf.DUMMYFUNCTION("join(""; "",A19:C19)"),"Anderson et al., 2001; HT; 33") -> Anderson et al., 2001; HT; 33 | E19: Beynnon et al., 2002; HT; 22 | F19: =IFERROR(__xludf.DUMMYFUNCTION("split(E19,"";"",FALSE)"),"Beynnon et al., 2002") -> Beynnon et al., 2002 | G19: =IFERROR(__xludf.DUMMYFUNCTION("""COMPUTED_VALUE""")," HT") -> HT | H19: =IFERROR(__xludf.DUMMYFUNCTION("""COMPUTED_VALUE"""),22.0) -> 22 | J19: Beynnon et al., 2002 | K19: HT | L19: 22
A20: =HYPERLINK("https://github.com/d-wkim/phd/blob/main/data/pdf/anz_2023.pdf","Anz et al., 2023") -> Anz et al., 2023 | B20: BPTB | C20: 16 | D20: =IFERROR(__xludf.DUMMYFUNCTION("join(""; "",A20:C20)"),"Anz et al., 2023; BPTB; 16") -> Anz et al., 2023; BPTB; 16 | E20: Bi et al., 2018; HT; 62 | F20: =IFERROR(__xludf.DUMMYFUNCTION("split(E20,"";"",FALSE)"),"Bi et al., 2018") -> Bi et al., 2018 | G20: =IFERROR(__xludf.DUMMYFUNCTION("""COMPUTED_VALUE""")," HT") -> HT | H20: =IFERROR(__xludf.DUMMYFUNCTION("""COMPUTED_VALUE"""),62.0) -> 62 | J20: Bi et al., 2018 | K20: HT | L20: 62
A21: =HYPERLINK("https://github.com/d-wkim/phd/blob/main/data/pdf/anz_2023.pdf","Anz et al., 2023") -> Anz et al., 2023 | B21: HT | C21: 16 | D21: =IFERROR(__xludf.DUMMYFUNCTION("join(""; "",A21:C21)"),"Anz et al., 2023; HT; 16") -> Anz et al., 2023; HT; 16 | E21: Bi et al., 2018; PLT; 62 | F21: =IFERROR(__xludf.DUMMYFUNCTION("split(E21,"";"",FALSE)"),"Bi et al., 2018") -> Bi et al., 2018 | G21: =IFERROR(__xludf.DUMMYFUNCTION("""COMPUTED_VALUE""")," PLT") -> PLT | H21: =IFERROR(__xludf.DUMMYFUNCTION("""COMPUTED_VALUE"""),62.0) -> 62 | J21: Bi et al., 2018 | K21: PLT | L21: 62
A22: =HYPERLINK("https://github.com/d-wkim/phd/blob/main/data/pdf/aune_2001.pdf","Aune et al., 2001") -> Aune et al., 2001 | B22: BPTB | C22: 32 | D22: =IFERROR(__xludf.DUMMYFUNCTION("join(""; "",A22:C22)"),"Aune et al., 2001; BPTB; 32") -> Aune et al., 2001; BPTB; 32 | E22: Björnsson et al., 2016; BPTB; 61 | F22: =IFERROR(__xludf.DUMMYFUNCTION("split(E22,"";"",FALSE)"),"Björnsson et al., 2016") -> Björnsson et al., 2016 | G22: =IFERROR(__xludf.DUMMYFUNCTION("""COMPUTED_VALUE""")," BPTB") -> BPTB | H22: =IFERROR(__xludf.DUMMYFUNCTION("""COMPUTED_VALUE"""),61.0) -> 61 | J22: Björnsson et al., 2016 | K22: BPTB | L22: 61
A23: =HYPERLINK("https://github.com/d-wkim/phd/blob/main/data/pdf/aune_2001.pdf","Aune et al., 2001") -> Aune et al., 2001 | B23: HT | C23: 29 | D23: =IFERROR(__xludf.DUMMYFUNCTION("join(""; "",A23:C23)"),"Aune et al., 2001; HT; 29") -> Aune et al., 2001; HT; 29 | E23: Björnsson et al., 2016; HT; 86 | F23: =IFERROR(__xludf.DUMMYFUNCTION("split(E23,"";"",FALSE)"),"Björnsson et al., 2016") -> Björnsson et al., 2016 | G23: =IFERROR(__xludf.DUMMYFUNCTION("""COMPUTED_VALUE""")," HT") -> HT | H23: =IFERROR(__xludf.DUMMYFUNCTION("""COMPUTED_VALUE"""),86.0) -> 86 | J23: Björnsson et al., 2016 | K23: HT | L23: 86
A24: =HYPERLINK("https://github.com/d-wkim/phd/blob/main/data/pdf/barenius_2010.pdf","Barenius et al., 2010") -> Barenius et al., 2010 | B24: BPTB | C24: 78 | D24: =IFERROR(__xludf.DUMMYFUNCTION("join(""; "",A24:C24)"),"Barenius et al., 2010; BPTB; 78") -> Barenius et al., 2010; BPTB; 78 | E24: Bottoni et al., 2015; HT; 44 | F24: =IFERROR(__xludf.DUMMYFUNCTION("split(E24,"";"",FALSE)"),"Bottoni et al., 2015") -> Bottoni et al., 2015 | G24: =IFERROR(__xludf.DUMMYFUNCTION("""COMPUTED_VALUE""")," HT") -> HT | H24: =IFERROR(__xludf.DUMMYFUNCTION("""COMPUTED_VALUE"""),44.0) -> 44 | J24: Bottoni et al., 2015 | K24: HT | L24: 44
A25: =HYPERLINK("https://github.com/d-wkim/phd/blob/main/data/pdf/barenius_2010.pdf","Barenius et al., 2010") -> Barenius et al., 2010 | B25: BPTB | C25: 78 | D25: =IFERROR(__xludf.DUMMYFUNCTION("join(""; "",A25:C25)"),"Barenius et al., 2010; BPTB; 78") -> Barenius et al., 2010; BPTB; 78 | E25: Bottoni et al., 2015; TA; 36 | F25: =IFERROR(__xludf.DUMMYFUNCTION("split(E25,"";"",FALSE)"),"Bottoni et al., 2015") -> Bottoni et al., 2015 | G25: =IFERROR(__xludf.DUMMYFUNCTION("""COMPUTED_VALUE""")," TA") -> TA | H25: =IFERROR(__xludf.DUMMYFUNCTION("""COMPUTED_VALUE"""),36.0) -> 36 | J25: Bottoni et al., 2015 | K25: TA | L25: 36
A26: =HYPERLINK("https://github.com/d-wkim/phd/blob/main/data/pdf/barenius_2010.pdf","Barenius et al., 2010") -> Barenius et al., 2010 | B26: HT | C26: 75 | D26: =IFERROR(__xludf.DUMMYFUNCTION("join(""; "",A26:C26)"),"Barenius et al., 2010; HT; 75") -> Barenius et al., 2010; HT; 75 | E26: Butt et al., 2024; HT; 30 | F26: =IFERROR(__xludf.DUMMYFUNCTION("split(E26,"";"",FALSE)"),"Butt et al., 2024") -> Butt et al., 2024 | G26: =IFERROR(__xludf.DUMMYFUNCTION("""COMPUTED_VALUE""")," HT") -> HT | H26: =IFERROR(__xludf.DUMMYFUNCTION("""COMPUTED_VALUE"""),30.0) -> 30 | J26: Butt et al., 2024 | K26: HT | L26: 30
A27: =HYPERLINK("https://github.com/d-wkim/phd/blob/main/data/pdf/barenius_2010.pdf","Barenius et al., 2010") -> Barenius et al., 2010 | B27: HT | C27: 75 | D27: =IFERROR(__xludf.DUMMYFUNCTION("join(""; "",A27:C27)"),"Barenius et al., 2010; HT; 75") -> Barenius et al., 2010; HT; 75 | E27: Butt et al., 2024; PLT; 30 | F27: =IFERROR(__xludf.DUMMYFUNCTION("split(E27,"";"",FALSE)"),"Butt et al., 2024") -> Butt et al., 2024 | G27: =IFERROR(__xludf.DUMMYFUNCTION("""COMPUTED_VALUE""")," PLT") -> PLT | H27: =IFERROR(__xludf.DUMMYFUNCTION("""COMPUTED_VALUE"""),30.0) -> 30 | J27: Butt et al., 2024 | K27: PLT | L27: 30
A28: =HYPERLINK("https://github.com/d-wkim/phd/blob/main/data/pdf/barié_2020.pdf","Barié et al., 2020") -> Barié et al., 2020 | B28: BPTB | C28: 43 | D28: =IFERROR(__xludf.DUMMYFUNCTION("join(""; "",A28:C28)"),"Barié et al., 2020; BPTB; 43") -> Barié et al., 2020; BPTB; 43 | E28: Calvert et al., 2025; HT; 92 | F28: =IFERROR(__xludf.DUMMYFUNCTION("split(E28,"";"",FALSE)"),"Calvert et al., 2025") -> Calvert et al., 2025 | G28: =IFERROR(__xludf.DUMMYFUNCTION("""COMPUTED_VALUE""")," HT") -> HT | H28: =IFERROR(__xludf.DUMMYFUNCTION("""COMPUTED_VALUE"""),92.0) -> 92 | J28: Calvert et al., 2025 | K28: HT | L28: 92
A29: =HYPERLINK("https://github.com/d-wkim/phd/blob/main/data/pdf/barié_2020.pdf","Barié et al., 2020") -> Barié et al., 2020 | B29: BPTB | C29: 43 | D29: =IFERROR(__xludf.DUMMYFUNCTION("join(""; "",A29:C29)"),"Barié et al., 2020; BPTB; 43") -> Barié et al., 2020; BPTB; 43 | E29: Calvert et al., 2025; QT; 89 | F29: =IFERROR(__xludf.DUMMYFUNCTION("split(E29,"";"",FALSE)"),"Calvert et al., 2025") -> Calvert et al., 2025 | G29: =IFERROR(__xludf.DUMMYFUNCTION("""COMPUTED_VALUE""")," QT") -> QT | H29: =IFERROR(__xludf.DUMMYFUNCTION("""COMPUTED_VALUE"""),89.0) -> 89 | J29: Calvert et al., 2025 | K29: QT | L29: 89
A30: =HYPERLINK("https://github.com/d-wkim/phd/blob/main/data/pdf/barié_2020.pdf","Barié et al., 2020") -> Barié et al., 2020 | B30: BPTB | C30: 43 | D30: =IFERROR(__xludf.DUMMYFUNCTION("join(""; "",A30:C30)"),"Barié et al., 2020; BPTB; 43") -> Barié et al., 2020; BPTB; 43 | E30: Ejerhed et al., 2003; BPTB; 32 | F30: =IFERROR(__xludf.DUMMYFUNCTION("split(E30,"";"",FALSE)"),"Ejerhed et al., 2003") -> Ejerhed et al., 2003 | G30: =IFERROR(__xludf.DUMMYFUNCTION("""COMPUTED_VALUE""")," BPTB") -> BPTB | H30: =IFERROR(__xludf.DUMMYFUNCTION("""COMPUTED_VALUE"""),32.0) -> 32 | J30: Ejerhed et al., 2003 | K30: BPTB | L30: 32
A31: =HYPERLINK("https://github.com/d-wkim/phd/blob/main/data/pdf/barié_2020.pdf","Barié et al., 2020") -> Barié et al., 2020 | B31: BPTB | C31: 43 | D31: =IFERROR(__xludf.DUMMYFUNCTION("join(""; "",A31:C31)"),"Barié et al., 2020; BPTB; 43") -> Barié et al., 2020; BPTB; 43 | E31: Ejerhed et al., 2003; HT; 34 | F31: =IFERROR(__xludf.DUMMYFUNCTION("split(E31,"";"",FALSE)"),"Ejerhed et al., 2003") -> Ejerhed et al., 2003 | G31: =IFERROR(__xludf.DUMMYFUNCTION("""COMPUTED_VALUE""")," HT") -> HT | H31: =IFERROR(__xludf.DUMMYFUNCTION("""COMPUTED_VALUE"""),34.0) -> 34 | J31: Ejerhed et al., 2003 | K31: HT | L31: 34
A32: =HYPERLINK("https://github.com/d-wkim/phd/blob/main/data/pdf/barié_2020.pdf","Barié et al., 2020") -> Barié et al., 2020 | B32: QT | C32: 43 | D32: =IFERROR(__xludf.DUMMYFUNCTION("join(""; "",A32:C32)"),"Barié et al., 2020; QT; 43") -> Barié et al., 2020; QT; 43 | E32: Eriksson et al., 2001; BPTB; 42 | F32: =IFERROR(__xludf.DUMMYFUNCTION("split(E32,"";"",FALSE)"),"Eriksson et al., 2001") -> Eriksson et al., 2001 | G32: =IFERROR(__xludf.DUMMYFUNCTION("""COMPUTED_VALUE""")," BPTB") -> BPTB | H32: =IFERROR(__xludf.DUMMYFUNCTION("""COMPUTED_VALUE"""),42.0) -> 42 | J32: Eriksson et al., 2001 | K32: BPTB | L32: 42
A33: =HYPERLINK("https://github.com/d-wkim/phd/blob/main/data/pdf/barié_2020.pdf","Barié et al., 2020") -> Barié et al., 2020 | B33: QT | C33: 43 | D33: =IFERROR(__xludf.DUMMYFUNCTION("join(""; "",A33:C33)"),"Barié et al., 2020; QT; 43") -> Barié et al., 2020; QT; 43 | E33: Eriksson et al., 2001; HT; 47 | F33: =IFERROR(__xludf.DUMMYFUNCTION("split(E33,"";"",FALSE)"),"Eriksson et al., 2001") -> Eriksson et al., 2001 | G33: =IFERROR(__xludf.DUMMYFUNCTION("""COMPUTED_VALUE""")," HT") -> HT | H33: =IFERROR(__xludf.DUMMYFUNCTION("""COMPUTED_VALUE"""),47.0) -> 47 | J33: Eriksson et al., 2001 | K33: HT | L33: 47
A34: =HYPERLINK("https://github.com/d-wkim/phd/blob/main/data/pdf/barié_2020.pdf","Barié et al., 2020") -> Barié et al., 2020 | B34: QT | C34: 43 | D34: =IFERROR(__xludf.DUMMYFUNCTION("join(""; "",A34:C34)"),"Barié et al., 2020; QT; 43") -> Barié et al., 2020; QT; 43 | E34: Feller & Webster, 2003; BPTB; 27 | F34: =IFERROR(__xludf.DUMMYFUNCTION("split(E34,"";"",FALSE)"),"Feller & Webster, 2003") -> Feller & Webster, 2003 | G34: =IFERROR(__xludf.DUMMYFUNCTION("""COMPUTED_VALUE""")," BPTB") -> BPTB | H34: =IFERROR(__xludf.DUMMYFUNCTION("""COMPUTED_VALUE"""),27.0) -> 27 | J34: Feller & Webster, 2003 | K34: BPTB | L34: 27
A35: =HYPERLINK("https://github.com/d-wkim/phd/blob/main/data/pdf/barié_2020.pdf","Barié et al., 2020") -> Barié et al., 2020 | B35: QT | C35: 43 | D35: =IFERROR(__xludf.DUMMYFUNCTION("join(""; "",A35:C35)"),"Barié et al., 2020; QT; 43") -> Barié et al., 2020; QT; 43 | E35: Feller & Webster, 2003; HT; 21 | F35: =IFERROR(__xludf.DUMMYFUNCTION("split(E35,"";"",FALSE)"),"Feller & Webster, 2003") -> Feller & Webster, 2003 | G35: =IFERROR(__xludf.DUMMYFUNCTION("""COMPUTED_VALUE""")," HT") -> HT | H35: =IFERROR(__xludf.DUMMYFUNCTION("""COMPUTED_VALUE"""),21.0) -> 21 | J35: Feller & Webster, 2003 | K35: HT | L35: 21
A36: =HYPERLINK("https://github.com/d-wkim/phd/blob/main/data/pdf/beynnon_2002.pdf","Beynnon et al., 2002") -> Beynnon et al., 2002 | B36: BPTB | C36: 22 | D36: =IFERROR(__xludf.DUMMYFUNCTION("join(""; "",A36:C36)"),"Beynnon et al., 2002; BPTB; 22") -> Beynnon et al., 2002; BPTB; 22 | E36: Gifstad et al., 2013; BPTB; 41 | F36: =IFERROR(__xludf.DUMMYFUNCTION("split(E36,"";"",FALSE)"),"Gifstad et al., 2013") -> Gifstad et al., 2013 | G36: =IFERROR(__xludf.DUMMYFUNCTION("""COMPUTED_VALUE""")," BPTB") -> BPTB | H36: =IFERROR(__xludf.DUMMYFUNCTION("""COMPUTED_VALUE"""),41.0) -> 41 | J36: Gifstad et al., 2013 | K36: BPTB | L36: 41
A37: =HYPERLINK("https://github.com/d-wkim/phd/blob/main/data/pdf/beynnon_2002.pdf","Beynnon et al., 2002") -> Beynnon et al., 2002 | B37: BPTB | C37: 22 | D37: =IFERROR(__xludf.DUMMYFUNCTION("join(""; "",A37:C37)"),"Beynnon et al., 2002; BPTB; 22") -> Beynnon et al., 2002; BPTB; 22 | E37: Gifstad et al., 2013; HT; 36 | F37: =IFERROR(__xludf.DUMMYFUNCTION("split(E37,"";"",FALSE)"),"Gifstad et al., 2013") -> Gifstad et al., 2013 | G37: =IFERROR(__xludf.DUMMYFUNCTION("""COMPUTED_VALUE""")," HT") -> HT | H37: =IFERROR(__xludf.DUMMYFUNCTION("""COMPUTED_VALUE"""),36.0) -> 36 | J37: Gifstad et al., 2013 | K37: HT | L37: 36
A38: =HYPERLINK("https://github.com/d-wkim/phd/blob/main/data/pdf/beynnon_2002.pdf","Beynnon et al., 2002") -> Beynnon et al., 2002 | B38: HT | C38: 22 | D38: =IFERROR(__xludf.DUMMYFUNCTION("join(""; "",A38:C38)"),"Beynnon et al., 2002; HT; 22") -> Beynnon et al., 2002; HT; 22 | E38: Guglielmetti et al., 2021; BPTB; 31 | F38: =IFERROR(__xludf.DUMMYFUNCTION("split(E38,"";"",FALSE)"),"Guglielmetti et al., 2021") -> Guglielmetti et al., 2021 | G38: =IFERROR(__xludf.DUMMYFUNCTION("""COMPUTED_VALUE""")," BPTB") -> BPTB | H38: =IFERROR(__xludf.DUMMYFUNCTION("""COMPUTED_VALUE"""),31.0) -> 31 | J38: Guglielmetti et al., 2021 | K38: BPTB | L38: 31
A39: =HYPERLINK("https://github.com/d-wkim/phd/blob/main/data/pdf/beynnon_2002.pdf","Beynnon et al., 2002") -> Beynnon et al., 2002 | B39: HT | C39: 22 | D39: =IFERROR(__xludf.DUMMYFUNCTION("join(""; "",A39:C39)"),"Beynnon et al., 2002; HT; 22") -> Beynnon et al., 2002; HT; 22 | E39: Guglielmetti et al., 2021; HT; 31 | F39: =IFERROR(__xludf.DUMMYFUNCTION("split(E39,"";"",FALSE)"),"Guglielmetti et al., 2021") -> Guglielmetti et al., 2021 | G39: =IFERROR(__xludf.DUMMYFUNCTION("""COMPUTED_VALUE""")," HT") -> HT | H39: =IFERROR(__xludf.DUMMYFUNCTION("""COMPUTED_VALUE"""),31.0) -> 31 | J39: Guglielmetti et al., 2021 | K39: HT | L39: 31
A40: =HYPERLINK("https://github.com/d-wkim/phd/blob/main/data/pdf/bi_2018.pdf","Bi et al., 2018") -> Bi et al., 2018 | B40: HT | C40: 62 | D40: =IFERROR(__xludf.DUMMYFUNCTION("join(""; "",A40:C40)"),"Bi et al., 2018; HT; 62") -> Bi et al., 2018; HT; 62 | E40: Harilainen et al., 2006; BPTB; 37 | F40: =IFERROR(__xludf.DUMMYFUNCTION("split(E40,"";"",FALSE)"),"Harilainen et al., 2006") -> Harilainen et al., 2006 | G40: =IFERROR(__xludf.DUMMYFUNCTION("""COMPUTED_VALUE""")," BPTB") -> BPTB | H40: =IFERROR(__xludf.DUMMYFUNCTION("""COMPUTED_VALUE"""),37.0) -> 37 | J40: Harilainen et al., 2006 | K40: BPTB | L40: 37
A41: =HYPERLINK("https://github.com/d-wkim/phd/blob/main/data/pdf/bi_2018.pdf","Bi et al., 2018") -> Bi et al., 2018 | B41: HT | C41: 62 | D41: =IFERROR(__xludf.DUMMYFUNCTION("join(""; "",A41:C41)"),"Bi et al., 2018; HT; 62") -> Bi et al., 2018; HT; 62 | E41: Harilainen et al., 2006; HT; 37 | F41: =IFERROR(__xludf.DUMMYFUNCTION("split(E41,"";"",FALSE)"),"Harilainen et al., 2006") -> Harilainen et al., 2006 | G41: =IFERROR(__xludf.DUMMYFUNCTION("""COMPUTED_VALUE""")," HT") -> HT | H41: =IFERROR(__xludf.DUMMYFUNCTION("""COMPUTED_VALUE"""),37.0) -> 37 | J41: Harilainen et al., 2006 | K41: HT | L41: 37
A42: =HYPERLINK("https://github.com/d-wkim/phd/blob/main/data/pdf/bi_2018.pdf","Bi et al., 2018") -> Bi et al., 2018 | B42: HT | C42: 62 | D42: =IFERROR(__xludf.DUMMYFUNCTION("join(""; "",A42:C42)"),"Bi et al., 2018; HT; 62") -> Bi et al., 2018; HT; 62 | E42: Heijne & Werner, 2010; BPTB; 30 | F42: =IFERROR(__xludf.DUMMYFUNCTION("split(E42,"";"",FALSE)"),"Heijne & Werner, 2010") -> Heijne & Werner, 2010 | G42: =IFERROR(__xludf.DUMMYFUNCTION("""COMPUTED_VALUE""")," BPTB") -> BPTB | H42: =IFERROR(__xludf.DUMMYFUNCTION("""COMPUTED_VALUE"""),30.0) -> 30 | J42: Heijne & Werner, 2010 | K42: BPTB | L42: 30
A43: =HYPERLINK("https://github.com/d-wkim/phd/blob/main/data/pdf/bi_2018.pdf","Bi et al., 2018") -> Bi et al., 2018 | B43: PLT | C43: 62 | D43: =IFERROR(__xludf.DUMMYFUNCTION("join(""; "",A43:C43)"),"Bi et al., 2018; PLT; 62") -> Bi et al., 2018; PLT; 62 | E43: Heijne & Werner, 2010; HT; 29 | F43: =IFERROR(__xludf.DUMMYFUNCTION("split(E43,"";"",FALSE)"),"Heijne & Werner, 2010") -> Heijne & Werner, 2010 | G43: =IFERROR(__xludf.DUMMYFUNCTION("""COMPUTED_VALUE""")," HT") -> HT | H43: =IFERROR(__xludf.DUMMYFUNCTION("""COMPUTED_VALUE"""),29.0) -> 29 | J43: Heijne & Werner, 2010 | K43: HT | L43: 29
A44: =HYPERLINK("https://github.com/d-wkim/phd/blob/main/data/pdf/bi_2018.pdf","Bi et al., 2018") -> Bi et al., 2018 | B44: PLT | C44: 62 | D44: =IFERROR(__xludf.DUMMYFUNCTION("join(""; "",A44:C44)"),"Bi et al., 2018; PLT; 62") -> Bi et al., 2018; PLT; 62 | E44: Holm et al., 2010; BPTB; 28 | F44: =IFERROR(__xludf.DUMMYFUNCTION("split(E44,"";"",FALSE)"),"Holm et al., 2010") -> Holm et al., 2010 | G44: =IFERROR(__xludf.DUMMYFUNCTION("""COMPUTED_VALUE""")," BPTB") -> BPTB | H44: =IFERROR(__xludf.DUMMYFUNCTION("""COMPUTED_VALUE"""),28.0) -> 28 | J44: Holm et al., 2010 | K44: BPTB | L44: 28
A45: =HYPERLINK("https://github.com/d-wkim/phd/blob/main/data/pdf/bi_2018.pdf","Bi et al., 2018") -> Bi et al., 2018 | B45: PLT | C45: 62 | D45: =IFERROR(__xludf.DUMMYFUNCTION("join(""; "",A45:C45)"),"Bi et al., 2018; PLT; 62") -> Bi et al., 2018; PLT; 62 | E45: Holm et al., 2010; HT; 29 | F45: =IFERROR(__xludf.DUMMYFUNCTION("split(E45,"";"",FALSE)"),"Holm et al., 2010") -> Holm et al., 2010 | G45: =IFERROR(__xludf.DUMMYFUNCTION("""COMPUTED_VALUE""")," HT") -> HT | H45: =IFERROR(__xludf.DUMMYFUNCTION("""COMPUTED_VALUE"""),29.0) -> 29 | J45: Holm et al., 2010 | K45: HT | L45: 29
A46: =HYPERLINK("https://github.com/d-wkim/phd/blob/main/data/pdf/björnsson_2016.pdf","Björnsson et al., 2016") -> Björnsson et al., 2016 | B46: BPTB | C46: 61 | D46: =IFERROR(__xludf.DUMMYFUNCTION("join(""; "",A46:C46)"),"Björnsson et al., 2016; BPTB; 61") -> Björnsson et al., 2016; BPTB; 61 | E46: Horstmann et al., 2022; HT; 26 | F46: =IFERROR(__xludf.DUMMYFUNCTION("split(E46,"";"",FALSE)"),"Horstmann et al., 2022") -> Horstmann et al., 2022 | G46: =IFERROR(__xludf.DUMMYFUNCTION("""COMPUTED_VALUE""")," HT") -> HT | H46: =IFERROR(__xludf.DUMMYFUNCTION("""COMPUTED_VALUE"""),26.0) -> 26 | J46: Horstmann et al., 2022 | K46: HT | L46: 26
A47: =HYPERLINK("https://github.com/d-wkim/phd/blob/main/data/pdf/björnsson_2016.pdf","Björnsson et al., 2016") -> Björnsson et al., 2016 | B47: BPTB | C47: 61 | D47: =IFERROR(__xludf.DUMMYFUNCTION("join(""; "",A47:C47)"),"Björnsson et al., 2016; BPTB; 61") -> Björnsson et al., 2016; BPTB; 61 | E47: Horstmann et al., 2022; QT; 23 | F47: =IFERROR(__xludf.DUMMYFUNCTION("split(E47,"";"",FALSE)"),"Horstmann et al., 2022") -> Horstmann et al., 2022 | G47: =IFERROR(__xludf.DUMMYFUNCTION("""COMPUTED_VALUE""")," QT") -> QT | H47: =IFERROR(__xludf.DUMMYFUNCTION("""COMPUTED_VALUE"""),23.0) -> 23 | J47: Horstmann et al., 2022 | K47: QT | L47: 23
A48: =HYPERLINK("https://github.com/d-wkim/phd/blob/main/data/pdf/björnsson_2016.pdf","Björnsson et al., 2016") -> Björnsson et al., 2016 | B48: BPTB | C48: 61 | D48: =IFERROR(__xludf.DUMMYFUNCTION("join(""; "",A48:C48)"),"Björnsson et al., 2016; BPTB; 61") -> Björnsson et al., 2016; BPTB; 61 | E48: Ibrahim et al., 2005; BPTB; 40 | F48: =IFERROR(__xludf.DUMMYFUNCTION("split(E48,"";"",FALSE)"),"Ibrahim et al., 2005") -> Ibrahim et al., 2005 | G48: =IFERROR(__xludf.DUMMYFUNCTION("""COMPUTED_VALUE""")," BPTB") -> BPTB | H48: =IFERROR(__xludf.DUMMYFUNCTION("""COMPUTED_VALUE"""),40.0) -> 40 | J48: Ibrahim et al., 2005 | K48: BPTB | L48: 40
A49: =HYPERLINK("https://github.com/d-wkim/phd/blob/main/data/pdf/björnsson_2016.pdf","Björnsson et al., 2016") -> Björnsson et al., 2016 | B49: BPTB | C49: 61 | D49: =IFERROR(__xludf.DUMMYFUNCTION("join(""; "",A49:C49)"),"Björnsson et al., 2016; BPTB; 61") -> Björnsson et al., 2016; BPTB; 61 | E49: Ibrahim et al., 2005; HT; 46 | F49: =IFERROR(__xludf.DUMMYFUNCTION("split(E49,"";"",FALSE)"),"Ibrahim et al., 2005") -> Ibrahim et al., 2005 | G49: =IFERROR(__xludf.DUMMYFUNCTION("""COMPUTED_VALUE""")," HT") -> HT | H49: =IFERROR(__xludf.DUMMYFUNCTION("""COMPUTED_VALUE"""),46.0) -> 46 | J49: Ibrahim et al., 2005 | K49: HT | L49: 46
A50: =HYPERLINK("https://github.com/d-wkim/phd/blob/main/data/pdf/björnsson_2016.pdf","Björnsson et al., 2016") -> Björnsson et al., 2016 | B50: BPTB | C50: 61 | D50: =IFERROR(__xludf.DUMMYFUNCTION("join(""; "",A50:C50)"),"Björnsson et al., 2016; BPTB; 61") -> Björnsson et al., 2016; BPTB; 61 | E50: Ibrahim et al., 2005; HT; 45 | F50: =IFERROR(__xludf.DUMMYFUNCTION("split(E50,"";"",FALSE)"),"Ibrahim et al., 2005") -> Ibrahim et al., 2005 | G50: =IFERROR(__xludf.DUMMYFUNCTION("""COMPUTED_VALUE""")," HT") -> HT | H50: =IFERROR(__xludf.DUMMYFUNCTION("""COMPUTED_VALUE"""),45.0) -> 45 | J50: Ibrahim et al., 2005 | K50: HT | L50: 45
A51: =HYPERLINK("https://github.com/d-wkim/phd/blob/main/data/pdf/björnsson_2016.pdf","Björnsson et al., 2016") -> Björnsson et al., 2016 | B51: HT | C51: 86 | D51: =IFERROR(__xludf.DUMMYFUNCTION("join(""; "",A51:C51)"),"Björnsson et al., 2016; HT; 86") -> Björnsson et al., 2016; HT; 86 | E51: Iliopoulos et al., 2017; BPTB; 45 | F51: =IFERROR(__xludf.DUMMYFUNCTION("split(E51,"";"",FALSE)"),"Iliopoulos et al., 2017") -> Iliopoulos et al., 2017 | G51: =IFERROR(__xludf.DUMMYFUNCTION("""COMPUTED_VALUE""")," BPTB") -> BPTB | H51: =IFERROR(__xludf.DUMMYFUNCTION("""COMPUTED_VALUE"""),45.0) -> 45 | J51: Iliopoulos et al., 2017 | K51: BPTB | L51: 45
A52: =HYPERLINK("https://github.com/d-wkim/phd/blob/main/data/pdf/björnsson_2016.pdf","Björnsson et al., 2016") -> Björnsson et al., 2016 | B52: HT | C52: 86 | D52: =IFERROR(__xludf.DUMMYFUNCTION("join(""; "",A52:C52)"),"Björnsson et al., 2016; HT; 86") -> Björnsson et al., 2016; HT; 86 | E52: Iliopoulos et al., 2017; HT; 45 | F52: =IFERROR(__xludf.DUMMYFUNCTION("split(E52,"";"",FALSE)"),"Iliopoulos et al., 2017") -> Iliopoulos et al., 2017 | G52: =IFERROR(__xludf.DUMMYFUNCTION("""COMPUTED_VALUE""")," HT") -> HT | H52: =IFERROR(__xludf.DUMMYFUNCTION("""COMPUTED_VALUE"""),45.0) -> 45 | J52: Iliopoulos et al., 2017 | K52: HT | L52: 45
A53: =HYPERLINK("https://github.com/d-wkim/phd/blob/main/data/pdf/björnsson_2016.pdf","Björnsson et al., 2016") -> Björnsson et al., 2016 | B53: HT | C53: 86 | D53: =IFERROR(__xludf.DUMMYFUNCTION("join(""; "",A53:C53)"),"Björnsson et al., 2016; HT; 86") -> Björnsson et al., 2016; HT; 86 | E53: Jansson et al., 2003; BPTB; 43 | F53: =IFERROR(__xludf.DUMMYFUNCTION("split(E53,"";"",FALSE)"),"Jansson et al., 2003") -> Jansson et al., 2003 | G53: =IFERROR(__xludf.DUMMYFUNCTION("""COMPUTED_VALUE""")," BPTB") -> BPTB | H53: =IFERROR(__xludf.DUMMYFUNCTION("""COMPUTED_VALUE"""),43.0) -> 43 | J53: Jansson et al., 2003 | K53: BPTB | L53: 43
A54: =HYPERLINK("https://github.com/d-wkim/phd/blob/main/data/pdf/björnsson_2016.pdf","Björnsson et al., 2016") -> Björnsson et al., 2016 | B54: HT | C54: 86 | D54: =IFERROR(__xludf.DUMMYFUNCTION("join(""; "",A54:C54)"),"Björnsson et al., 2016; HT; 86") -> Björnsson et al., 2016; HT; 86 | E54: Jansson et al., 2003; HT; 46 | F54: =IFERROR(__xludf.DUMMYFUNCTION("split(E54,"";"",FALSE)"),"Jansson et al., 2003") -> Jansson et al., 2003 | G54: =IFERROR(__xludf.DUMMYFUNCTION("""COMPUTED_VALUE""")," HT") -> HT | H54: =IFERROR(__xludf.DUMMYFUNCTION("""COMPUTED_VALUE"""),46.0) -> 46 | J54: Jansson et al., 2003 | K54: HT | L54: 46
A55: =HYPERLINK("https://github.com/d-wkim/phd/blob/main/data/pdf/björnsson_2016.pdf","Björnsson et al., 2016") -> Björnsson et al., 2016 | B55: HT | C55: 86 | D55: =IFERROR(__xludf.DUMMYFUNCTION("join(""; "",A55:C55)"),"Björnsson et al., 2016; HT; 86") -> Björnsson et al., 2016; HT; 86 | E55: Kautzner et al., 2015; BPTB; 74 | F55: =IFERROR(__xludf.DUMMYFUNCTION("split(E55,"";"",FALSE)"),"Kautzner et al., 2015") -> Kautzner et al., 2015 | G55: =IFERROR(__xludf.DUMMYFUNCTION("""COMPUTED_VALUE""")," BPTB") -> BPTB | H55: =IFERROR(__xludf.DUMMYFUNCTION("""COMPUTED_VALUE"""),74.0) -> 74 | J55: Kautzner et al., 2015 | K55: BPTB | L55: 74
A56: =HYPERLINK("https://github.com/d-wkim/phd/blob/main/data/pdf/bottoni_2015.pdf","Bottoni et al., 2015") -> Bottoni et al., 2015 | B56: HT | C56: 44 | D56: =IFERROR(__xludf.DUMMYFUNCTION("join(""; "",A56:C56)"),"Bottoni et al., 2015; HT; 44") -> Bottoni et al., 2015; HT; 44 | E56: Kautzner et al., 2015; HT; 73 | F56: =IFERROR(__xludf.DUMMYFUNCTION("split(E56,"";"",FALSE)"),"Kautzner et al., 2015") -> Kautzner et al., 2015 | G56: =IFERROR(__xludf.DUMMYFUNCTION("""COMPUTED_VALUE""")," HT") -> HT | H56: =IFERROR(__xludf.DUMMYFUNCTION("""COMPUTED_VALUE"""),73.0) -> 73 | J56: Kautzner et al., 2015 | K56: HT | L56: 73
A57: =HYPERLINK("https://github.com/d-wkim/phd/blob/main/data/pdf/bottoni_2015.pdf","Bottoni et al., 2015") -> Bottoni et al., 2015 | B57: HT | C57: 44 | D57: =IFERROR(__xludf.DUMMYFUNCTION("join(""; "",A57:C57)"),"Bottoni et al., 2015; HT; 44") -> Bottoni et al., 2015; HT; 44 | E57: Komzak et al., 2022; BPTB; 36 | F57: =IFERROR(__xludf.DUMMYFUNCTION("split(E57,"";"",FALSE)"),"Komzak et al., 2022") -> Komzak et al., 2022 | G57: =IFERROR(__xludf.DUMMYFUNCTION("""COMPUTED_VALUE""")," BPTB") -> BPTB | H57: =IFERROR(__xludf.DUMMYFUNCTION("""COMPUTED_VALUE"""),36.0) -> 36 | J57: Komzak et al., 2022 | K57: BPTB | L57: 36
A58: =HYPERLINK("https://github.com/d-wkim/phd/blob/main/data/pdf/bottoni_2015.pdf","Bottoni et al., 2015") -> Bottoni et al., 2015 | B58: TA | C58: 36 | D58: =IFERROR(__xludf.DUMMYFUNCTION("join(""; "",A58:C58)"),"Bottoni et al., 2015; TA; 36") -> Bottoni et al., 2015; TA; 36 | E58: Komzak et al., 2022; QT; 36 | F58: =IFERROR(__xludf.DUMMYFUNCTION("split(E58,"";"",FALSE)"),"Komzak et al., 2022") -> Komzak et al., 2022 | G58: =IFERROR(__xludf.DUMMYFUNCTION("""COMPUTED_VALUE""")," QT") -> QT | H58: =IFERROR(__xludf.DUMMYFUNCTION("""COMPUTED_VALUE"""),36.0) -> 36 | J58: Komzak et al., 2022 | K58: QT | L58: 36
A59: =HYPERLINK("https://github.com/d-wkim/phd/blob/main/data/pdf/bottoni_2015.pdf","Bottoni et al., 2015") -> Bottoni et al., 2015 | B59: TA | C59: 36 | D59: =IFERROR(__xludf.DUMMYFUNCTION("join(""; "",A59:C59)"),"Bottoni et al., 2015; TA; 36") -> Bottoni et al., 2015; TA; 36 | E59: Konrads et al., 2016; BPTB; 24 | F59: =IFERROR(__xludf.DUMMYFUNCTION("split(E59,"";"",FALSE)"),"Konrads et al., 2016") -> Konrads et al., 2016 | G59: =IFERROR(__xludf.DUMMYFUNCTION("""COMPUTED_VALUE""")," BPTB") -> BPTB | H59: =IFERROR(__xludf.DUMMYFUNCTION("""COMPUTED_VALUE"""),24.0) -> 24 | J59: Konrads et al., 2016 | K59: BPTB | L59: 24
A60: =HYPERLINK("https://github.com/d-wkim/phd/blob/main/data/pdf/butt_2024.pdf","Butt et al., 2024") -> Butt et al., 2024 | B60: HT | C60: 30 | D60: =IFERROR(__xludf.DUMMYFUNCTION("join(""; "",A60:C60)"),"Butt et al., 2024; HT; 30") -> Butt et al., 2024; HT; 30 | E60: Konrads et al., 2016; HT; 23 | F60: =IFERROR(__xludf.DUMMYFUNCTION("split(E60,"";"",FALSE)"),"Konrads et al., 2016") -> Konrads et al., 2016 | G60: =IFERROR(__xludf.DUMMYFUNCTION("""COMPUTED_VALUE""")," HT") -> HT | H60: =IFERROR(__xludf.DUMMYFUNCTION("""COMPUTED_VALUE"""),23.0) -> 23 | J60: Konrads et al., 2016 | K60: HT | L60: 23
A61: =HYPERLINK("https://github.com/d-wkim/phd/blob/main/data/pdf/butt_2024.pdf","Butt et al., 2024") -> Butt et al., 2024 | B61: HT | C61: 30 | D61: =IFERROR(__xludf.DUMMYFUNCTION("join(""; "",A61:C61)"),"Butt et al., 2024; HT; 30") -> Butt et al., 2024; HT; 30 | E61: Laoruengthana et al., 2009; BPTB; 15 | F61: =IFERROR(__xludf.DUMMYFUNCTION("split(E61,"";"",FALSE)"),"Laoruengthana et al., 2009") -> Laoruengthana et al., 2009 | G61: =IFERROR(__xludf.DUMMYFUNCTION("""COMPUTED_VALUE""")," BPTB") -> BPTB | H61: =IFERROR(__xludf.DUMMYFUNCTION("""COMPUTED_VALUE"""),15.0) -> 15 | J61: Laoruengthana et al., 2009 | K61: BPTB | L61: 15
A62: =HYPERLINK("https://github.com/d-wkim/phd/blob/main/data/pdf/butt_2024.pdf","Butt et al., 2024") -> Butt et al., 2024 | B62: PLT | C62: 30 | D62: =IFERROR(__xludf.DUMMYFUNCTION("join(""; "",A62:C62)"),"Butt et al., 2024; PLT; 30") -> Butt et al., 2024; PLT; 30 | E62: Laoruengthana et al., 2009; HT; 13 | F62: =IFERROR(__xludf.DUMMYFUNCTION("split(E62,"";"",FALSE)"),"Laoruengthana et al., 2009") -> Laoruengthana et al., 2009 | G62: =IFERROR(__xludf.DUMMYFUNCTION("""COMPUTED_VALUE""")," HT") -> HT | H62: =IFERROR(__xludf.DUMMYFUNCTION("""COMPUTED_VALUE"""),13.0) -> 13 | J62: Laoruengthana et al., 2009 | K62: HT | L62: 13
A63: =HYPERLINK("https://github.com/d-wkim/phd/blob/main/data/pdf/butt_2024.pdf","Butt et al., 2024") -> Butt et al., 2024 | B63: PLT | C63: 30 | D63: =IFERROR(__xludf.DUMMYFUNCTION("join(""; "",A63:C63)"),"Butt et al., 2024; PLT; 30") -> Butt et al., 2024; PLT; 30 | E63: Lawhorn et al., 2012; HT; 48 | F63: =IFERROR(__xludf.DUMMYFUNCTION("split(E63,"";"",FALSE)"),"Lawhorn et al., 2012") -> Lawhorn et al., 2012 | G63: =IFERROR(__xludf.DUMMYFUNCTION("""COMPUTED_VALUE""")," HT") -> HT | H63: =IFERROR(__xludf.DUMMYFUNCTION("""COMPUTED_VALUE"""),48.0) -> 48 | J63: Lawhorn et al., 2012 | K63: HT | L63: 48
A64: =HYPERLINK("https://github.com/d-wkim/phd/blob/main/data/pdf/calvert_2025.pdf","Calvert et al., 2025") -> Calvert et al., 2025 | B64: HT | C64: 92 | D64: =IFERROR(__xludf.DUMMYFUNCTION("join(""; "",A64:C64)"),"Calvert et al., 2025; HT; 92") -> Calvert et al., 2025; HT; 92 | E64: Lawhorn et al., 2012; TA; 44 | F64: =IFERROR(__xludf.DUMMYFUNCTION("split(E64,"";"",FALSE)"),"Lawhorn et al., 2012") -> Lawhorn et al., 2012 | G64: =IFERROR(__xludf.DUMMYFUNCTION("""COMPUTED_VALUE""")," TA") -> TA | H64: =IFERROR(__xludf.DUMMYFUNCTION("""COMPUTED_VALUE"""),44.0) -> 44 | J64: Lawhorn et al., 2012 | K64: TA | L64: 44
A65: =HYPERLINK("https://github.com/d-wkim/phd/blob/main/data/pdf/calvert_2025.pdf","Calvert et al., 2025") -> Calvert et al., 2025 | B65: HT | C65: 92 | D65: =IFERROR(__xludf.DUMMYFUNCTION("join(""; "",A65:C65)"),"Calvert et al., 2025; HT; 92") -> Calvert et al., 2025; HT; 92 | E65: Laxdal et al., 2005; BPTB; 40 | F65: =IFERROR(__xludf.DUMMYFUNCTION("split(E65,"";"",FALSE)"),"Laxdal et al., 2005") -> Laxdal et al., 2005 | G65: =IFERROR(__xludf.DUMMYFUNCTION("""COMPUTED_VALUE""")," BPTB") -> BPTB | H65: =IFERROR(__xludf.DUMMYFUNCTION("""COMPUTED_VALUE"""),40.0) -> 40 | J65: Laxdal et al., 2005 | K65: BPTB | L65: 40
A66: =HYPERLINK("https://github.com/d-wkim/phd/blob/main/data/pdf/calvert_2025.pdf","Calvert et al., 2025") -> Calvert et al., 2025 | B66: QT | C66: 89 | D66: =IFERROR(__xludf.DUMMYFUNCTION("join(""; "",A66:C66)"),"Calvert et al., 2025; QT; 89") -> Calvert et al., 2025; QT; 89 | E66: Laxdal et al., 2005; HT; 78 | F66: =IFERROR(__xludf.DUMMYFUNCTION("split(E66,"";"",FALSE)"),"Laxdal et al., 2005") -> Laxdal et al., 2005 | G66: =IFERROR(__xludf.DUMMYFUNCTION("""COMPUTED_VALUE""")," HT") -> HT | H66: =IFERROR(__xludf.DUMMYFUNCTION("""COMPUTED_VALUE"""),78.0) -> 78 | J66: Laxdal et al., 2005 | K66: HT | L66: 78
A67: =HYPERLINK("https://github.com/d-wkim/phd/blob/main/data/pdf/calvert_2025.pdf","Calvert et al., 2025") -> Calvert et al., 2025 | B67: QT | C67: 89 | D67: =IFERROR(__xludf.DUMMYFUNCTION("join(""; "",A67:C67)"),"Calvert et al., 2025; QT; 89") -> Calvert et al., 2025; QT; 89 | E67: Li et al., 2015; HT; 32 | F67: =IFERROR(__xludf.DUMMYFUNCTION("split(E67,"";"",FALSE)"),"Li et al., 2015") -> Li et al., 2015 | G67: =IFERROR(__xludf.DUMMYFUNCTION("""COMPUTED_VALUE""")," HT") -> HT | H67: =IFERROR(__xludf.DUMMYFUNCTION("""COMPUTED_VALUE"""),32.0) -> 32 | J67: Li et al., 2015 | K67: HT | L67: 32
A68: =HYPERLINK("https://github.com/d-wkim/phd/blob/main/data/pdf/ejerhed_2003.pdf","Ejerhed et al., 2003") -> Ejerhed et al., 2003 | B68: BPTB | C68: 32 | D68: =IFERROR(__xludf.DUMMYFUNCTION("join(""; "",A68:C68)"),"Ejerhed et al., 2003; BPTB; 32") -> Ejerhed et al., 2003; BPTB; 32 | E68: Li et al., 2015; TA; 32 | F68: =IFERROR(__xludf.DUMMYFUNCTION("split(E68,"";"",FALSE)"),"Li et al., 2015") -> Li et al., 2015 | G68: =IFERROR(__xludf.DUMMYFUNCTION("""COMPUTED_VALUE""")," TA") -> TA | H68: =IFERROR(__xludf.DUMMYFUNCTION("""COMPUTED_VALUE"""),32.0) -> 32 | J68: Li et al., 2015 | K68: TA | L68: 32
A69: =HYPERLINK("https://github.com/d-wkim/phd/blob/main/data/pdf/ejerhed_2003.pdf","Ejerhed et al., 2003") -> Ejerhed et al., 2003 | B69: BPTB | C69: 32 | D69: =IFERROR(__xludf.DUMMYFUNCTION("join(""; "",A69:C69)"),"Ejerhed et al., 2003; BPTB; 32") -> Ejerhed et al., 2003; BPTB; 32 | E69: Lidén et al., 2007; BPTB; 30 | F69: =IFERROR(__xludf.DUMMYFUNCTION("split(E69,"";"",FALSE)"),"Lidén et al., 2007") -> Lidén et al., 2007 | G69: =IFERROR(__xludf.DUMMYFUNCTION("""COMPUTED_VALUE""")," BPTB") -> BPTB | H69: =IFERROR(__xludf.DUMMYFUNCTION("""COMPUTED_VALUE"""),30.0) -> 30 | J69: Lidén et al., 2007 | K69: BPTB | L69: 30
A70: =HYPERLINK("https://github.com/d-wkim/phd/blob/main/data/pdf/ejerhed_2003.pdf","Ejerhed et al., 2003") -> Ejerhed et al., 2003 | B70: BPTB | C70: 32 | D70: =IFERROR(__xludf.DUMMYFUNCTION("join(""; "",A70:C70)"),"Ejerhed et al., 2003; BPTB; 32") -> Ejerhed et al., 2003; BPTB; 32 | E70: Lidén et al., 2007; HT; 32 | F70: =IFERROR(__xludf.DUMMYFUNCTION("split(E70,"";"",FALSE)"),"Lidén et al., 2007") -> Lidén et al., 2007 | G70: =IFERROR(__xludf.DUMMYFUNCTION("""COMPUTED_VALUE""")," HT") -> HT | H70: =IFERROR(__xludf.DUMMYFUNCTION("""COMPUTED_VALUE"""),32.0) -> 32 | J70: Lidén et al., 2007 | K70: HT | L70: 32
A71: =HYPERLINK("https://github.com/d-wkim/phd/blob/main/data/pdf/ejerhed_2003.pdf","Ejerhed et al., 2003") -> Ejerhed et al., 2003 | B71: BPTB | C71: 32 | D71: =IFERROR(__xludf.DUMMYFUNCTION("join(""; "",A71:C71)"),"Ejerhed et al., 2003; BPTB; 32") -> Ejerhed et al., 2003; BPTB; 32 | E71: Lind et al., 2020; HT; 49 | F71: =IFERROR(__xludf.DUMMYFUNCTION("split(E71,"";"",FALSE)"),"Lind et al., 2020") -> Lind et al., 2020 | G71: =IFERROR(__xludf.DUMMYFUNCTION("""COMPUTED_VALUE""")," HT") -> HT | H71: =IFERROR(__xludf.DUMMYFUNCTION("""COMPUTED_VALUE"""),49.0) -> 49 | J71: Lind et al., 2020 | K71: HT | L71: 49
A72: =HYPERLINK("https://github.com/d-wkim/phd/blob/main/data/pdf/ejerhed_2003.pdf","Ejerhed et al., 2003") -> Ejerhed et al., 2003 | B72: HT | C72: 34 | D72: =IFERROR(__xludf.DUMMYFUNCTION("join(""; "",A72:C72)"),"Ejerhed et al., 2003; HT; 34") -> Ejerhed et al., 2003; HT; 34 | E72: Lind et al., 2020; QT; 47 | F72: =IFERROR(__xludf.DUMMYFUNCTION("split(E72,"";"",FALSE)"),"Lind et al., 2020") -> Lind et al., 2020 | G72: =IFERROR(__xludf.DUMMYFUNCTION("""COMPUTED_VALUE""")," QT") -> QT | H72: =IFERROR(__xludf.DUMMYFUNCTION("""COMPUTED_VALUE"""),47.0) -> 47 | J72: Lind et al., 2020 | K72: QT | L72: 47
A73: =HYPERLINK("https://github.com/d-wkim/phd/blob/main/data/pdf/ejerhed_2003.pdf","Ejerhed et al., 2003") -> Ejerhed et al., 2003 | B73: HT | C73: 34 | D73: =IFERROR(__xludf.DUMMYFUNCTION("join(""; "",A73:C73)"),"Ejerhed et al., 2003; HT; 34") -> Ejerhed et al., 2003; HT; 34 | E73: Lucidi et al., 2025; BPTB; 19 | F73: =IFERROR(__xludf.DUMMYFUNCTION("split(E73,"";"",FALSE)"),"Lucidi et al., 2025") -> Lucidi et al., 2025 | G73: =IFERROR(__xludf.DUMMYFUNCTION("""COMPUTED_VALUE""")," BPTB") -> BPTB | H73: =IFERROR(__xludf.DUMMYFUNCTION("""COMPUTED_VALUE"""),19.0) -> 19 | J73: Lucidi et al., 2025 | K73: BPTB | L73: 19
A74: =HYPERLINK("https://github.com/d-wkim/phd/blob/main/data/pdf/ejerhed_2003.pdf","Ejerhed et al., 2003") -> Ejerhed et al., 2003 | B74: HT | C74: 34 | D74: =IFERROR(__xludf.DUMMYFUNCTION("join(""; "",A74:C74)"),"Ejerhed et al., 2003; HT; 34") -> Ejerhed et al., 2003; HT; 34 | E74: Lucidi et al., 2025; HT; 20 | F74: =IFERROR(__xludf.DUMMYFUNCTION("split(E74,"";"",FALSE)"),"Lucidi et al., 2025") -> Lucidi et al., 2025 | G74: =IFERROR(__xludf.DUMMYFUNCTION("""COMPUTED_VALUE""")," HT") -> HT | H74: =IFERROR(__xludf.DUMMYFUNCTION("""COMPUTED_VALUE"""),20.0) -> 20 | J74: Lucidi et al., 2025 | K74: HT | L74: 20
A75: =HYPERLINK("https://github.com/d-wkim/phd/blob/main/data/pdf/ejerhed_2003.pdf","Ejerhed et al., 2003") -> Ejerhed et al., 2003 | B75: HT | C75: 34 | D75: =IFERROR(__xludf.DUMMYFUNCTION("join(""; "",A75:C75)"),"Ejerhed et al., 2003; HT; 34") -> Ejerhed et al., 2003; HT; 34 | E75: Lui et al., 2012; BPTB; 14 | F75: =IFERROR(__xludf.DUMMYFUNCTION("split(E75,"";"",FALSE)"),"Lui et al., 2012") -> Lui et al., 2012 | G75: =IFERROR(__xludf.DUMMYFUNCTION("""COMPUTED_VALUE""")," BPTB") -> BPTB | H75: =IFERROR(__xludf.DUMMYFUNCTION("""COMPUTED_VALUE"""),14.0) -> 14 | J75: Lui et al., 2012 | K75: BPTB | L75: 14
A76: =HYPERLINK("https://github.com/d-wkim/phd/blob/main/data/pdf/eriksson_2006.pdf","Eriksson et al., 2001") -> Eriksson et al., 2001 | B76: BPTB | C76: 42 | D76: =IFERROR(__xludf.DUMMYFUNCTION("join(""; "",A76:C76)"),"Eriksson et al., 2001; BPTB; 42") -> Eriksson et al., 2001; BPTB; 42 | E76: Lui et al., 2012; HT; 17 | F76: =IFERROR(__xludf.DUMMYFUNCTION("split(E76,"";"",FALSE)"),"Lui et al., 2012") -> Lui et al., 2012 | G76: =IFERROR(__xludf.DUMMYFUNCTION("""COMPUTED_VALUE""")," HT") -> HT | H76: =IFERROR(__xludf.DUMMYFUNCTION("""COMPUTED_VALUE"""),17.0) -> 17 | J76: Lui et al., 2012 | K76: HT | L76: 17
A77: =HYPERLINK("https://github.com/d-wkim/phd/blob/main/data/pdf/eriksson_2006.pdf","Eriksson et al., 2001") -> Eriksson et al., 2001 | B77: BPTB | C77: 42 | D77: =IFERROR(__xludf.DUMMYFUNCTION("join(""; "",A77:C77)"),"Eriksson et al., 2001; BPTB; 42") -> Eriksson et al., 2001; BPTB; 42 | E77: Lund et al., 2014; BPTB; 18 | F77: =IFERROR(__xludf.DUMMYFUNCTION("split(E77,"";"",FALSE)"),"Lund et al., 2014") -> Lund et al., 2014 | G77: =IFERROR(__xludf.DUMMYFUNCTION("""COMPUTED_VALUE""")," BPTB") -> BPTB | H77: =IFERROR(__xludf.DUMMYFUNCTION("""COMPUTED_VALUE"""),18.0) -> 18 | J77: Lund et al., 2014 | K77: BPTB | L77: 18
A78: =HYPERLINK("https://github.com/d-wkim/phd/blob/main/data/pdf/eriksson_2006.pdf","Eriksson et al., 2001") -> Eriksson et al., 2001 | B78: HT | C78: 47 | D78: =IFERROR(__xludf.DUMMYFUNCTION("join(""; "",A78:C78)"),"Eriksson et al., 2001; HT; 47") -> Eriksson et al., 2001; HT; 47 | E78: Lund et al., 2014; QT; 21 | F78: =IFERROR(__xludf.DUMMYFUNCTION("split(E78,"";"",FALSE)"),"Lund et al., 2014") -> Lund et al., 2014 | G78: =IFERROR(__xludf.DUMMYFUNCTION("""COMPUTED_VALUE""")," QT") -> QT | H78: =IFERROR(__xludf.DUMMYFUNCTION("""COMPUTED_VALUE"""),21.0) -> 21 | J78: Lund et al., 2014 | K78: QT | L78: 21
A79: =HYPERLINK("https://github.com/d-wkim/phd/blob/main/data/pdf/eriksson_2006.pdf","Eriksson et al., 2001") -> Eriksson et al., 2001 | B79: HT | C79: 47 | D79: =IFERROR(__xludf.DUMMYFUNCTION("join(""; "",A79:C79)"),"Eriksson et al., 2001; HT; 47") -> Eriksson et al., 2001; HT; 47 | E79: Malik et al., 2026; HT; 25 | F79: =IFERROR(__xludf.DUMMYFUNCTION("split(E79,"";"",FALSE)"),"Malik et al., 2026") -> Malik et al., 2026 | G79: =IFERROR(__xludf.DUMMYFUNCTION("""COMPUTED_VALUE""")," HT") -> HT | H79: =IFERROR(__xludf.DUMMYFUNCTION("""COMPUTED_VALUE"""),25.0) -> 25 | J79: Malik et al., 2026 | K79: HT | L79: 25
A80: =HYPERLINK("https://github.com/d-wkim/phd/blob/main/data/pdf/feller_webster_2003.pdf","Feller & Webster, 2003") -> Feller & Webster, 2003 | B80: BPTB | C80: 27 | D80: =IFERROR(__xludf.DUMMYFUNCTION("join(""; "",A80:C80)"),"Feller & Webster, 2003; BPTB; 27") -> Feller & Webster, 2003; BPTB; 27 | E80: Malik et al., 2026; PLT; 25 | F80: =IFERROR(__xludf.DUMMYFUNCTION("split(E80,"";"",FALSE)"),"Malik et al., 2026") -> Malik et al., 2026 | G80: =IFERROR(__xludf.DUMMYFUNCTION("""COMPUTED_VALUE""")," PLT") -> PLT | H80: =IFERROR(__xludf.DUMMYFUNCTION("""COMPUTED_VALUE"""),25.0) -> 25 | J80: Malik et al., 2026 | K80: PLT | L80: 25
A81: =HYPERLINK("https://github.com/d-wkim/phd/blob/main/data/pdf/feller_webster_2003.pdf","Feller & Webster, 2003") -> Feller & Webster, 2003 | B81: BPTB | C81: 27 | D81: =IFERROR(__xludf.DUMMYFUNCTION("join(""; "",A81:C81)"),"Feller & Webster, 2003; BPTB; 27") -> Feller & Webster, 2003; BPTB; 27 | E81: Matsumoto et al., 2006; BPTB; 37 | F81: =IFERROR(__xludf.DUMMYFUNCTION("split(E81,"";"",FALSE)"),"Matsumoto et al., 2006") -> Matsumoto et al., 2006 | G81: =IFERROR(__xludf.DUMMYFUNCTION("""COMPUTED_VALUE""")," BPTB") -> BPTB | H81: =IFERROR(__xludf.DUMMYFUNCTION("""COMPUTED_VALUE"""),37.0) -> 37 | J81: Matsumoto et al., 2006 | K81: BPTB | L81: 37
A82: =HYPERLINK("https://github.com/d-wkim/phd/blob/main/data/pdf/feller_webster_2003.pdf","Feller & Webster, 2003") -> Feller & Webster, 2003 | B82: BPTB | C82: 27 | D82: =IFERROR(__xludf.DUMMYFUNCTION("join(""; "",A82:C82)"),"Feller & Webster, 2003; BPTB; 27") -> Feller & Webster, 2003; BPTB; 27 | E82: Matsumoto et al., 2006; HT; 35 | F82: =IFERROR(__xludf.DUMMYFUNCTION("split(E82,"";"",FALSE)"),"Matsumoto et al., 2006") -> Matsumoto et al., 2006 | G82: =IFERROR(__xludf.DUMMYFUNCTION("""COMPUTED_VALUE""")," HT") -> HT | H82: =IFERROR(__xludf.DUMMYFUNCTION("""COMPUTED_VALUE"""),35.0) -> 35 | J82: Matsumoto et al., 2006 | K82: HT | L82: 35
A83: =HYPERLINK("https://github.com/d-wkim/phd/blob/main/data/pdf/feller_webster_2003.pdf","Feller & Webster, 2003") -> Feller & Webster, 2003 | B83: HT | C83: 21 | D83: =IFERROR(__xludf.DUMMYFUNCTION("join(""; "",A83:C83)"),"Feller & Webster, 2003; HT; 21") -> Feller & Webster, 2003; HT; 21 | E83: Mohtadi et al., 2016; BPTB; 110 | F83: =IFERROR(__xludf.DUMMYFUNCTION("split(E83,"";"",FALSE)"),"Mohtadi et al., 2016") -> Mohtadi et al., 2016 | G83: =IFERROR(__xludf.DUMMYFUNCTION("""COMPUTED_VALUE""")," BPTB") -> BPTB | H83: =IFERROR(__xludf.DUMMYFUNCTION("""COMPUTED_VALUE"""),110.0) -> 110 | J83: Mohtadi et al., 2016 | K83: BPTB | L83: 110
A84: =HYPERLINK("https://github.com/d-wkim/phd/blob/main/data/pdf/feller_webster_2003.pdf","Feller & Webster, 2003") -> Feller & Webster, 2003 | B84: HT | C84: 21 | D84: =IFERROR(__xludf.DUMMYFUNCTION("join(""; "",A84:C84)"),"Feller & Webster, 2003; HT; 21") -> Feller & Webster, 2003; HT; 21 | E84: Mohtadi et al., 2016; HT; 110 | F84: =IFERROR(__xludf.DUMMYFUNCTION("split(E84,"";"",FALSE)"),"Mohtadi et al., 2016") -> Mohtadi et al., 2016 | G84: =IFERROR(__xludf.DUMMYFUNCTION("""COMPUTED_VALUE""")," HT") -> HT | H84: =IFERROR(__xludf.DUMMYFUNCTION("""COMPUTED_VALUE"""),110.0) -> 110 | J84: Mohtadi et al., 2016 | K84: HT | L84: 110
A85: =HYPERLINK("https://github.com/d-wkim/phd/blob/main/data/pdf/feller_webster_2003.pdf","Feller & Webster, 2003") -> Feller & Webster, 2003 | B85: HT | C85: 21 | D85: =IFERROR(__xludf.DUMMYFUNCTION("join(""; "",A85:C85)"),"Feller & Webster, 2003; HT; 21") -> Feller & Webster, 2003; HT; 21 | E85: Moraiti et al., 2010; BPTB; 6 | F85: =IFERROR(__xludf.DUMMYFUNCTION("split(E85,"";"",FALSE)"),"Moraiti et al., 2010") -> Moraiti et al., 2010 | G85: =IFERROR(__xludf.DUMMYFUNCTION("""COMPUTED_VALUE""")," BPTB") -> BPTB | H85: =IFERROR(__xludf.DUMMYFUNCTION("""COMPUTED_VALUE"""),6.0) -> 6 | J85: Moraiti et al., 2010 | K85: BPTB | L85: 6
A86: =HYPERLINK("https://github.com/d-wkim/phd/blob/main/data/pdf/gifstad_2013.pdf","Gifstad et al., 2013") -> Gifstad et al., 2013 | B86: BPTB | C86: 41 | D86: =IFERROR(__xludf.DUMMYFUNCTION("join(""; "",A86:C86)"),"Gifstad et al., 2013; BPTB; 41") -> Gifstad et al., 2013; BPTB; 41 | E86: Moraiti et al., 2010; HT; 6 | F86: =IFERROR(__xludf.DUMMYFUNCTION("split(E86,"";"",FALSE)"),"Moraiti et al., 2010") -> Moraiti et al., 2010 | G86: =IFERROR(__xludf.DUMMYFUNCTION("""COMPUTED_VALUE""")," HT") -> HT | H86: =IFERROR(__xludf.DUMMYFUNCTION("""COMPUTED_VALUE"""),6.0) -> 6 | J86: Moraiti et al., 2010 | K86: HT | L86: 6
A87: =HYPERLINK("https://github.com/d-wkim/phd/blob/main/data/pdf/gifstad_2013.pdf","Gifstad et al., 2013") -> Gifstad et al., 2013 | B87: BPTB | C87: 41 | D87: =IFERROR(__xludf.DUMMYFUNCTION("join(""; "",A87:C87)"),"Gifstad et al., 2013; BPTB; 41") -> Gifstad et al., 2013; BPTB; 41 | E87: Noh et al., 2011; HT; 33 | F87: =IFERROR(__xludf.DUMMYFUNCTION("split(E87,"";"",FALSE)"),"Noh et al., 2011") -> Noh et al., 2011 | G87: =IFERROR(__xludf.DUMMYFUNCTION("""COMPUTED_VALUE""")," HT") -> HT | H87: =IFERROR(__xludf.DUMMYFUNCTION("""COMPUTED_VALUE"""),33.0) -> 33 | J87: Noh et al., 2011 | K87: HT | L87: 33
A88: =HYPERLINK("https://github.com/d-wkim/phd/blob/main/data/pdf/gifstad_2013.pdf","Gifstad et al., 2013") -> Gifstad et al., 2013 | B88: HT | C88: 36 | D88: =IFERROR(__xludf.DUMMYFUNCTION("join(""; "",A88:C88)"),"Gifstad et al., 2013; HT; 36") -> Gifstad et al., 2013; HT; 36 | E88: Noh et al., 2011; AT; 32 | F88: =IFERROR(__xludf.DUMMYFUNCTION("split(E88,"";"",FALSE)"),"Noh et al., 2011") -> Noh et al., 2011 | G88: =IFERROR(__xludf.DUMMYFUNCTION("""COMPUTED_VALUE""")," AT") -> AT | H88: =IFERROR(__xludf.DUMMYFUNCTION("""COMPUTED_VALUE"""),32.0) -> 32 | J88: Noh et al., 2011 | K88: AT | L88: 32
A89: =HYPERLINK("https://github.com/d-wkim/phd/blob/main/data/pdf/gifstad_2013.pdf","Gifstad et al., 2013") -> Gifstad et al., 2013 | B89: HT | C89: 36 | D89: =IFERROR(__xludf.DUMMYFUNCTION("join(""; "",A89:C89)"),"Gifstad et al., 2013; HT; 36") -> Gifstad et al., 2013; HT; 36 | E89: Papalia et al., 2015; BPTB; 20 | F89: =IFERROR(__xludf.DUMMYFUNCTION("split(E89,"";"",FALSE)"),"Papalia et al., 2015") -> Papalia et al., 2015 | G89: =IFERROR(__xludf.DUMMYFUNCTION("""COMPUTED_VALUE""")," BPTB") -> BPTB | H89: =IFERROR(__xludf.DUMMYFUNCTION("""COMPUTED_VALUE"""),20.0) -> 20 | J89: Papalia et al., 2015 | K89: BPTB | L89: 20
A90: =HYPERLINK("https://github.com/d-wkim/phd/blob/main/data/pdf/guglielmetti_2021.pdf","Guglielmetti et al., 2021") -> Guglielmetti et al., 2021 | B90: BPTB | C90: 31 | D90: =IFERROR(__xludf.DUMMYFUNCTION("join(""; "",A90:C90)"),"Guglielmetti et al., 2021; BPTB; 31") -> Guglielmetti et al., 2021; BPTB; 31 | E90: Papalia et al., 2015; HT; 20 | F90: =IFERROR(__xludf.DUMMYFUNCTION("split(E90,"";"",FALSE)"),"Papalia et al., 2015") -> Papalia et al., 2015 | G90: =IFERROR(__xludf.DUMMYFUNCTION("""COMPUTED_VALUE""")," HT") -> HT | H90: =IFERROR(__xludf.DUMMYFUNCTION("""COMPUTED_VALUE"""),20.0) -> 20 | J90: Papalia et al., 2015 | K90: HT | L90: 20
A91: =HYPERLINK("https://github.com/d-wkim/phd/blob/main/data/pdf/guglielmetti_2021.pdf","Guglielmetti et al., 2021") -> Guglielmetti et al., 2021 | B91: BPTB | C91: 31 | D91: =IFERROR(__xludf.DUMMYFUNCTION("join(""; "",A91:C91)"),"Guglielmetti et al., 2021; BPTB; 31") -> Guglielmetti et al., 2021; BPTB; 31 | E91: Pinczewski et al., 2007; BPTB; 53 | F91: =IFERROR(__xludf.DUMMYFUNCTION("split(E91,"";"",FALSE)"),"Pinczewski et al., 2007") -> Pinczewski et al., 2007 | G91: =IFERROR(__xludf.DUMMYFUNCTION("""COMPUTED_VALUE""")," BPTB") -> BPTB | H91: =IFERROR(__xludf.DUMMYFUNCTION("""COMPUTED_VALUE"""),53.0) -> 53 | J91: Pinczewski et al., 2007 | K91: BPTB | L91: 53
A92: =HYPERLINK("https://github.com/d-wkim/phd/blob/main/data/pdf/guglielmetti_2021.pdf","Guglielmetti et al., 2021") -> Guglielmetti et al., 2021 | B92: BPTB | C92: 31 | D92: =IFERROR(__xludf.DUMMYFUNCTION("join(""; "",A92:C92)"),"Guglielmetti et al., 2021; BPTB; 31") -> Guglielmetti et al., 2021; BPTB; 31 | E92: Pinczewski et al., 2007; BPTB; 54 | F92: =IFERROR(__xludf.DUMMYFUNCTION("split(E92,"";"",FALSE)"),"Pinczewski et al., 2007") -> Pinczewski et al., 2007 | G92: =IFERROR(__xludf.DUMMYFUNCTION("""COMPUTED_VALUE""")," BPTB") -> BPTB | H92: =IFERROR(__xludf.DUMMYFUNCTION("""COMPUTED_VALUE"""),54.0) -> 54 | J92: Pinczewski et al., 2007 | K92: BPTB | L92: 54
A93: =HYPERLINK("https://github.com/d-wkim/phd/blob/main/data/pdf/guglielmetti_2021.pdf","Guglielmetti et al., 2021") -> Guglielmetti et al., 2021 | B93: BPTB | C93: 31 | D93: =IFERROR(__xludf.DUMMYFUNCTION("join(""; "",A93:C93)"),"Guglielmetti et al., 2021; BPTB; 31") -> Guglielmetti et al., 2021; BPTB; 31 | E93: Pinczewski et al., 2007; BPTB; 90 | F93: =IFERROR(__xludf.DUMMYFUNCTION("split(E93,"";"",FALSE)"),"Pinczewski et al., 2007") -> Pinczewski et al., 2007 | G93: =IFERROR(__xludf.DUMMYFUNCTION("""COMPUTED_VALUE""")," BPTB") -> BPTB | H93: =IFERROR(__xludf.DUMMYFUNCTION("""COMPUTED_VALUE"""),90.0) -> 90 | J93: Pinczewski et al., 2007 | K93: BPTB | L93: 90
A94: =HYPERLINK("https://github.com/d-wkim/phd/blob/main/data/pdf/guglielmetti_2021.pdf","Guglielmetti et al., 2021") -> Guglielmetti et al., 2021 | B94: HT | C94: 31 | D94: =IFERROR(__xludf.DUMMYFUNCTION("join(""; "",A94:C94)"),"Guglielmetti et al., 2021; HT; 31") -> Guglielmetti et al., 2021; HT; 31 | E94: Pinczewski et al., 2007; HT; 58 | F94: =IFERROR(__xludf.DUMMYFUNCTION("split(E94,"";"",FALSE)"),"Pinczewski et al., 2007") -> Pinczewski et al., 2007 | G94: =IFERROR(__xludf.DUMMYFUNCTION("""COMPUTED_VALUE""")," HT") -> HT | H94: =IFERROR(__xludf.DUMMYFUNCTION("""COMPUTED_VALUE"""),58.0) -> 58 | J94: Pinczewski et al., 2007 | K94: HT | L94: 58
A95: =HYPERLINK("https://github.com/d-wkim/phd/blob/main/data/pdf/guglielmetti_2021.pdf","Guglielmetti et al., 2021") -> Guglielmetti et al., 2021 | B95: HT | C95: 31 | D95: =IFERROR(__xludf.DUMMYFUNCTION("join(""; "",A95:C95)"),"Guglielmetti et al., 2021; HT; 31") -> Guglielmetti et al., 2021; HT; 31 | E95: Pinczewski et al., 2007; HT; 90 | F95: =IFERROR(__xludf.DUMMYFUNCTION("split(E95,"";"",FALSE)"),"Pinczewski et al., 2007") -> Pinczewski et al., 2007 | G95: =IFERROR(__xludf.DUMMYFUNCTION("""COMPUTED_VALUE""")," HT") -> HT | H95: =IFERROR(__xludf.DUMMYFUNCTION("""COMPUTED_VALUE"""),90.0) -> 90 | J95: Pinczewski et al., 2007 | K95: HT | L95: 90
A96: =HYPERLINK("https://github.com/d-wkim/phd/blob/main/data/pdf/guglielmetti_2021.pdf","Guglielmetti et al., 2021") -> Guglielmetti et al., 2021 | B96: HT | C96: 31 | D96: =IFERROR(__xludf.DUMMYFUNCTION("join(""; "",A96:C96)"),"Guglielmetti et al., 2021; HT; 31") -> Guglielmetti et al., 2021; HT; 31 | E96: Popovic et al., 2024; BPTB; 38 | F96: =IFERROR(__xludf.DUMMYFUNCTION("split(E96,"";"",FALSE)"),"Popovic et al., 2024") -> Popovic et al., 2024 | G96: =IFERROR(__xludf.DUMMYFUNCTION("""COMPUTED_VALUE""")," BPTB") -> BPTB | H96: =IFERROR(__xludf.DUMMYFUNCTION("""COMPUTED_VALUE"""),38.0) -> 38 | J96: Popovic et al., 2024 | K96: BPTB | L96: 38
A97: =HYPERLINK("https://github.com/d-wkim/phd/blob/main/data/pdf/guglielmetti_2021.pdf","Guglielmetti et al., 2021") -> Guglielmetti et al., 2021 | B97: HT | C97: 31 | D97: =IFERROR(__xludf.DUMMYFUNCTION("join(""; "",A97:C97)"),"Guglielmetti et al., 2021; HT; 31") -> Guglielmetti et al., 2021; HT; 31 | E97: Popovic et al., 2024; HT; 33 | F97: =IFERROR(__xludf.DUMMYFUNCTION("split(E97,"";"",FALSE)"),"Popovic et al., 2024") -> Popovic et al., 2024 | G97: =IFERROR(__xludf.DUMMYFUNCTION("""COMPUTED_VALUE""")," HT") -> HT | H97: =IFERROR(__xludf.DUMMYFUNCTION("""COMPUTED_VALUE"""),33.0) -> 33 | J97: Popovic et al., 2024 | K97: HT | L97: 33
A98: =HYPERLINK("https://github.com/d-wkim/phd/blob/main/data/pdf/harilainen_2006.pdf","Harilainen et al., 2006") -> Harilainen et al., 2006 | B98: BPTB | C98: 37 | D98: =IFERROR(__xludf.DUMMYFUNCTION("join(""; "",A98:C98)"),"Harilainen et al., 2006; BPTB; 37") -> Harilainen et al., 2006; BPTB; 37 | E98: Sajovic et al., 2018; BPTB; 24 | F98: =IFERROR(__xludf.DUMMYFUNCTION("split(E98,"";"",FALSE)"),"Sajovic et al., 2018") -> Sajovic et al., 2018 | G98: =IFERROR(__xludf.DUMMYFUNCTION("""COMPUTED_VALUE""")," BPTB") -> BPTB | H98: =IFERROR(__xludf.DUMMYFUNCTION("""COMPUTED_VALUE"""),24.0) -> 24 | J98: Sajovic et al., 2018 | K98: BPTB | L98: 24
A99: =HYPERLINK("https://github.com/d-wkim/phd/blob/main/data/pdf/harilainen_2006.pdf","Harilainen et al., 2006") -> Harilainen et al., 2006 | B99: BPTB | C99: 37 | D99: =IFERROR(__xludf.DUMMYFUNCTION("join(""; "",A99:C99)"),"Harilainen et al., 2006; BPTB; 37") -> Harilainen et al., 2006; BPTB; 37 | E99: Sajovic et al., 2018; HT; 24 | F99: =IFERROR(__xludf.DUMMYFUNCTION("split(E99,"";"",FALSE)"),"Sajovic et al., 2018") -> Sajovic et al., 2018 | G99: =IFERROR(__xludf.DUMMYFUNCTION("""COMPUTED_VALUE""")," HT") -> HT | H99: =IFERROR(__xludf.DUMMYFUNCTION("""COMPUTED_VALUE"""),24.0) -> 24 | J99: Sajovic et al., 2018 | K99: HT | L99: 24
A100: =HYPERLINK("https://github.com/d-wkim/phd/blob/main/data/pdf/harilainen_2006.pdf","Harilainen et al., 2006") -> Harilainen et al., 2006 | B100: BPTB | C100: 37 | D100: =IFERROR(__xludf.DUMMYFUNCTION("join(""; "",A100:C100)"),"Harilainen et al., 2006; BPTB; 37") -> Harilainen et al., 2006; BPTB; 37 | E100: Sinding et al., 2020; HT; 43 | F100: =IFERROR(__xludf.DUMMYFUNCTION("split(E100,"";"",FALSE)"),"Sinding et al., 2020") -> Sinding et al., 2020 | G100: =IFERROR(__xludf.DUMMYFUNCTION("""COMPUTED_VALUE""")," HT") -> HT | H100: =IFERROR(__xludf.DUMMYFUNCTION("""COMPUTED_VALUE"""),43.0) -> 43 | J100: Sinding et al., 2020 | K100: HT | L100: 43
...

Sheet covariates
A1: id | B1: study | C1: subgroup | D1: total | F1: age | G1: age_mean | H1: age_sd | I1: a | J1: q1 | K1: m | L1: q3 | M1: b | N1: notes | O1: male | P1: male_% | Q1: female | R1: female_% | S1: follow-up_mo | T1: follow-up_yr | U1: follow-up_mean | V1: follow-up_sd | W1: follow-up_min | X1: follow-up_q1 | Y1: follow-up_median | Z1: follow-up_q3 | AA1: follow-up_max
A2: =column(A2) -> 1 | B2: 1 | C2: 2 | D2: 3 | E2: 4 | F2: 5 | G2: 6 | H2: 7 | I2: 8 | J2: 9 | K2: 10 | L2: 11 | M2: 12 | N2: 13 | O2: 14 | P2: 15 | Q2: 16 | R2: 17 | S2: 18 | T2: 19 | U2: 20 | V2: 21 | W2: 22
A3: 1 | B3: Ageberg et al., 2009 | C3: BPTB | D3: 20 | E3: at surgery | G3: 32 | H3: 5 | O3: 15 | P3: 0.75 | Q3: 5 | R3: 0.25 | S3: 36 | T3: 3 | W3: 36
A4: 1 | B4: Ageberg et al., 2009 | C4: HT | D4: 16 | E4: at surgery | G4: 28 | H4: 4.4 | O4: 12 | P4: 0.75 | Q4: 4 | R4: 0.25 | S4: 36 | T4: 3 | W4: 36
A5: 2 | B5: Aglietti et al., 2004 | C5: BPTB | D5: 60 | E5: at surgery | G5: 25 | H5: 4.973 | I5: 16 | M5: 39 | O5: 46 | P5: 0.77 | Q5: 14 | R5: 0.23333333 | S5: 24 | T5: 2 | W5: 24
A6: 2 | B6: Aglietti et al., 2004 | C6: HT | D6: 60 | E6: at surgery | G6: 25 | H6: 5.189 | I6: 15 | M6: 39 | O6: 46 | P6: 0.77 | Q6: 14 | R6: 0.23333333 | S6: 24 | T6: 2 | W6: 24
A7: 3 | B7: Ahldén et al., 2009 | C7: BPTB | D7: 22 | E7: at surgery | G7: 27.412608 | H7: 8.902 | I7: 14 | K7: 26 | M7: 48 | O7: 14 | P7: 0.64 | Q7: 8 | R7: 0.36363636 | S7: 90.271348 | T7: 7.5 | U7: =MEDIAN_MEAN($D7,W7,Y7,AA7) -> 90.271348 | V7: =RANGE_SD(Q7,W7,AA7) -> 11.505 | W7: 77 | Y7: 89 | AA7: 110
A8: 3 | B8: Ahldén et al., 2009 | C8: HT | D8: 25 | E8: at surgery | G8: 28.604752 | H8: 6.364 | I8: 15 | K8: 29 | M8: 40 | O8: 18 | P8: 0.72 | Q8: 7 | R8: 0.28 | S8: 86.790496 | T8: 7.2 | U8: =MEDIAN_MEAN($D8,W8,Y8,AA8) -> 86.790496 | V8: =RANGE_SD(Q8,W8,AA8) -> 14.658 | W8: 69 | Y8: 86 | AA8: 109
A9: 5 | B9: Anderson et al., 2001 | C9: BPTB | D9: 35 | E9: at surgery | G9: 23.6 | H9: 7.132 | I9: 14 | M9: 44 | O9: 23 | P9: 0.66 | Q9: 12 | R9: 0.34285714 | S9: 34.6 | T9: 2.9 | U9: 34.6 | V9: 11.4
A10: 5 | B10: Anderson et al., 2001 | C10: 2-STG + LET | D10: 33 | E10: at surgery | G10: 22 | H10: 5.771 | I10: 14 | M10: 40 | O10: 22 | P10: 0.67 | Q10: 11 | R10: 0.33333333 | S10: 35.7 | T10: 3 | U10: 35.7 | V10: 12.1
A11: 5 | B11: Anderson et al., 2001 | C11: 2-STG | D11: 35 | E11: at surgery | G11: 20.1 | H11: 5.771 | I11: 14 | M11: 38 | O11: 23 | P11: 0.66 | Q11: 12 | R11: 0.34285714 | S11: 35.9 | T11: 3 | U11: 35.9 | V11: 11.7
A12: 5 | B12: Anderson et al., 2001 | C12: HT | D12: 68 | E12: at surgery | G12: 21.022059 | H12: 5.8071109 | O12: 45 | P12: 0.66 | Q12: 23 | R12: 0.33823529 | S12: 35.802941 | T12: 3 | U12: =SUMPRODUCT($D10:$D11,U10:U11)/sum($D10,$D11) -> 35.802941 | V12: =COMBINE_SD($D10,$D11,V10,V11,U10,U11) -> 11.806942
A13: 6 | B13: Anz et al., 2023 | C13: BPTB | D13: 10 | E13: at surgery | G13: 29.4 | H13: 7.343 | O13: 4 | P13: 0.4 | Q13: 6 | R13: 0.6 | S13: 12 | T13: 1 | W13: 12
A14: 6 | B14: Anz et al., 2023 | C14: HT | D14: 10 | E14: at surgery | G14: 27.55 | H14: 8.643 | O14: 3 | P14: 0.3 | Q14: 7 | R14: 0.7 | S14: 12 | T14: 1 | W14: 12
A15: 7 | B15: Aune et al., 2001 | C15: BPTB | D15: 35 | E15: at surgery | G15: 25 | H15: 7 | O15: 19 | P15: 0.54 | Q15: 16 | R15: 0.45714286 | S15: 24 | T15: 2 | W15: 24
A16: 7 | B16: Aune et al., 2001 | C16: HT | D16: 37 | E16: at surgery | G16: 27 | H16: 9 | O16: 21 | P16: 0.57 | Q16: 16 | R16: 0.43243243 | S16: 24 | T16: 2 | W16: 24
A17: 9 | B17: Barenius et al., 2010 | C17: BPTB | D17: 78 | E17: at follow-up | G17: 33 | H17: 6.3 | N17: Mean (SD) age at last follow-up. | O17: 38 | P17: 0.49 | Q17: 40 | R17: 0.51282051 | S17: 96 | T17: 8 | W17: 96
A18: 9 | B18: Barenius et al., 2010 | C18: HT | D18: 75 | E18: at follow-up | G18: 35 | H18: 7.5 | N18: Mean (SD) age at last follow-up. | O18: 51 | P18: 0.68 | Q18: 24 | R18: 0.32 | S18: 96 | T18: 8 | W18: 96
A19: 10 | B19: Barié et al., 2020 | C19: BPTB | D19: 30 | E19: at surgery | G19: 30.6 | H19: 7.5 | O19: 17 | P19: 0.57 | Q19: 13 | R19: 0.43333333 | S19: 122.4 | T19: 10.2 | U19: 122.4 | V19: 2.88
A20: 10 | B20: Barié et al., 2020 | C20: QT | D20: 30 | E20: at surgery | G20: 30.5 | H20: 7.8 | O20: 17 | P20: 0.57 | Q20: 13 | R20: 0.43333333 | S20: 123.6 | T20: 10.3 | U20: 123.6 | V20: 3
A21: 11 | B21: Beynnon et al., 2002 | C21: BPTB | D21: 28 | E21: at surgery | G21: 28.5 | H21: 6.959 | I21: 18 | M21: 46 | O21: 18 | P21: 0.64 | Q21: 10 | R21: 0.35714286 | S21: 36 | T21: 3 | W21: 36
A22: 11 | B22: Beynnon et al., 2002 | C22: HT | D22: 28 | E22: at surgery | G22: 29.9 | H22: 5.716 | I22: 19 | M22: 42 | O22: 13 | P22: 0.46 | Q22: 15 | R22: 0.53571429 | S22: 36 | T22: 3 | W22: 36
A23: 12 | B23: Bi et al., 2018 | C23: HT | D23: 62 | E23: at surgery | G23: 27.9 | H23: 6.7 | O23: 31 | P23: 0.5 | Q23: 31 | R23: 0.5 | S23: 30.3 | T23: 2.5 | U23: 30.3 | V23: 3.5
A24: 12 | B24: Bi et al., 2018 | C24: PLT | D24: 62 | E24: at surgery | G24: 29.1 | H24: 6.5 | O24: 34 | P24: 0.55 | Q24: 28 | R24: 0.4516129 | S24: 29.7 | T24: 2.5 | U24: 29.7 | V24: 3.7
A25: 13 | B25: Björnsson et al., 2016 | C25: BPTB | D25: 61 | E25: at surgery | G25: 28.2 | H25: 9.1 | I25: 14 | K25: 26 | M25: 52 | N25: Age at follow-up is 44.7 (9.1). | O25: 42 | P25: 0.69 | Q25: 19 | R25: 0.31147541 | S25: 202.6 | T25: 16.9 | U25: 202.6 | V25: 10.4 | W25: 164 | Y25: 203 | AA25: 224
A26: 13 | B26: Björnsson et al., 2016 | C26: HT | D26: 86 | E26: at surgery | G26: 26.8 | H26: 7.6 | I26: 15 | K26: 26 | M26: 59 | N26: Age at follow-up is 42.3 (7.8). | O26: 53 | P26: 0.62 | Q26: 33 | R26: 0.38372093 | S26: 191.9 | T26: 16 | U26: 191.9 | V26: 15.1 | W26: 159 | Y26: 197 | AA26: 225
A27: 14 | B27: Bottoni et al., 2015 | C27: HT | D27: 48 | E27: at surgery | G27: 28.9 | H27: 5.8 | O27: 41 | P27: 0.85 | Q27: 7 | R27: 0.14583333 | S27: 120 | T27: 10 | W27: 120
A28: 14 | B28: Bottoni et al., 2015 | C28: TA | D28: 49 | E28: at surgery | G28: 29.2 | H28: 5.5 | O28: 43 | P28: 0.88 | Q28: 6 | R28: 0.12244898 | S28: 120 | T28: 10 | W28: 120
A29: 18 | B29: Butt et al., 2024 | C29: HT | D29: 30 | E29: at surgery | G29: 29.17 | H29: 5.03 | O29: 29 | P29: 0.97 | Q29: 1 | R29: 0.033333333 | S29: 60 | T29: 5 | W29: 60
A30: 18 | B30: Butt et al., 2024 | C30: PLT | D30: 30 | E30: at surgery | G30: 27.73 | H30: 4.14 | O30: 30 | P30: 1 | Q30: 0 | R30: 0 | S30: 60 | T30: 5 | W30: 60
A31: 19 | B31: Calvert et al., 2025 | C31: HT | D31: 55 | E31: at surgery | G31: 29.4 | H31: 7.7 | O31: 28 | P31: 0.51 | Q31: 27 | R31: 0.49090909 | S31: 24 | T31: 2 | W31: 24
A32: 19 | B32: Calvert et al., 2025 | C32: QT | D32: 57 | E32: at surgery | G32: 28.1 | H32: 8.2 | O32: 28 | P32: 0.49 | Q32: 29 | R32: 0.50877193 | S32: 24 | T32: 2 | W32: 24
A33: 23 | B33: Ejerhed et al., 2003 | C33: BPTB | D33: 32 | E33: at surgery | G33: 27.260431 | H33: 8.467 | I33: 14 | K33: 26 | M33: 49 | O33: 21 | P33: 0.66 | Q33: 11 | R33: 0.34375 | S33: 24 | T33: 2 | W33: 24
A34: 23 | B34: Ejerhed et al., 2003 | C34: HT | D34: 34 | E34: at surgery | G34: 30.769891 | H34: 10.52 | I34: 15 | K34: 29 | M34: 59 | O34: 25 | P34: 0.74 | Q34: 9 | R34: 0.26470588 | S34: 24 | T34: 2 | W34: 24
A35: 25 | B35: Eriksson et al., 2001 | C35: BPTB | D35: 59 | E35: at surgery | G35: 27 | H35: 6 | N35: Mean and SD for age were reported for both subgroups combined. | P35: 0 | R35: 0 | S35: 6.7 | T35: 0.6 | U35: 6.7 | V35: 0.9
A36: 25 | B36: Eriksson et al., 2001 | C36: HT | D36: 57 | E36: at surgery | G36: 27 | H36: 6 | P36: 0 | R36: 0 | S36: 6.7 | T36: 0.6 | U36: 6.7 | V36: 0.9
A37: 26 | B37: Feller & Webster, 2003 | C37: BPTB | D37: 31 | E37: at surgery | G37: 25.8 | H37: 6 | O37: 23 | P37: 0.74 | Q37: 8 | R37: 0.25806452 | S37: 36 | T37: 3 | W37: 36
A38: 26 | B38: Feller & Webster, 2003 | C38: HT | D38: 34 | E38: at surgery | G38: 26.3 | H38: 6 | O38: 24 | P38: 0.71 | Q38: 10 | R38: 0.29411765 | S38: 36 | T38: 3 | W38: 36
A39: 30 | B39: Gifstad et al., 2013 | C39: BPTB | D39: 41 | E39: at surgery | G39: 27 | H39: 6.74 | I39: 18 | M39: 49 | P39: 0 | R39: 0 | S39: 84 | T39: 7 | W39: 84
A40: 30 | B40: Gifstad et al., 2013 | C40: HT | D40: 36 | E40: at surgery | G40: 27 | H40: 6.779 | I40: 18 | M40: 49 | P40: 0 | R40: 0 | S40: 84 | T40: 7 | W40: 84
A41: 32 | B41: Guglielmetti et al., 2021 | C41: BPTB | D41: 31 | E41: at surgery | G41: 25.2 | H41: 5.48 | O41: 23 | P41: 0.74 | Q41: 8 | R41: 0.25806452 | S41: 24 | T41: 2 | W41: 24
A42: 32 | B42: Guglielmetti et al., 2021 | C42: HT | D42: 31 | E42: at surgery | G42: 24.64 | H42: 5.33 | O42: 19 | P42: 0.61 | Q42: 12 | R42: 0.38709677 | S42: 24 | T42: 2 | W42: 24
A43: 33 | B43: Harilainen et al., 2006 | C43: BPTB | D43: 40 | E43: at surgery | P43: 0 | R43: 0 | S43: 60.6 | T43: 5.1 | U43: 60.6 | V43: =RANGE_SD(D43,W43,AA43) -> 7.42 | W43: 47 | Y43: 60 | AA43: 79
A44: 33 | B44: Harilainen et al., 2006 | C44: HT | D44: 39 | E44: at surgery | P44: 0 | R44: 0 | S44: 60.6 | T44: 5.1 | U44: 60.6 | V44: =RANGE_SD(D44,W44,AA44) -> 7.455 | W44: 47 | Y44: 60 | AA44: 79
A45: 34 | B45: Heijne & Werner, 2010 | C45: BPTB | D45: 34 | E45: at surgery | G45: 29 | H45: 7 | O45: 22 | P45: 0.65 | Q45: 12 | R45: 0.35294118 | S45: 24.7 | T45: 2.1 | U45: 24.7 | V45: 1.2
A46: 34 | B46: Heijne & Werner, 2010 | C46: HT | D46: 34 | E46: at surgery | G46: 30 | H46: 9 | O46: 14 | P46: 0.41 | Q46: 20 | R46: 0.58823529 | S46: 24.7 | T46: 2.1 | U46: 24.7 | V46: 1.2
A47: 35 | B47: Holm et al., 2010 | C47: BPTB | D47: 28 | E47: at surgery | G47: 33.9 | H47: 6.2 | O47: 18 | P47: 0.64 | Q47: 10 | R47: 0.35714286 | S47: 10.2 | T47: 0.9 | U47: 10.2 | V47: 0.4
A48: 35 | B48: Holm et al., 2010 | C48: HT | D48: 29 | E48: at surgery | G48: 37.9 | H48: 9.1 | O48: 15 | P48: 0.52 | Q48: 14 | R48: 0.48275862 | S48: 10.7 | T48: 0.9 | U48: 10.7 | V48: 0.4
A49: 36 | B49: Horstmann et al., 2022 | C49: HT | D49: 27 | E49: at surgery | G49: 32.7 | H49: 11.4 | O49: 12 | P49: 0.44 | Q49: 15 | R49: 0.55555556 | S49: 24 | T49: 2 | W49: 24
A50: 36 | B50: Horstmann et al., 2022 | C50: QT | D50: 24 | E50: at surgery | G50: 24.1 | H50: 3.6 | O50: 21 | P50: 0.88 | Q50: 3 | R50: 0.125 | S50: 24 | T50: 2 | W50: 24
A51: 37 | B51: Ibrahim et al., 2005 | C51: BPTB | D51: 40 | E51: at surgery | G51: 22.3 | H51: 3.942 | I51: 17 | M51: 34 | O51: 40 | P51: 1 | Q51: 0 | R51: 0 | S51: 81 | T51: 6.8 | U51: 81 | V51: =RANGE_SD(D51,W51,AA51) -> 8.347 | W51: 60 | AA51: 96
A52: 37 | B52: Ibrahim et al., 2005 | C52: HT | D52: 46 | E52: at surgery | G52: 22.3 | H52: 3.844 | I52: 17 | M52: 34 | O52: 46 | P52: 1 | Q52: 0 | R52: 0 | S52: 81 | T52: 6.8 | U52: 81 | V52: =RANGE_SD(D52,W52,AA52) -> 8.141 | W52: 60 | AA52: 96
A53: 38 | B53: Iliopoulos et al., 2017 | C53: BPTB | D53: 10 | E53: at surgery | G53: 24.8 | H53: 5 | O53: 10 | P53: 1 | Q53: 0 | R53: 0 | S53: 9 | T53: 0.8 | W53: 9
A54: 38 | B54: Iliopoulos et al., 2017 | C54: HT | D54: 10 | E54: at surgery | G54: 26.7 | H54: 7.2 | O54: 10 | P54: 1 | Q54: 0 | R54: 0 | S54: 9 | T54: 0.8 | W54: 9
A55: 41 | B55: Jansson et al., 2003 | C55: BPTB | D55: 43 | E55: at surgery | N55: Mean and SD for age was not reported. | P55: 0 | R55: 0 | S55: 24 | T55: 2 | U55: 24 | W55: 21 | AA55: 38
A56: 41 | B56: Jansson et al., 2003 | C56: HT | D56: 46 | E56: at surgery | N56: Mean and SD for age was not reported. | P56: 0 | R56: 0 | S56: 24 | T56: 2 | U56: 24 | W56: 21
A57: 43 | B57: Kautzner et al., 2015 | C57: BPTB | D57: 74 | E57: at surgery | G57: 26 | H57: 6.275 | I57: 17 | M57: 47 | O57: 0 | P57: 0 | Q57: 74 | R57: 1 | S57: 24 | T57: 2 | W57: 24
A58: 43 | B58: Kautzner et al., 2015 | C58: HT | D58: 73 | E58: at surgery | G58: 26 | H58: 6.288 | I58: 17 | M58: 47 | O58: 0 | P58: 0 | Q58: 73 | R58: 1 | S58: 24 | T58: 2 | W58: 24
A59: 44 | B59: Komzak et al., 2022 | C59: BPTB | D59: 36 | E59: at surgery | G59: 31 | H59: 9.459 | I59: 15 | M59: 55 | O59: 23 | P59: 0.64 | Q59: 17 | R59: 0.47222222 | S59: 28 | T59: 2.3 | U59: 28 | V59: =RANGE_SD(D59,W59,AA59) -> 2.128 | W59: 24 | AA59: 33
A60: 44 | B60: Komzak et al., 2022 | C60: QT | D60: 36 | E60: at surgery | G60: 29.8 | H60: 9.459 | I60: 15 | M60: 55 | O60: 21 | P60: 0.58 | Q60: 19 | R60: 0.52777778 | S60: 28 | T60: 2.3 | U60: 28 | V60: =RANGE_SD(D60,W60,AA60) -> 2.128 | W60: 24 | AA60: 33
A61: 45 | B61: Konrads et al., 2016 | C61: BPTB | D61: 31 | E61: at surgery | G61: 29.8 | H61: 6.33 | I61: 18 | M61: 44 | O61: 22 | P61: 0.71 | Q61: 9 | R61: 0.29032258 | S61: 120 | T61: 10 | W61: 120
A62: 45 | B62: Konrads et al., 2016 | C62: HT | D62: 31 | E62: at surgery | G62: 29.8 | H62: 6.33 | I62: 18 | M62: 44 | O62: 23 | P62: 0.74 | Q62: 8 | R62: 0.25806452 | S62: 120 | T62: 10 | W62: 120
A63: 46 | B63: Laoruengthana et al., 2009 | C63: BPTB | D63: 15 | E63: at surgery | G63: 29.93 | H63: 8.911 | I63: 16 | M63: 47 | P63: 0 | R63: 0 | S63: 19 | T63: 1.6 | U63: 19
A64: 46 | B64: Laoruengthana et al., 2009 | C64: HT | D64: 13 | E64: at surgery | G64: 28.65 | H64: 9.265 | I64: 16 | M64: 47 | P64: 0 | R64: 0 | S64: 19 | T64: 1.6 | U64: 19
A65: 47 | B65: Lawhorn et al., 2012 | C65: HT | D65: 44 | E65: at surgery | G65: 32 | H65: 8.433 | I65: 16.4 | M65: 53.4 | O65: 32 | P65: 0.73 | Q65: 22 | R65: 0.5 | S65: 24 | T65: 2 | W65: 24
A66: 47 | B66: Lawhorn et al., 2012 | C66: TA | D66: 48 | E66: at surgery | G66: 33 | H66: 8.305 | I66: 16.4 | M66: 53.4 | O66: 38 | P66: 0.79 | Q66: 10 | R66: 0.20833333 | S66: 24 | T66: 2 | W66: 24
A67: 49 | B67: Laxdal et al., 2005 | C67: BPTB | D67: 40 | E67: at surgery | G67: 28 | H67: 8.347 | I67: 16 | M67: 52 | P67: 0 | R67: 0 | S67: 26 | T67: 2.2 | U67: 26 | V67: 5.242 | W67: 20 | AA67: 43
